Workbook
Name AGRICULTURE: '.'!$AC$2:$AC$5
Name AGRICULTURE: PARAMETRAGE!$AC$2:$AC$5
Name ALIBORI: '.'!$P$2:$P$7
Name ALIBORI: PARAMETRAGE!$P$2:$P$7
Name Alimentation: PARAMETRAGE!$AD$4
Name ARTISANAT: '.'!$AE$2:$AE$9
Name ARTISANAT: PARAMETRAGE!$AE$2:$AE$9
Name Assistance: PARAMETRAGE!$AF$3
Name ATACORA: '.'!$Q$2:$Q$10
Name ATACORA: PARAMETRAGE!$Q$2:$Q$10
Name ATLANTIQUE: '.'!$R$2:$R$9
Name ATLANTIQUE: PARAMETRAGE!$R$2:$R$9
Name Auto_école: PARAMETRAGE!$AF$5
Name Autre: '.'!$AM$1
Name Autre: PARAMETRAGE!$AM$1
Name Autres_revenus: '.'!$CP$1:$CP$6
Name Autres_revenus: PARAMETRAGE!$CP$1:$CP$6
Name Boffa: PARAMETRAGE!$Q$9:$Q$16
Name BOKÉ: PARAMETRAGE!$Q$2:$Q$6
Name Boké_: PARAMETRAGE!$R$9:$R$18
Name BORGOU: '.'!$S$2:$S$9
Name BORGOU: PARAMETRAGE!$S$2:$S$9
Name Charges_exploitation: '.'!$K$1:$K$26
Name Charges_exploitation: PARAMETRAGE!$K$1:$K$26
Name Coiffure: PARAMETRAGE!$AE$4
Name COLLINES: '.'!$T$2:$T$7
Name COLLINES: PARAMETRAGE!$T$2:$T$7
Name COMMERCE: '.'!$AD$2:$AD$8
Name COMMERCE: PARAMETRAGE!$AD$2:$AD$8
Name Commercialisation: '.'!$AL$2:$AL$15
Name Commercialisation: PARAMETRAGE!$AL$2:$AL$16
Name CONAKRY: PARAMETRAGE!$P$2
Name Cordonnerie: PARAMETRAGE!$AE$7
Name Cosmétique: PARAMETRAGE!$AD$5
Name COUFFO: '.'!$U$2:$U$7
Name COUFFO: PARAMETRAGE!$U$2:$U$7
Name Département: '.'!$O$1:$O$12
Name Département: PARAMETRAGE!$O$1:$O$12
Name Divers_Service: PARAMETRAGE!$AF$4
Name DONGA: '.'!$V$2:$V$5
Name DONGA: PARAMETRAGE!$V$2:$V$5
Name École___Collège: PARAMETRAGE!$AF$6
Name Fabrication: PARAMETRAGE!$AG$2
Name FARANAH: PARAMETRAGE!$U$2:$U$5
Name FIVE: PARAMETRAGE!$ED$1:$ED$6
Name Formation: PARAMETRAGE!$AF$2
Name FOUR: PARAMETRAGE!$EC$1:$EC$5
Name Habillement: PARAMETRAGE!$AD$2
Name Historique: '.'!$L$8:$L$14
Name Historique: PARAMETRAGE!$L$8:$L$14
Name INDUSTRIE: '.'!$AG$2:$AG$3
Name INDUSTRIE: PARAMETRAGE!$AG$2:$AG$3
Name KANKAN: PARAMETRAGE!$V$2:$V$5
Name KINDIA: PARAMETRAGE!$R$2:$R$6
Name LABÉ: PARAMETRAGE!$T$2:$T$6
Name LITTORAL: '.'!$W$2
Name LITTORAL: PARAMETRAGE!$W$2
Name Maçonnerie: PARAMETRAGE!$AE$6
Name MAMOU: PARAMETRAGE!$S$2:$S$4
Name Mécanique: PARAMETRAGE!$AE$5

Sheet Modele

Sheet .
A1: 1 | B1: L’emprunteur fait partie de l’élite des producteurs; il se démarque par ses capacités de gestionnaire et une bonne solidité financière. Il maîtrise bien ses outils de production et est en mesure de donner à l’agent de crédit une information pertinente dans les délais requis. Il respecte ses engagements personnels et financiers. Bien qu’il n’existe aucune situation où les risques de défaut sont nuls, cette catégorie d’emprunteurs pourra disposer de conditions de crédit et d’encadrement favorables. | C1: Fonds de roulement | F1: Cout de production | G1: Chiffre d'affaire | K1: Loyer | L1: Excellent | M1: Sous-sous-secteur d'activité | N1: 1 | O1: Alibori | P1: ALIBORI | Q1: ATACORA | R1: ATLANTIQUE | S1: BORGOU | T1: COLLINES | U1: COUFFO | V1: DONGA | W1: LITTORAL | X1: MONO | Y1: OUÉMÉ | Z1: PLATEAU | AA1: ZOU | AC1: AGRICULTURE | AD1: COMMERCE | AE1: ARTISANAT | AF1: SERVICE | AG1: INDUSTRIE | AH1: Autre | AI1: Production_animale | AJ1: Production_végétale | AK1: Transformation | AL1: Commercialisation | AM1: Autre | AO1: Ratios | AV1: ='5. RESULTAT'!K36 -> Calculs | AX1: ='5. RESULTAT'!M36 -> Résultats | AY1: Excellent | AZ1: Bon ratio | BA1: Passable | BB1: insuffisant | BC1: Médiocre | BF1: =CONCATENATE("Le crédit dépasse le besoin réel de ",(BF4),"%") -> Le crédit dépasse le besoin réel de -67,49% | CM1: Prélèvement | CN1: =IF('5. RESULTAT'!D16="Prélèvement de l'exploitant",'5. RESULTAT'!K16,0) -> 0 | CP1: Revenus nets issus d'autres activités commerciales
A2: 2 | B2: Il est évident que l’emprunteur ayant une cote de risque basse constitue aussi pour la compétition une cible de choix; l’agent de crédit devra donc éviter de négliger cette clientèle. Avec cette clientèle, l'agent de crédit devra être proactif et orienté sur le maintien d’une bonne relation d’affaires et le service-conseil. | C2: Achat d'intrants | E2: Production végétale | F2: ='2. PROD'!I16 -> 922680000 | G2: ='2. PROD'!I24 -> 1700000000 | K2: Salaires employés | L2: Très bien | M2: Agrumes | N2: 2 | O2: Atacora | P2: Banikoara | Q2: Boukoumbé | R2: Abomey-Calavi | S2: Bembéréké | T2: Bantè | U2: Aplahoué | V2: Bassila | W2: Cotonou | X2: Athiémé | Y2: Adjarra | Z2: Ifangni | AA2: Abomey | AC2: Production_animale | AD2: Habillement | AE2: Menuiserie | AF2: Formation | AG2: Fabrication | AI2: Bovin | AJ2: Agrumes | AK2: Agrumes | AL2: Agrumes | AO2: Niveau de participation R ≤ 65 % | AQ2: Montant du crédit proposé | AV2: ='5. RESULTAT'!K37 -> 300000000 | AX2: ='5. RESULTAT'!M37 -> 0.32513981 | AY2: Excellent ratio. Le niveau de participation de financement est très faible. | AZ2: Bon ratio. Le niveau de participation de financement est acceptable. | BA2: Ratio passable. Le niveau de participation de financement est au seuil de la norme indiquée. | BB2: Le niveau de participation de financement dépasse la limite sugérée. | BC2: Attention, le niveau de participation de financement dépasse les dépenses prévues. | BE2: =IF('1. DEMANDE'!I54="Investissement",'3. BILAN'!J50,'3. BILAN'!J60) -> 922680000 | BF2: =IF('8. PROPOSITION'!M12>BE2,BF1,IF('8. PROPOSITION'!M12=BE2,"Le crédit couvre bien le besoin réel.","Attention, le crédit ne couvre pas le besoin réel.")) -> Attention, le crédit ne couvre pas le besoin réel. | BG2: =IF(AX2<=20%,AY2,IF(AND(AX2>20%,AX2<=50%),AZ2,IF(AND(AX2>50%,AX2<=65%),BA2,IF(AND(AX2>65%,AX2<=100%),BB2,IF(AX2>100%,BC2,""))))) -> Bon ratio. Le niveau de participation de financement est acceptable. | BH2: =CONCATENATE(BG2," ",BF2) -> Bon ratio. Le niveau de participation de financement est acceptable. Attention, le crédit ne couvre pas le besoin réel. | BI2: =IF('8. PROPOSITION'!M12="","",IF(BE2<0,"Attention ! Ce client n'a de besoin réel identifié - veuillez revoir les analyses",BH2)) -> Bon ratio. Le niveau de participation de financement est acceptable. Attention, le crédit ne couvre pas le besoin réel. | CM2: Prélèvement | CN2: =IF('5. RESULTAT'!D17="Prélèvement de l'exploitant",'5. RESULTAT'!K17,0) -> 0 | CP2: Salaires net (après déduction des engagements)
A3: 3 | B3: L’emprunteur faisant partie de cette catégorie ne constitue pas un risque dans la mesure où il est bien encadré. Sa maîtrise des outils de production et de gestion est bonne mais pourrait être améliorée. Puisque la majorité des emprunteurs font partie de cette catégorie, l’agent de crédit doit user de son jugement, s’appuyer sur son expérience et faire preuve de discernement afin de bien conseiller cette clientèle et appuyer son développement. | C3: Achats de petits outillages | E3: Production animale | F3: =ANIMAL!J24 -> 0 | G3: =ANIMAL!J32 -> 0 | K3: Fourniture de bureau | L3: Bien | M3: Anacarde | N3: 3 | O3: Atlantique | P3: Gogounou | Q3: Cobly | R3: Allada | S3: Kalalé | T3: Dassa-Zoumè | U3: Djakotomey | V3: Copargo | X3: Bopa | Y3: Adjohoun | Z3: Adja-Ouèrè | AA3: Agbangnizoun | AC3: Production_végétale | AD3: Restauration | AE3: Soudure | AF3: Assistance | AG3: Autre | AI3: Aquaculture | AJ3: Anacarde | AK3: Anacarde | AL3: Anacarde | AQ3: Total Dépenses d'exploitation | AV3: ='5. RESULTAT'!K38 -> 922680000 | AY3: <=20% | AZ3: >20 et <=50 | BA3: >50 et <=65 | BB3: >65 et <=100 | BC3: >100 | BF3: =(('8. PROPOSITION'!M12/BE2)-1)*100 -> -67.486019 | CM3: Prélèvement | CN3: =IF('5. RESULTAT'!D18="Prélèvement de l'exploitant",'5. RESULTAT'!K18,0) -> 0 | CP3: Prélèvement de l'exploitant
A4: 4 | B4: Il peut s’agir d’un emprunteur de longue date qui a connu une situation adverse avec qui il faut opérer un redressement ou d’un emprunteur qui est financièrement plus serré, mais qui démontre des aptitudes pour progresser vers les catégories supérieures ou qui est en expansion rapide. Bien que non obligatoire, le support d’un conseiller technique et de gestion pourrait être suggéré. Appuyez-vous sur les commentaires relatifs aux Ratios de décision pour valider votre recommandation. | C4: Investissement | E4: Transformation | F4: =TRFM1!J29+TRFM2!J29+TRFM3!J29 -> 0 | G4: =TRFM1!J37+TRFM2!J37+TRFM3!J37 -> 0 | K4: Publicité et promotion | L4: Passable | M4: Ananas | N4: 4 | O4: Borgou | P4: Kandi | Q4: Kérou | R4: Kpomassè | S4: N'Dali | T4: Glazoué | U4: Dogbo | V4: Djougou | X4: Comè | Y4: Aguégués | Z4: Kétou | AA4: Bohicon | AC4: Transformation | AD4: Alimentation | AE4: Coiffure | AF4: Service divers | AI4: Aviculture | AJ4: Ananas | AK4: Ananas | AL4: Ananas | AO4: Couverture de l'échéance R ≥ 1,5 | AQ4: Capacité de remboursement | AV4: ='5. RESULTAT'!K39 -> 2.6050533e+08 | AX4: ='5. RESULTAT'!M39 -> 1.439256 | AY4: >4 | AZ4: <=4 et >=2 | BA4: <2 et >=1,5 | BB4: <1,5 et >=1 | BC4: <1 | BF4: =ROUNDUP(BF3,2) -> -67.49 | BI4: =IF('8. PROPOSITION'!M12="","",IF('5. RESULTAT'!K32<0,"Attention ! La capacité de rembourssement est négative - veuillez échanger avec le client",BG5)) -> La couverture de l'échéance est acceptable mais trop juste. Le risque d'impayé est à prendre en compte. | CM4: Prélèvement | CN4: =IF('5. RESULTAT'!D19="Prélèvement de l'exploitant",'5. RESULTAT'!K19,0) -> 0 | CP4: Contribution d'autres personnes de la famille
A5: 5 | B5: En tant que professionnel, l’agent de crédit doit traiter tous les emprunteurs avec considération et professionnalisme. Avec les emprunteurs de cette catégorie, il devra donc considérer les demandes visant à améliorer la situation des emprunteurs tout en portant un suivi attentif à son dossier de crédit parce que celui-ci n’a pas une grande marge de manœuvre en cas de difficulté. Puisque les emprunteurs dans cette catégorie ne pourront obtenir des crédits importants, le rôle de l’agent de crédit sera donc de les conseiller afin qu’ils utilisent leur crédit judicieusement, qu’ils respectent leurs échéances et qu’ils améliorent leur maîtrise de la production. Ceci afin de pouvoir améliorer leur cote de risque et l’accès au financement. Les crédits devraient tous être adéquatement garantis et/ou avalisés. Toute autre mesure d’atténuation de risque telle que l’assurance agricole (si cela existe) devrait être obligatoire. | C5: Autre | E5: Commercialisation | F5: =COMM!J24 -> 0 | G5: =COMM!J32 -> 0 | K5: Téléphone / Internet | L5: Faible | M5: Aquaculture | N5: 5 | O5: Collines | P5: Karimama | Q5: Kouandé | R5: Ouidah | S5: Nikki | T5: Ouèssè | U5: Klouékanmè | V5: Ouaké | X5: Grand-Popo | Y5: Akpro-Missérété | Z5: Pobè | AA5: Covè | AC5: Commercialisation | AD5: Cosmétique | AE5: Mécanique | AF5: Auto-école | AI5: Caprin | AJ5: Arachide | AK5: Arachide | AL5: Arachide | AQ5: Service de la dette | AV5: ='5. RESULTAT'!K40 -> 181000000 | AY5: Excellent ratio. La couverture de l'échéance ou de service de la dette est confortable. | AZ5: Bon ratio. La couverture de l'échéance ou de service de la dette est bonne. | BA5: Ratio acceptable. La couverture de l'échéance ou de service de la dette est rassurante. | BB5: La couverture de l'échéance est acceptable mais trop juste. Le risque d'impayé est à prendre en compte. | BC5: Ratio trop faible - L'échéance ou le service de la dette n'est pas couvert. Forte probabilité de défaut. | BG5: =IF(AX4>4,AY5,IF(AND(AX4<=4,AX4>=2),AZ5,IF(AND(AX4<2,AX4>=1.5),BA5,IF(AND(AX4<1.5,AX4>=1),BB5,IF(AX4<1,BC5,""))))) -> La couverture de l'échéance est acceptable mais trop juste. Le risque d'impayé est à prendre en compte. | BI5: =IF('5. RESULTAT'!K33<0,"Attention ! La capacité de rembourssement est négative - veuillez échanger avec le client",IF('8. PROPOSITION'!M13="","",BG6)) | CM5: Prélèvement | CN5: =IF('5. RESULTAT'!D20="Prélèvement de l'exploitant",'5. RESULTAT'!K20,0) -> 0 | CP5: Revenus nets issus de la location (biens immobiliers et/matériels)
A6: 6 | B6: L’emprunteur (client) : - n'a pas d'expérience avérée dans le domaine - a de fortes probabilités d’être en défaut à court terme; - n’a pas de marge de manœuvre; - emprunte au-delà de sa capacité de remboursement. - a un mauvais historique de crédit; - a dans le passé, refusé certainement de collaborer afin de trouver des solutions à ses problèmes. Appuyez-vous sur les commentaires associés aux ratios de décision avant de valider le rejet de cette demande de crédit. | F6: =IF(OR('1. DEMANDE'!G30="COMMERCE",'1. DEMANDE'!G30="SERVICE"),F5,IF('1. DEMANDE'!R30="Production_végétale",F2,IF('1. DEMANDE'!R30="Production_animale",F3,IF(OR('1. DEMANDE'!R30="Transformation",'1. DEMANDE'!G30="ARTISANAT",'1. DEMANDE'!G30="INDUSTRIE"),F4,IF('1. DEMANDE'!R30="Commercialisation",F5,0))))) -> 922680000 | G6: =IF(OR('1. DEMANDE'!G30="COMMERCE",'1. DEMANDE'!G30="SERVICE"),G5,IF('1. DEMANDE'!R30="Production_végétale",G2,IF('1. DEMANDE'!R30="Production_animale",G3,IF(OR('1. DEMANDE'!R30="Transformation",'1. DEMANDE'!G30="ARTISANAT",'1. DEMANDE'!G30="INDUSTRIE"),G4,IF('1. DEMANDE'!R30="Commercialisation",G5,0))))) -> 1700000000 | K6: Communication | L6: Très faible | M6: Pêche | N6: 6 | O6: Couffo | P6: Malanville | Q6: Matéri | R6: Sô-Ava | S6: Parakou | T6: Savalou | U6: Lalo | X6: Houéyogbé | Y6: Avrankou | Z6: Sakété | AA6: Djidja | AD6: Mercerie | AE6: Maçonnerie | AF6: École - Collège | AI6: Ovin | AJ6: Coton | AK6: Coton | AL6: Igname | AO6: Ratio de fonds de roulement R ≥ 1,5 | AQ6: Actif à court terme | AV6: ='5. RESULTAT'!K41 -> 56000000 | AX6: ='5. RESULTAT'!M41 -> 2.8 | AY6: >4 | AZ6: <=4 et >=2 | BA6: <2 et >=1,5 | BB6: <1,5 et >=1 | BC6: <1 | BI6: =IF('8. PROPOSITION'!M12="","",BG7) -> Bon ratio. Les actifs à court terme surpassent les dettes à moins d'un an et dégagent un surplus important. | CM6: Prélèvement | CN6: =IF('5. RESULTAT'!D21="Prélèvement de l'exploitant",'5. RESULTAT'!K21,0) -> 0 | CP6: Autres sources de revenus
K7: Électricité | M7: Arachide | N7: 7 | O7: Donga | P7: Segbana | Q7: Natitingou | R7: Toffo | S7: Pèrèrè | T7: Savè | U7: Toviklin | X7: Lokossa | Y7: Bonou | AA7: Ouinhi | AD7: Vaisselle -Émaux | AE7: Cordonnerie | AF7: Autre | AI7: Pêche | AJ7: Igname | AK7: Igname | AL7: Maïs | AQ7: Passif à court terme | AV7: ='5. RESULTAT'!K42 -> 20000000 | AY7: Excellent ratio. Il existe un fonds de roulement conséquent permettant de faire tourner l'activité. | AZ7: Bon ratio. Les actifs à court terme surpassent les dettes à moins d'un an et dégagent un surplus important. | BA7: Bon ratio. Les actifs à court terme surpassent les dettes à moins d'un an et dégagent un surplus important. | BB7: Ratio passable. Les actifs à court terme surpassent légèrement les dettes à moins d'un an. Risque d'insuffisance du fonds de roulement. | BC7: Ratio trop faible - Fonds de roulement négatif. Nécessité de renforcer l'exploitation. | BG7: =IF(AX6>4,AY7,IF(AND(AX6<=4,AX6>=2),AZ7,IF(AND(AX6<2,AX6>=1.5),BA7,IF(AND(AX6<1.5,AX6>=1),BB7,IF(AX6<1,BC7,""))))) -> Bon ratio. Les actifs à court terme surpassent les dettes à moins d'un an et dégagent un surplus important. | BI7: =IF('5. RESULTAT'!K35<0,"Attention ! La capacité de rembourssement est négative - veuillez échanger avec le client",IF('8. PROPOSITION'!M15="","",BG8)) | CM7: Prélèvement | CN7: =IF('5. RESULTAT'!D22="Prélèvement de l'exploitant",'5. RESULTAT'!K22,0) -> 0
K8: Eau | L8: Nouveau Client | M8: Aviculture | O8: Littoral | Q8: Pehonko | R8: Tori-Bossito | S8: Sinendé | Y8: Dangbo | AA8: Za-Kpota | AD8: Autre | AE8: Coiffure | AI8: Pisciculture | AJ8: Maïs | AK8: Maïs | AL8: Mangue | AO8: Ratio de solvabilité R ≤ 0,5 | AQ8: Dettes totales | AV8: ='5. RESULTAT'!K43 -> 20000000 | AX8: ='5. RESULTAT'!M43 -> 0.017050298 | AY8: <0,1 | AZ8: >=0,1 et<=0,5 | BA8: >=0,1 et<=0,5 | BB8: >=0,5 et<=1 | BC8: >1 | CM8: Prélèvement | CN8: =IF('5. RESULTAT'!D23="Prélèvement de l'exploitant",'5. RESULTAT'!K23,0) -> 0
K9: Assurances | L9: Excellent | M9: Coton | O9: Mono | Q9: Tanguiéta | R9: Zè | S9: Tchaourou | Y9: Porto-Novo | AA9: Zagnanado | AE9: Autre | AI9: Autre | AJ9: Mangue | AK9: Mangue | AL9: Manioc | AQ9: Fonds propres | AV9: ='5. RESULTAT'!K44 -> 1173000000 | AY9: Excellent ratio de solvabilité. Les dettes de l'entreprise sont très faibles par rapport aux fonds propres | AZ9: La norme de solvabilité est respectée. Les dettes de l'entreprise sont faibles par rapport aux fonds propres | BB9: La norme de solvabilité n'est pas respectée. Les dettes de l'entreprise sont élevés et s'étendent vers le niveau de fonds propres | BC9: Les dettes de l'entreprise sont très élevées et dépassent le niveau de fonds propres. L'entreprise n'est pas solvable. | BF9: =IF('3. BILAN'!I37<0,"Attention, les fonds propres sont négatifs. Il faut échanger avec le client.",'.'!BG9) -> Excellent ratio de solvabilité. Les dettes de l'entreprise sont très faibles par rapport aux fonds propres | BG9: =IF(AX8<0.1,AY9,IF(AND(AX8>=0.1,AX8<=0.5),AZ9,IF(AND(AX8>0.5,AX8<=1),BB9,IF(AX8>1,BC9,"")))) -> Excellent ratio de solvabilité. Les dettes de l'entreprise sont très faibles par rapport aux fonds propres | BI9: =IF('8. PROPOSITION'!M12="","",BF9) -> Excellent ratio de solvabilité. Les dettes de l'entreprise sont très faibles par rapport aux fonds propres | CM9: Prélèvement | CN9: =IF('5. RESULTAT'!D24="Prélèvement de l'exploitant",'5. RESULTAT'!K24,0) -> 0
K10: Frais de transport | L10: Très bien | M10: Bovin/Ovin/Caprin | O10: Ouémé | Q10: Toucountouna | Y10: Sèmè-Kpodji | AA10: Zogbodomey | AJ10: Manioc | AK10: Manioc | AL10: Maraîchage | AO10: Ratio de liquidité immédiate R ≥ 1 | AQ10: Trésorerie disponible | AV10: ='5. RESULTAT'!K45 -> 36000000 | AX10: ='5. RESULTAT'!M45 -> 1.8 | AY10: >4 | AZ10: <=4 et >=2 | BA10: <2 et >=1 | BB10: <1 et >=0,75 | BC10: <075 | CM10: Prélèvement | CN10: =IF('5. RESULTAT'!D25="Prélèvement de l'exploitant",'5. RESULTAT'!K25,0) -> 0
K11: Entretien et réparation | L11: Bien | M11: Igname | O11: Plateau | AJ11: Maraîchage | AK11: Niébé | AL11: Niébé | AQ11: Passif à court terme | AV11: ='5. RESULTAT'!K46 -> 20000000 | AY11: Excellent ratio. Les "dettes à moins d'un an" peuvent être réglées facilement. | AZ11: Très bon ratio. La trésorerie et les créances sont assez importantes pour régler les dettes à moins d'un an. | BA11: Ratio respectant la norme. Les dettes à moins d'un an seront réglées. | BB11: Ratio ne respectant pas la norme. Des difficultés subsistent pour le règlement des dettes à moins d'un an. | BC11: Ratio hors norme. L'entreprise peut être en difficulté et doit compter sur la vente de ses stocks pour régler ses dettes à court terme. | BG11: =IF(AX10>4,AY11,IF(AND(AX10<=4,AX10>=2),AZ11,IF(AND(AX10<2,AX10>=1),BA11,IF(AND(AX10<1,AX10>=0.75),BB11,IF(AX10<0.75,BC11,""))))) -> Ratio respectant la norme. Les dettes à moins d'un an seront réglées. | BI11: =IF('8. PROPOSITION'!M12="","",BG11) -> Ratio respectant la norme. Les dettes à moins d'un an seront réglées. | CM11: Prélèvement | CN11: =IF('5. RESULTAT'!D26="Prélèvement de l'exploitant",'5. RESULTAT'!K26,0) -> 0
B12: Critères | C12: Cote de risque (1 à 6) | D12: Zone de risque maximun (proche de 6) | F12: Zone de risque maximun (proche de 6) | G12: Zone de risque maximun (proche de 6) | H12: Zone de risque maximun (proche de 6) | I12: Zone de risque maximun (proche de 6) | K12: Carburant | L12: Passable | M12: Maïs | O12: Zou | AJ12: Niébé | AK12: Palmier à huile | AL12: Riz | AO12: Ratio d'endettement R < 65 % | AQ12: Dettes totales + Crédit proposé | AV12: ='5. RESULTAT'!K47 -> 320000000 | AX12: ='5. RESULTAT'!M47 -> 0.21433356 | AY12: <10 | AZ12: >=10<25 | BA12: >=25<75 | BB12: >75<=100 | BC12: >100 | CM12: Total | CN12: =CN1+CN2+CN3+CN4+CN5+CN6+CN7+CN8+CN9+CN10+CN11 -> 0
B13: ='7. RISQUE'!B13 -> A. Direction Compétences, expériences, qualité morale, stabilité sociale.. | C13: =IF('7. RISQUE'!$B$23="Veuillez noter tous les critères de risques !",0,'7. RISQUE'!H13) -> 1 | D13: 6 | E13: Zone de risque maximun (proche de 6) | F13: 4 | G13: 3 | H13: 2 | I13: 1 | K13: Frais douane | L13: Faible | M13: Manguier | T13: ='8. PROPOSITION'!M12 -> 300000000 | U13: =T13/'8. PROPOSITION'!M20 -> 100000000 | AJ13: Palmier à huile | AK13: Riz | AL13: Soja | AQ13: Actif total + Crédit proposé | AV13: ='5. RESULTAT'!K48 -> 1493000000 | AY13: Niveau d'endettement très faible pour l'entreprise. Elle peut profiter des crédits productifs pour sa croissance. | AZ13: Niveau d'endettement faible pour l'entreprise. Elle possède une bonne marge pour s'endetter davantage. | BA13: Niveau d'endettement acceptable. | BB13: Niveau d'endettement très élevé pour l'entreprise. | BC13: Surendettement de l'entreprise. Le nouveau crédit risque de plonger davantage l'entreprise | BG13: =IF(AX12<10%,AY13,IF(AND(AX12>=10%,AX12<25%),AZ13,IF(AND(AX12>=25%,AX12<65%),BA13,IF(AND(AX12>65%,AX12<=100%),BB13,IF(AX12>100%,BC13,""))))) -> Niveau d'endettement faible pour l'entreprise. Elle possède une bonne marge pour s'endetter davantage. | BI13: =IF('8. PROPOSITION'!M12="","",BG13) -> Niveau d'endettement faible pour l'entreprise. Elle possède une bonne marge pour s'endetter davantage.
B14: ='7. RISQUE'!B14 -> B. Historique de crédits et scoring de remboursement | C14: =IF('7. RISQUE'!$B$23="Veuillez noter tous les critères de risques !",0,'7. RISQUE'!H14) -> 4 | D14: 6 | E14: 5 | F14: 4 | G14: 3 | H14: 2 | I14: 1 | K14: Voyage ( Billet et hôtel) | L14: Très faible | M14: Manioc | AJ14: Riz | AK14: Soja | AL14: Sorgho | AO14: Ratio de consommation familiale 35% < R ≤ 65% | AQ14: Consommation familiale | AV14: ='5. RESULTAT'!K49 -> 450800000 | AX14: ='5. RESULTAT'!M49 -> 0.36581526 | AY14: <=35 | AZ14: >35<=65 | BB14: >75<=100 | BC14: >100
B15: ='7. RISQUE'!B15 -> C. Accès aux intrants | C15: =IF('7. RISQUE'!$B$23="Veuillez noter tous les critères de risques !",0,'7. RISQUE'!H15) -> 2 | D15: 6 | E15: 5 | F15: 4 | G15: 3 | H15: 2 | I15: 1 | K15: Frais bancaires | M15: Maraîchage | AJ15: Soja | AK15: Sorgho | AL15: Autre | AQ15: Revenus totaux | AV15: ='5. RESULTAT'!K50 -> 1232316000 | AY15: Le niveau de consommation du ménage de l'entrepreneur est très faible. Il faut rechercher les dépenses familiales cachées. | AZ15: Le niveau de consommation du ménage de l'entrepreneur est dans les normes. | BB15: Le niveau de consommation du ménage de l'entrepreneur est très élevé. Risque de détourner le crédit à des fins personnelles. | BC15: Niveau de consommation très élevé et dépasant l'ensemble des revenus de l'entrepreneur. Risque d'impayé très présent. | BF15: =IF('5. RESULTAT'!K29<0,"Le cumul des revenus de cet entrepreneur est négatif - Impossible de couvrir les dépenses familiales.",BG15) -> Le niveau de consommation du ménage de l'entrepreneur est dans les normes. | BG15: =IF(AX14<=35%,AY15,IF(AND(AX14>35%,AX14<=65%),AZ15,IF(AND(AX14>65%,AX14<=100%),BB15,IF(AX14>100%,BC15,"")))) -> Le niveau de consommation du ménage de l'entrepreneur est dans les normes. | BI15: =IF('8. PROPOSITION'!M12="","",BF15) -> Le niveau de consommation du ménage de l'entrepreneur est dans les normes.
B16: ='7. RISQUE'!B16 -> D. Accès et position dans le marché | C16: =IF('7. RISQUE'!$B$23="Veuillez noter tous les critères de risques !",0,'7. RISQUE'!H16) -> 3 | D16: 6 | E16: 5 | F16: 4 | G16: 3 | H16: 2 | I16: 1 | K16: Intérêts sur emprunts | M16: Niébé | AJ16: Sorgho | AK16: Autre | AO16: Ratio de dependance des autres revenus R ≤ 50% | AQ16: Autres revenus | AV16: ='5. RESULTAT'!K51 -> 454996000 | AX16: ='5. RESULTAT'!M51 -> 0.36922023 | AY16: <0 | AZ16: =0 -> 0 | BA16: >0<=50 | BB16: >50<100 | BC16: >100 | BI16: =IF('8. PROPOSITION'!M13="","",BF16)
B17: ='7. RISQUE'!B17 -> E. Qualité des actifs de l'entreprise/exploitation | C17: =IF('7. RISQUE'!$B$23="Veuillez noter tous les critères de risques !",0,'7. RISQUE'!H17) -> 3 | D17: 6 | E17: 5 | F17: 4 | G17: 3 | H17: 2 | I17: 1 | K17: Échéance autre crédit | M17: Palmier à huile | AJ17: Autre | AQ17: Revenus totaux | AV17: ='5. RESULTAT'!K52 -> 1232316000 | AY17: Le cumul des revenus de cet entrepreneur est négatif - L'excédent d'exploitation est déficitaire ou trop faible | AZ17: L'entrepreneur n'a pas d'autres sources de revenus. Aucune déclaration à cet effet. À vérifier | BA17: Ratio de dépendance aux autres revenus dans la norme. | BB17: L'entrepreneur dépend énormément des autres revenus. Vérifier la rentabilité de l'activité à financer. | BC17: Les autres revenus sont très importants dans la capacité financière du client. Vérifier la rentabilité réelle de l'activité. | BF17: =IF('5. RESULTAT'!K29<0,"Le cumul des revenus de cet entrepreneur est négatif - L'excédent d'exploitation est déficitaire ou trop faible.",BG17) -> Ratio de dépendance aux autres revenus dans la norme. | BG17: =IF(AX16<0%,AY17,IF(AX16=0%,AZ17,IF(AND(AX16>0%,AX16<=50%),BA17,IF(AND(AX16>50%,AX16<=100%),BB17,IF(AX16>100%,BC17,""))))) -> Ratio de dépendance aux autres revenus dans la norme. | BI17: =IF('8. PROPOSITION'!M12="","",BG17) -> Ratio de dépendance aux autres revenus dans la norme.
B18: ='7. RISQUE'!B18 -> F. Production et Exploitation | C18: =IF('7. RISQUE'!$B$23="Veuillez noter tous les critères de risques !",0,'7. RISQUE'!H18) -> 6 | D18: 6 | E18: 5 | F18: 4 | G18: 3 | H18: 2 | I18: 1 | K18: Impôts - Taxes et permis | M18: Riz
B19: ='7. RISQUE'!B19 -> G. Environnement | C19: =IF('7. RISQUE'!$B$23="Veuillez noter tous les critères de risques !",0,'7. RISQUE'!H19) -> 2 | D19: 6 | E19: 5 | F19: 4 | G19: 3 | H19: 2 | I19: 1 | K19: Réparation et maintenance | M19: Soja
B20: ='7. RISQUE'!B20 -> H. Capacité de remboursement, Solvabilité et niveau d'endettement | C20: =IF('7. RISQUE'!$B$23="Veuillez noter tous les critères de risques !",0,'7. RISQUE'!H20) -> 3 | D20: 6 | E20: 5 | F20: 4 | G20: 3 | H20: 2 | I20: 1 | K20: Amortissement | M20: Sorgho
E21: 5 | K21: Provisions | M21: Autre
K22: Prélèvement de l'exploitant
K23: Honoraires professionnels
K24: Eau, électricté, téléphone
K25: Autre
C32: FICHE D'ANALYSE DES DEMANDES DE CRÉDITS AGRICOLES
C36: Une proposition de Développement International Desjardins
C38: Adapatation (Guinée)
C39: Août_2022

Sheet PARAMETRAGE
A1: 1 | B1: L’emprunteur fait partie de l’élite des producteurs; il se démarque par ses capacités de gestionnaire et une bonne solidité financière. Il maîtrise bien ses outils de production et est en mesure de donner à l’agent de crédit une information pertinente dans les délais requis. Il respecte ses engagements personnels et financiers. Bien qu’il n’existe aucune situation où les risques de défaut sont nuls, cette catégorie d’emprunteurs pourra disposer de conditions de crédit et d’encadrement favorables. | C1: Fonds de roulement | F1: Cout de production | G1: Chiffre d'affaire | K1: Loyer | L1: Excellent | M1: Sous-sous-secteur d'activité | N1: A | O1: Alibori | P1: CONAKRY | Q1: BOKÉ | R1: KINDIA | S1: MAMOU | T1: LABÉ | U1: FARANAH | V1: KANKAN | W1: NZÉRÉKORÉ | AC1: AGRICULTURE | AD1: COMMERCE | AE1: ARTISANAT | AF1: SERVICE | AG1: INDUSTRIE | AH1: Autre | AI1: Production_animale | AJ1: Production_végétale | AK1: Transformation | AL1: Commercialisation | AM1: Autre | AO1: Ratios | AV1: ='5. RESULTAT'!K36 -> Calculs | AX1: ='5. RESULTAT'!M36 -> Résultats | AY1: Excellent | AZ1: Bon ratio | BA1: Passable | BB1: insuffisant | BC1: Médiocre | BF1: =CONCATENATE("Le crédit dépasse le besoin réel de ",(BF4),"%") -> Le crédit dépasse le besoin réel de -67,49% | CM1: Prélèvement | CN1: =IF('5. RESULTAT'!D16="Prélèvement de l'exploitant",'5. RESULTAT'!K16,0) -> 0 | CP1: Revenus nets issus d'autres activités commerciales | CS1: =IF('8. PROPOSITION'!M20="",0,CU1) -> 300000000 | CT1: ='8. PROPOSITION'!M12/'8. PROPOSITION'!M20 -> 100000000 | CU1: ='8. PROPOSITION'!M12+EH12 -> 300000000 | DY1: ='1. DEMANDE'!V50 -> 8 | DZ1: Mensuelle | EA1: Unique | EB1: Unique | EC1: Unique | ED1: Unique | EE1: Unique | EI1: Montant Prélevé provision | EJ1: Montant prélevé Amortissement
A2: 2 | B2: Il est évident que l’emprunteur ayant une cote de risque basse constitue aussi pour la compétition une cible de choix; l’agent de crédit devra donc éviter de négliger cette clientèle. Avec cette clientèle, l'agent de crédit devra être proactif et orienté sur le maintien d’une bonne relation d’affaires et le service-conseil. | C2: Achat d'intrants | E2: Production végétale | F2: ='.'!F2 -> 922680000 | G2: ='.'!G2 -> 1700000000 | K2: Salaires employés | L2: Très bien | M2: Agrumes | N2: B | O2: Atacora | P2: Conakry | Q2: Boffa | R2: Coyah | S2: Dalaba | T2: Koubia | U2: Dabola | V2: Kankan | W2: Beyla | AC2: Production_animale | AD2: Habillement | AE2: Menuiserie | AF2: Formation | AG2: Fabrication | AI2: Bovin | AJ2: Agrumes | AK2: Agrumes | AL2: Agrumes | AO2: Niveau de participation R ≤ 65 % | AQ2: Montant du crédit proposé | AV2: ='5. RESULTAT'!K37 -> 300000000 | AX2: ='5. RESULTAT'!M37 -> 0.32513981 | AY2: Excellent ratio. Le niveau de participation de financement est très faible. | AZ2: Bon ratio. Le niveau de participation de financement est acceptable. | BA2: Ratio passable. Le niveau de participation de financement est au seuil de la norme indiquée. | BB2: Le niveau de participation de financement dépasse la limite sugérée. | BC2: Attention, le niveau de participation de financement dépasse les dépenses prévues. | BE2: =IF('1. DEMANDE'!I54="Investissement",'3. BILAN'!J50,'3. BILAN'!J60) -> 922680000 | BF2: =IF('8. PROPOSITION'!M12>BE2,BF1,IF('8. PROPOSITION'!M12=BE2,"Le crédit couvre bien le besoin réel.","Attention, le crédit ne couvre pas le besoin réel.")) -> Attention, le crédit ne couvre pas le besoin réel. | BG2: =IF(AX2<=20%,AY2,IF(AND(AX2>20%,AX2<=50%),AZ2,IF(AND(AX2>50%,AX2<=65%),BA2,IF(AND(AX2>65%,AX2<=100%),BB2,IF(AX2>100%,BC2,""))))) -> Bon ratio. Le niveau de participation de financement est acceptable. | BH2: =CONCATENATE(BG2," ",BF2) -> Bon ratio. Le niveau de participation de financement est acceptable. Attention, le crédit ne couvre pas le besoin réel. | BI2: =IF('8. PROPOSITION'!M12="","",IF(BE2<0,"Attention ! Ce client n'a de besoin réel identifié - veuillez revoir les analyses",BH2)) -> Bon ratio. Le niveau de participation de financement est acceptable. Attention, le crédit ne couvre pas le besoin réel. | CM2: Prélèvement | CN2: =IF('5. RESULTAT'!D17="Prélèvement de l'exploitant",'5. RESULTAT'!K17,0) -> 0 | CP2: Salaires net (après déduction des engagements) | CS2: =IF('8. PROPOSITION'!M20="",0,EH12) -> 0 | DY2: =IF(DY1=1,"ONE",IF(DY1=2,"TWO",IF(DY1=3,"THREE",IF(DY1=4,"FOUR",IF(DY1=5,"FOUR",IF(AND(DY1>5,DY1<12),"FIVE",IF(DY1>11,"SIX",""))))))) -> FIVE | EA2: Mensuelle | EB2: Mensuelle | EC2: Mensuelle | ED2: Mensuelle | EE2: Mensuelle | EH2: Ligne 1 | EI2: =IF('5. RESULTAT'!D16="Provisions",'5. RESULTAT'!K16,0) -> 0 | EJ2: =IF('5. RESULTAT'!D16="Amortissement ",'5. RESULTAT'!K16,0) -> 0
A3: 3 | B3: L’emprunteur faisant partie de cette catégorie ne constitue pas un risque dans la mesure où il est bien encadré. Sa maîtrise des outils de production et de gestion est bonne mais pourrait être améliorée. Puisque la majorité des emprunteurs font partie de cette catégorie, l’agent de crédit doit user de son jugement, s’appuyer sur son expérience et faire preuve de discernement afin de bien conseiller cette clientèle et appuyer son développement. | C3: Achats de petits outillages | E3: Production animale | F3: ='.'!F3 -> 0 | G3: ='.'!G3 -> 0 | K3: Fourniture de bureau | L3: Bien | M3: Anacarde | N3: C | O3: Atlantique | Q3: Boké_ | R3: Dubréka | S3: Mamou | T3: Labé | U3: Dinguiraye | V3: Kérouane | W3: Guéckédou | AC3: Production_végétale | AD3: Restauration | AE3: Soudure | AF3: Assistance | AG3: Autre | AI3: Aquaculture | AJ3: Anacarde | AK3: Anacarde | AL3: Anacarde | AQ3: Total Dépenses d'exploitation | AV3: ='5. RESULTAT'!K38 -> 922680000 | AY3: <=20% | AZ3: >20 et <=50 | BA3: >50 et <=65 | BB3: >65 et <=100 | BC3: >100 | BF3: =(('8. PROPOSITION'!M12/BE2)-1)*100 -> -67.486019 | CM3: Prélèvement | CN3: =IF('5. RESULTAT'!D18="Prélèvement de l'exploitant",'5. RESULTAT'!K18,0) -> 0 | CP3: Prélèvement de l'exploitant | EA3: Bimestrielle | EB3: Bimestrielle | EC3: Bimestrielle | ED3: Bimestrielle | EE3: Bimestrielle | EH3: Ligne 2 | EI3: =IF('5. RESULTAT'!D17="Provisions",'5. RESULTAT'!K17,0) -> 0 | EJ3: =IF('5. RESULTAT'!D17="Amortissement ",'5. RESULTAT'!K17,0) -> 0
A4: 4 | B4: Il faut être prudent avec ce genre de client. Soit il est nouveau, soit il s’agir d’un emprunteur de longue date qui a connu une situation adverse avec qui il faut opérer un redressement ou d’un emprunteur qui est financièrement plus serré, mais qui démontre des aptitudes pour progresser. Bien que non obligatoire, le support d’un conseiller technique et/ou de gestion pourrait être suggéré. Appuyez-vous sur les commentaires relatifs aux Ratios de décision pour valider votre recommandation. | C4: Investissement | E4: Transformation | F4: ='.'!F4 -> 0 | G4: ='.'!G4 -> 0 | K4: Publicité et promotion | L4: Passable | M4: Ananas | N4: D | O4: Borgou | Q4: Fria | R4: Forécariah | S4: Pita | T4: Lélouma | U4: Faranah | V4: Kouroussa | W4: Lola | AC4: Transformation | AD4: Alimentation | AE4: Coiffure | AF4: Divers_Service | AI4: Aviculture | AJ4: Ananas | AK4: Ananas | AL4: Ananas | AO4: Couverture de l'échéance R ≥ 1,5 | AQ4: Capacité de remboursement | AV4: ='5. RESULTAT'!K39 -> 2.6050533e+08 | AX4: ='5. RESULTAT'!M39 -> 1.439256 | AY4: >4 | AZ4: <=4 et >=2 | BA4: <2 et >=1,5 | BB4: <1,5 et >=1 | BC4: <1 | BF4: =ROUNDUP(BF3,2) -> -67.49 | BI4: =IF('8. PROPOSITION'!M12="","",IF('5. RESULTAT'!K32<0,"Attention ! La capacité de remboursement est négative - veuillez échanger avec le client",BG5)) -> La couverture de l'échéance est acceptable mais trop juste. Le risque d'impayé est à prendre en compte. | CM4: Prélèvement | CN4: =IF('5. RESULTAT'!D19="Prélèvement de l'exploitant",'5. RESULTAT'!K19,0) -> 0 | CP4: Contribution d'autres personnes de la famille | EB4: Trimestrielle | EC4: Trimestrielle | ED4: Trimestrielle | EE4: Trimestrielle | EH4: Ligne 3 | EI4: =IF('5. RESULTAT'!D18="Provisions",'5. RESULTAT'!K18,0) -> 0 | EJ4: =IF('5. RESULTAT'!D18="Amortissement ",'5. RESULTAT'!K18,0) -> 0
A5: 5 | B5: En tant que professionnel, l’agent de crédit doit traiter tous les emprunteurs avec considération et professionnalisme. Avec les emprunteurs de cette catégorie, il devra donc considérer les demandes visant à améliorer la situation des emprunteurs tout en portant un suivi attentif à son dossier de crédit parce que celui-ci n’a pas une grande marge de manœuvre en cas de difficulté. Puisque les emprunteurs dans cette catégorie ne pourront obtenir des crédits importants, le rôle de l’agent de crédit sera donc de les conseiller afin qu’ils utilisent leur crédit judicieusement, qu’ils respectent leurs échéances et qu’ils améliorent leur maîtrise de la production. Ceci afin de pouvoir améliorer leur cote de risque et l’accès au financement. Les crédits devraient tous être adéquatement garantis et/ou avalisés. Pour un crédit agricole, toute autre mesure d’atténuation de risque telle que l’assurance agricole (si cela existe) devrait être obligatoire. | C5: Autre | E5: Commercialisation | F5: ='.'!F5 -> 0 | G5: ='.'!G5 -> 0 | K5: Téléphone / Internet | L5: Faible | M5: Aquaculture | N5: E | O5: Collines | Q5: Gaoual | R5: Kindia | T5: Mali | U5: Kissidougou | V5: Mandiana | W5: Macenta | AC5: Commercialisation | AD5: Cosmétique | AE5: Mécanique | AF5: Auto_école | AI5: Caprin | AJ5: Arachide | AK5: Arachide | AL5: Arachide | AQ5: Service de la dette | AV5: ='5. RESULTAT'!K40 -> 181000000 | AY5: Excellent ratio. La couverture de l'échéance ou de service de la dette est confortable. | AZ5: Bon ratio. La couverture de l'échéance ou de service de la dette est bonne. | BA5: Ratio acceptable. La couverture de l'échéance ou de service de la dette est rassurante. | BB5: La couverture de l'échéance est acceptable mais trop juste. Le risque d'impayé est à prendre en compte. | BC5: Ratio trop faible - L'échéance ou le service de la dette n'est pas couvert. Forte probabilité de défaut. | BG5: =IF(AX4>4,AY5,IF(AND(AX4<=4,AX4>=2),AZ5,IF(AND(AX4<2,AX4>=1.5),BA5,IF(AND(AX4<1.5,AX4>=1),BB5,IF(AX4<1,BC5,""))))) -> La couverture de l'échéance est acceptable mais trop juste. Le risque d'impayé est à prendre en compte. | BI5: =IF('5. RESULTAT'!K33<0,"Attention ! La capacité de rembourssement est négative - veuillez échanger avec le client",IF('8. PROPOSITION'!M13="","",BG6)) | CM5: Prélèvement | CN5: =IF('5. RESULTAT'!D20="Prélèvement de l'exploitant",'5. RESULTAT'!K20,0) -> 0 | CP5: Revenus nets issus de la location (biens immobiliers et/matériels) | CU5: ='5. RESULTAT'!K32/'8. PROPOSITION'!M20 -> 2.6050533e+08 | CV5: Montant disponible en tranche | EC5: Quadrimestre | ED5: Quadrimestre | EE5: Quadrimestre | EH5: Ligne 4 | EI5: =IF('5. RESULTAT'!D19="Provisions",'5. RESULTAT'!K19,0) -> 0 | EJ5: =IF('5. RESULTAT'!D19="Amortissement ",'5. RESULTAT'!K19,0) -> 0
A6: 6 | B6: L’emprunteur (client) : - n'a pas d'expérience avérée dans le domaine - a de fortes probabilités d’être en défaut à court terme; - n’a pas de marge de manœuvre; - emprunte au-delà de sa capacité de remboursement. - a un mauvais historique de crédit; - si ancien, a dans le passé, refusé certainement de collaborer afin de trouver des solutions à ses problèmes. Appuyez-vous sur les commentaires associés aux ratios de décision avant de valider le rejet de cette demande de crédit. | F6: ='.'!F6 -> 922680000 | G6: ='.'!G6 -> 1700000000 | K6: Communication | L6: Très faible | M6: Pêche | N6: F | O6: Couffo | Q6: Koundara | R6: Télimélé | T6: Tougué | W6: Nzérékoré | AD6: Mercerie | AE6: Maçonnerie | AF6: École_Collège | AI6: Ovin | AJ6: Coton | AK6: Coton | AL6: Igname | AO6: Ratio de fonds de roulement R ≥ 1,5 | AQ6: Actif à court terme | AV6: ='5. RESULTAT'!K41 -> 56000000 | AX6: ='5. RESULTAT'!M41 -> 2.8 | AY6: >4 | AZ6: <=4 et >=2 | BA6: <2 et >=1,5 | BB6: <1,5 et >=1 | BC6: <1 | BI6: =IF('8. PROPOSITION'!M12="","",BG7) -> Bon ratio. Les actifs à court terme surpassent les dettes à moins d'un an et dégagent un surplus important. | CM6: Prélèvement | CN6: =IF('5. RESULTAT'!D21="Prélèvement de l'exploitant",'5. RESULTAT'!K21,0) -> 0 | CP6: Autres sources de revenus | ED6: Semestrielle | EE6: Semestrielle | EH6: Ligne 5 | EI6: =IF('5. RESULTAT'!D20="Provisions",'5. RESULTAT'!K20,0) -> 0 | EJ6: =IF('5. RESULTAT'!D20="Amortissement ",'5. RESULTAT'!K20,0) -> 0
K7: Électricité | M7: Arachide | N7: G | O7: Donga | W7: Yomou | AD7: Vaisselle -Émaux | AE7: Cordonnerie | AF7: Autre | AI7: Pêche | AJ7: Igname | AK7: Igname | AL7: Maïs | AQ7: Passif à court terme | AV7: ='5. RESULTAT'!K42 -> 20000000 | AY7: Excellent ratio. Il existe un fonds de roulement conséquent permettant de faire tourner l'activité. | AZ7: Bon ratio. Les actifs à court terme surpassent les dettes à moins d'un an et dégagent un surplus important. | BA7: Bon ratio. Les actifs à court terme surpassent les dettes à moins d'un an et dégagent un surplus important. | BB7: Ratio passable. Les actifs à court terme surpassent légèrement les dettes à moins d'un an. Risque d'insuffisance du fonds de roulement. | BC7: Ratio trop faible - Fonds de roulement négatif. Nécessité de renforcer l'exploitation. | BG7: =IF(AX6>4,AY7,IF(AND(AX6<=4,AX6>=2),AZ7,IF(AND(AX6<2,AX6>=1.5),BA7,IF(AND(AX6<1.5,AX6>=1),BB7,IF(AX6<1,BC7,""))))) -> Bon ratio. Les actifs à court terme surpassent les dettes à moins d'un an et dégagent un surplus important. | BI7: =IF('5. RESULTAT'!K32<0,"Attention ! La capacité de remboursement est négative - veuillez échanger avec le client",IF('8. PROPOSITION'!M15="","",BG8)) | CM7: Prélèvement | CN7: =IF('5. RESULTAT'!D22="Prélèvement de l'exploitant",'5. RESULTAT'!K22,0) -> 0 | EE7: Annuelle | EH7: Ligne 6 | EI7: =IF('5. RESULTAT'!D21="Provisions",'5. RESULTAT'!K21,0) -> 0 | EJ7: =IF('5. RESULTAT'!D21="Amortissement ",'5. RESULTAT'!K21,0) -> 0
K8: Eau | L8: Nouveau Client | M8: Aviculture | N8: H | O8: Littoral | Q8: Boffa | R8: Boké_ | AD8: Autre | AE8: Coiffure | AI8: Pisciculture | AJ8: Maïs | AK8: Maïs | AL8: Mangue | AO8: Ratio de solvabilité R ≤ 0,5 | AQ8: Dettes totales | AV8: ='5. RESULTAT'!K43 -> 20000000 | AX8: ='5. RESULTAT'!M43 -> 0.017050298 | AY8: <0,1 | AZ8: >=0,1 et<=0,5 | BA8: >=0,1 et<=0,5 | BB8: >=0,5 et<=1 | BC8: >1 | CM8: Prélèvement | CN8: =IF('5. RESULTAT'!D23="Prélèvement de l'exploitant",'5. RESULTAT'!K23,0) -> 0 | EH8: Ligne 7 | EI8: =IF('5. RESULTAT'!D22="Provisions",'5. RESULTAT'!K22,0) -> 0 | EJ8: =IF('5. RESULTAT'!D22="Amortissement ",'5. RESULTAT'!K22,0) -> 0
K9: Assurances | L9: Excellent | M9: Coton | N9: I | O9: Mono | Q9: Boffa-Centre | R9: Boké-Centre | S9: Dabiss · Kamsar · Kanfarandé · Kolaboui · Malapouyah · Sangaredi · Sansalé · Tanéné | AE9: Autre | AI9: Autre | AJ9: Mangue | AK9: Mangue | AL9: Manioc | AQ9: Fonds propres | AV9: ='5. RESULTAT'!K44 -> 1173000000 | AY9: Excellent ratio de solvabilité. Les dettes de l'entreprise sont très faibles par rapport aux fonds propres | AZ9: La norme de solvabilité est respectée. Les dettes de l'entreprise sont faibles par rapport aux fonds propres | BB9: Les dettes de l'entreprise sont élevées et risquent de s'étendre vers le niveau des fonds propres avec un nouveau crédit. | BC9: Les dettes de l'entreprise sont très élevées et dépassent le niveau de fonds propres. L'entreprise n'est pas solvable. | BF9: =IF('3. BILAN'!I37<0,"Attention, les fonds propres sont négatifs. Il faut échanger avec le client.",PARAMETRAGE!BG9) -> Excellent ratio de solvabilité. Les dettes de l'entreprise sont très faibles par rapport aux fonds propres | BG9: =IF(AX8<0.1,AY9,IF(AND(AX8>=0.1,AX8<=0.5),AZ9,IF(AND(AX8>0.5,AX8<=1),BB9,IF(AX8>1,BC9,"")))) -> Excellent ratio de solvabilité. Les dettes de l'entreprise sont très faibles par rapport aux fonds propres | BI9: =IF('8. PROPOSITION'!M12="","",BF9) -> Excellent ratio de solvabilité. Les dettes de l'entreprise sont très faibles par rapport aux fonds propres | CM9: Prélèvement | CN9: =IF('5. RESULTAT'!D24="Prélèvement de l'exploitant",'5. RESULTAT'!K24,0) -> 0 | DZ9: ONE | EA9: TWO | EB9: THREE | EC9: FOUR | ED9: FIVE | EE9: SIX | EH9: Ligne 8 | EI9: =IF('5. RESULTAT'!D23="Provisions",'5. RESULTAT'!K23,0) -> 0 | EJ9: =IF('5. RESULTAT'!D23="Amortissement ",'5. RESULTAT'!K23,0) -> 0
K10: Frais de transport | L10: Très bien | M10: Bovin/Ovin/Caprin | O10: Ouémé | Q10: Colia | R10: Bintimodiya | S10: Dabiss · Kamsar · Kanfarandé · Kolaboui · Malapouyah · Sangaredi · Sansalé · Tanéné | AJ10: Manioc | AK10: Manioc | AL10: Maraîchage | AO10: Ratio de liquidité immédiate R ≥ 1 | AQ10: Trésorerie disponible | AV10: ='5. RESULTAT'!K45 -> 36000000 | AX10: ='5. RESULTAT'!M45 -> 1.8 | AY10: >4 | AZ10: <=4 et >=2 | BA10: <2 et >=1 | BB10: <1 et >=0,75 | BC10: <075 | CM10: Prélèvement | CN10: =IF('5. RESULTAT'!D25="Prélèvement de l'exploitant",'5. RESULTAT'!K25,0) -> 0 | EH10: Ligne 9 | EI10: =IF('5. RESULTAT'!D24="Provisions",'5. RESULTAT'!K24,0) -> 0 | EJ10: =IF('5. RESULTAT'!D24="Amortissement ",'5. RESULTAT'!K24,0) -> 0
K11: Entretien et réparation | L11: Bien | M11: Igname | O11: Plateau | Q11: Douprou | R11: Dabiss | S11: Dabiss · Kamsar · Kanfarandé · Kolaboui · Malapouyah · Sangaredi · Sansalé · Tanéné | AJ11: Maraîchage | AK11: Niébé | AL11: Niébé | AQ11: Passif à court terme | AV11: ='5. RESULTAT'!K46 -> 20000000 | AY11: Excellent ratio. Les "dettes à moins d'un an" peuvent être réglées facilement. | AZ11: Très bon ratio. La trésorerie et les créances sont assez importantes pour régler les dettes à moins d'un an. | BA11: Ratio respectant la norme. Les dettes à moins d'un an seront réglées. | BB11: Ratio ne respectant pas la norme. Des difficultés subsistent pour le règlement des dettes à moins d'un an. | BC11: Ratio hors norme. L'entreprise peut être en difficulté et doit compter sur la vente de ses stocks pour régler ses dettes à court terme. | BG11: =IF(AX10>4,AY11,IF(AND(AX10<=4,AX10>=2),AZ11,IF(AND(AX10<2,AX10>=1),BA11,IF(AND(AX10<1,AX10>=0.75),BB11,IF(AX10<0.75,BC11,""))))) -> Ratio respectant la norme. Les dettes à moins d'un an seront réglées. | BI11: =IF('8. PROPOSITION'!M12="","",BG11) -> Ratio respectant la norme. Les dettes à moins d'un an seront réglées. | CM11: Prélèvement | CN11: =IF('5. RESULTAT'!D26="Prélèvement de l'exploitant",'5. RESULTAT'!K26,0) -> 0 | EH11: Ligne 10 | EI11: ='5. RESULTAT'!D25 -> 0 | EJ11: =IF('5. RESULTAT'!D25="Amortissement ",'5. RESULTAT'!K25,0) -> 0
B12: Critères | C12: Cote de risque (1 à 6) | D12: Zone de risque maximun (proche de 6) | E12: Zone de risque maximun (proche de 6) | F12: Zone de risque maximun (proche de 6) | G12: Zone de risque maximun (proche de 6) | H12: Zone de risque maximun (proche de 6) | I12: Zone de risque maximun (proche de 6) | K12: Carburant | L12: Passable | M12: Maïs | O12: Zou | Q12: Koba-Tatema | R12: Kamsar | S12: Dabiss · Kamsar · Kanfarandé · Kolaboui · Malapouyah · Sangaredi · Sansalé · Tanéné | AJ12: Niébé | AK12: Palmier à huile | AL12: Pomme de terre | AO12: Ratio d'endettement R < 65 % | AQ12: Dettes totales + Crédit proposé | AV12: ='5. RESULTAT'!K47 -> 320000000 | AX12: ='5. RESULTAT'!M47 -> 0.21433356 | AY12: <10 | AZ12: >=10<25 | BA12: >=25<75 | BB12: >75<=100 | BC12: >100 | CM12: Total | CN12: =CN1+CN2+CN3+CN4+CN5+CN6+CN7+CN8+CN9+CN10+CN11 -> 0 | EH12: =EI12+EJ12 -> 0 | EI12: =EI2+EI3+EI4+EI5+EI6+EI7+EI8+EI9+EI10+EI11 -> 0 | EJ12: =EJ2+EJ3+EJ4+EJ5+EJ6+EJ7+EJ8+EJ9+EJ10+EJ11 -> 0
B13: ='7. RISQUE'!B13 -> A. Direction Compétences, expériences, qualité morale, stabilité sociale.. | C13: =IF('7. RISQUE'!$B$23="Veuillez noter tous les critères de risques !",0,'7. RISQUE'!H13) -> 1 | D13: 6 | E13: 5 | F13: 4 | G13: 3 | H13: 2 | I13: 1 | K13: Frais douane | L13: Faible | M13: Manguier | Q13: Lisso | R13: Kanfarandé | S13: Dabiss · Kamsar · Kanfarandé · Kolaboui · Malapouyah · Sangaredi · Sansalé · Tanéné | AJ13: Palmier à huile | AK13: Pomme de terre | AL13: Riz | AQ13: Actif total + Crédit proposé | AV13: ='5. RESULTAT'!K48 -> 1493000000 | AY13: Niveau d'endettement très faible pour l'entreprise. Elle peut profiter des crédits productifs pour sa croissance. | AZ13: Niveau d'endettement faible pour l'entreprise. Elle possède une bonne marge pour s'endetter davantage. | BA13: Niveau d'endettement acceptable. | BB13: Niveau d'endettement très élevé pour l'entreprise. | BC13: Surendettement de l'entreprise. Le nouveau crédit risque de plonger davantage l'entreprise | BG13: =IF(AX12<10%,AY13,IF(AND(AX12>=10%,AX12<25%),AZ13,IF(AND(AX12>=25%,AX12<65%),BA13,IF(AND(AX12>65%,AX12<=100%),BB13,IF(AX12>100%,BC13,""))))) -> Niveau d'endettement faible pour l'entreprise. Elle possède une bonne marge pour s'endetter davantage. | BI13: =IF('8. PROPOSITION'!M12="","",BG13) -> Niveau d'endettement faible pour l'entreprise. Elle possède une bonne marge pour s'endetter davantage.
B14: ='7. RISQUE'!B14 -> B. Historique de crédits et scoring de remboursement | C14: =IF('7. RISQUE'!$B$23="Veuillez noter tous les critères de risques !",0,'7. RISQUE'!H14) -> 4 | D14: 6 | E14: 5 | F14: 4 | G14: 3 | H14: 2 | I14: 1 | K14: Voyage ( Billet et hôtel) | L14: Très faible | M14: Manioc | Q14: Mankountan | R14: Kolaboui | S14: Dabiss · Kamsar · Kanfarandé · Kolaboui · Malapouyah · Sangaredi · Sansalé · Tanéné | AJ14: Pomme de terre | AK14: Riz | AL14: Soja | AO14: Ratio de consommation familiale 35% < R ≤ 65% | AQ14: Consommation familiale | AV14: ='5. RESULTAT'!K49 -> 450800000 | AX14: ='5. RESULTAT'!M49 -> 0.36581526 | AY14: <=35 | AZ14: >35<=65 | BB14: >75<=100 | BC14: >100
B15: ='7. RISQUE'!B15 -> C. Accès aux intrants | C15: =IF('7. RISQUE'!$B$23="Veuillez noter tous les critères de risques !",0,'7. RISQUE'!H15) -> 2 | D15: 6 | E15: 5 | F15: 4 | G15: 3 | H15: 2 | I15: 1 | K15: Frais bancaires | M15: Maraîchage | Q15: Tamita | R15: Malapouyah | S15: Dabiss · Kamsar · Kanfarandé · Kolaboui · Malapouyah · Sangaredi · Sansalé · Tanéné | AJ15: Riz | AK15: Soja | AL15: Sorgho | AQ15: Revenus totaux | AV15: ='5. RESULTAT'!K50 -> 1232316000 | AY15: Le niveau de consommation du ménage de l'entrepreneur est très faible. Il faut rechercher les dépenses familiales cachées. | AZ15: Le niveau de consommation du ménage de l'entrepreneur est dans les normes. | BB15: Le niveau de consommation du ménage de l'entrepreneur est très élevé. Risque de détourner le crédit à des fins personnelles. | BC15: Niveau de consommation très élevé et dépassant l'ensemble des revenus de l'entrepreneur. Risque d'impayé très élevé. | BF15: =IF(('5. RESULTAT'!K28+'4. BUDGET FAMILIAL'!K17)<0,"Le cumul des revenus de cet entrepreneur est négatif - Impossible de couvrir les dépenses familiales.",BG15) -> Le niveau de consommation du ménage de l'entrepreneur est dans les normes. | BG15: =IF(AX14<=35%,AY15,IF(AND(AX14>35%,AX14<=65%),AZ15,IF(AND(AX14>65%,AX14<=100%),BB15,IF(AX14>100%,BC15,"")))) -> Le niveau de consommation du ménage de l'entrepreneur est dans les normes. | BI15: =IF('8. PROPOSITION'!M12="","",BF15) -> Le niveau de consommation du ménage de l'entrepreneur est dans les normes.
B16: ='7. RISQUE'!B16 -> D. Accès et position dans le marché | C16: =IF('7. RISQUE'!$B$23="Veuillez noter tous les critères de risques !",0,'7. RISQUE'!H16) -> 3 | D16: 6 | E16: 5 | F16: 4 | G16: 3 | H16: 2 | I16: 1 | K16: Intérêts sur emprunts | M16: Niébé | Q16: Tougnifili | R16: Sangaredi | S16: Dabiss · Kamsar · Kanfarandé · Kolaboui · Malapouyah · Sangaredi · Sansalé · Tanéné | AJ16: Soja | AK16: Sorgho | AL16: Autre | AO16: Ratio de dependance des autres revenus R ≤ 50% | AQ16: Autres revenus | AV16: ='5. RESULTAT'!K51 -> 454996000 | AX16: ='5. RESULTAT'!M51 -> 0.36922023 | AY16: <0 | AZ16: =0 -> 0 | BA16: >0<=50 | BB16: >50<100 | BC16: >100 | BI16: =IF('8. PROPOSITION'!M13="","",BF16)
B17: ='7. RISQUE'!B17 -> E. Qualité des actifs de l'entreprise/exploitation | C17: =IF('7. RISQUE'!$B$23="Veuillez noter tous les critères de risques !",0,'7. RISQUE'!H17) -> 3 | D17: 6 | E17: 5 | F17: 4 | G17: 3 | H17: 2 | I17: 1 | K17: Redevance et autres | M17: Palmier à huile | R17: Sansalé | AJ17: Sorgho | AK17: Autre | AQ17: Revenus totaux | AV17: ='5. RESULTAT'!K52 -> 1232316000 | AY17: Attention ! Erreur ou le cumul des revenus de cet entrepreneur est négatif - L'excédent d'exploitation est déficitaire ou trop faible | AZ17: L'entrepreneur n'a pas d'autres sources de revenus. Aucune déclaration à cet effet. À vérifier | BA17: Ratio de dépendance aux autres revenus dans la norme. | BB17: L'entrepreneur dépend énormément des autres revenus. Vérifier la rentabilité de l'activité à financer. | BC17: Les autres revenus sont très importants dans la capacité financière du client. Vérifier la rentabilité réelle de l'activité. | BF17: =IF(('5. RESULTAT'!K28+'4. BUDGET FAMILIAL'!K17)<0,"Le cumul des revenus de cet entrepreneur est négatif - Le bénéfice d'exploitation est déficitaire.",BG17) -> Ratio de dépendance aux autres revenus dans la norme. | BG17: =IF(AX16<0%,AY17,IF(AX16=0%,AZ17,IF(AND(AX16>0%,AX16<=50%),BA17,IF(AND(AX16>50%,AX16<=100%),BB17,IF(AX16>100%,BC17,""))))) -> Ratio de dépendance aux autres revenus dans la norme. | BI17: =IF('8. PROPOSITION'!M12="","",BG17) -> Ratio de dépendance aux autres revenus dans la norme.
B18: ='7. RISQUE'!B18 -> F. Production et Exploitation | C18: =IF('7. RISQUE'!$B$23="Veuillez noter tous les critères de risques !",0,'7. RISQUE'!H18) -> 6 | D18: 6 | E18: 5 | F18: 4 | G18: 3 | H18: 2 | I18: 1 | K18: Impôts - Taxes et permis | M18: Riz | R18: Tanéné | AJ18: Autre
B19: ='7. RISQUE'!B19 -> G. Environnement | C19: =IF('7. RISQUE'!$B$23="Veuillez noter tous les critères de risques !",0,'7. RISQUE'!H19) -> 2 | D19: 6 | E19: 5 | F19: 4 | G19: 3 | H19: 2 | I19: 1 | K19: Réparation et maintenance | M19: Soja
B20: ='7. RISQUE'!B20 -> H. Capacité de remboursement, Solvabilité et niveau d'endettement | C20: =IF('7. RISQUE'!$B$23="Veuillez noter tous les critères de risques !",0,'7. RISQUE'!H20) -> 3 | D20: 6 | E20: 5 | F20: 4 | G20: 3 | H20: 2 | I20: 1 | K20: Amortissement | M20: Sorgho
K21: Provisions | M21: Autre
K22: Prélèvement de l'exploitant
K23: Honoraires professionnels
K24: Eau, électricité, téléphone | M24: Pôle A | N24: Riz, banane, ananas, agrume, légumes, palmier à huile, pêche, élevage, Taro. (Zone : Conakry, Forécariah, Dubréka, Boffa).
K25: Autre | M25: Pôle B | N25: Riz, culture fruitières, Maraichage, Manioc, Patate douce, Bovins. (Zone : Kindia, Mamou, Dalaba).
M26: Pôle C | N26: Mais, Pomme de terre, Culture fruitière, Maraichage, Fonio, arachide, Elevage, Taro. (Zone : Pita, Labé, Mali, Koubia, Tougé, Lélouma).
M27: Pôle D | N27: Riz, élevage bovins, arachide, coton, anacarde. (Zone : Boké, Télimelé, Koundara, Gaoual, Fria).
M28: Pôle E | N28: Riz, arachide, élevage bovin, caprin, niébé, maïs, fonio, sorgho, mil. (Zone : Faranah, Dabola, Dinguiraye).
M29: Pôle F | N29: Riz, mais, igname, manioc, coton, mangue, cultures maraichères, sorgho, mil. (Zones : Kankan, Kouroussa, Siguiri, Mandiana).
M30: Pôle G | N30: Riz palmier à huile, hévéa, café, cacao, banane, thé, élevage porcin. (Zone : Kissidougou, Guéckédou, Macenta).
M31: Pôle H | N31: Riz, élevage bovin, maïs, légumes, manioc, banane plantin, niébé, cola. (Zone : Kérouané, Beyla, Lola).
M32: Pôle I | N32: Riz, maïs, palmier à huile, hévéa, élevage porcin, manioc. (Zone : Nzérékoré, Yomou).

Sheet GRILLE

Sheet 1. DEMANDE
J3: =IF(G30="","DEMANDE DE CRÉDIT AGRICOLE",IF(G30<>"AGRICULTURE","DEMANDE DE CRÉDIT","DEMANDE DE CRÉDIT AGRICOLE")) -> DEMANDE DE CRÉDIT AGRICOLE
Z5: Agence de : | AD5: FORECARIAH
C7: Date de la demande : | I7: 23 | J7: / | K7: 12 | L7: / | M7: 2025 | Y7: Agent de crédit : | AD7: MOHAMED MMAH CAMARA
C9: Catégorie de clientèle : | I9: Individuel | O9: =IF(I9="","Type de Gpe/Grmt",IF(I9="Groupe","Type de Groupe",IF(I9="Groupement","Type de Grpment",""))) | Y9: =IF(I9="","Nombre de personnes",IF(OR(I9="Groupe",I9="Groupement"),"Nombre de personnes","")) | AH9: =IF(I9="","F",IF(OR(I9="Groupe",I9="Groupement"),"F","")) | AK9: =IF(I9="","H",IF(OR(I9="Groupe",I9="Groupement"),"H",""))
O11: =IF(I9="","Nom du Gpe/Grmt",IF(I9="Groupe","Nom du Groupe",IF(I9="Groupement","Nom du Grpment",""))) | AF11: =IF(I9="","Numéro :",IF(OR(I9="Groupe",I9="Groupement"),"Numéro :",""))
B13: 1. | C13: INFORMATIONS SUR LE MEMBRE/CLIENT
C15: Nom et Prénoms : | H15: MARIAMA KABA | AB15: Numéro/membre : | AH15: 10300181501
H16: (Suivant l'ordre de la pièce d’identité )
C17: Type de pièce d'identité : | J17: Carte d'Identité Biométrique | T17: Référence : | Y17: 2.2010125e+15
C19: Date et lieu de naissance : | J19: 1 | K19: / | L19: 1 | M19: / | N19: 1990 | P19: à | Q19: MAFERINYAH | Y19: Genre : | AA19: Femme
C21: Situation matrimoniale : | I21: Marié (e) | O21: Nombre de personnes à charge : | Y21: 7 | AA21: Nombre d'enfants scolarisés : | AJ21: 3
C23: Adresse de domicile et Contact : | K23: PLANTEUSE A MAFERINYAH CENTRE SECTEUR OLYMPIA TEL:623597829
O24: (Quartier, maison, lot et numéro de téléphone)
C25: Nombre d'années à l'adresse : | K25: 10 | P25: Type de propriété : | V25: Propriétaire
B28: 2. | C28: ACTIVITÉS
C30: Type d'activité : | G30: AGRICULTURE | M30: Sous-activité : | R30: Production_végétale | Z30: =IF(G30="","Sous-sous-activité (filière) :",IF(G30="AGRICULTURE","Sous-sous-activité (filière) :","Sous-sous-activité :")) -> Sous-sous-activité (filière) : | AG30: Ananas
C32: Description de l'activité : | J32: ACHAT D'UNE MACHINE ET INTRANTS AGRICOLE POUR LA REALISATION DE LA CULTURE D'ANANAS
C34: Nombre d'années dans l'activité : | L34: 5 | P34: Adresse du lieu d'activité : | X34: REALISATION DE LA CULTURE D'ANANAS A TAMBAYAH ET CONTA
C35: (Depuis combien de temps vous exercez cette activité ?)
C37: =IF(G30="","Superficie disponible :",IF(R30="Production_végétale","Superficie disponible :",IF(R30="Production_animale","Nombre de têtes :",""))) -> Superficie disponible : | I37: 2 | K37: =IF(G30="","Hectares",IF(R30="Production_végétale","Hectares","")) -> Hectares | P37: Région administrative : | W37: KINDIA | AC37: Préfecture : | AG37: Forécariah
C39: =IF(G30="","Superficie emblavée :",IF(R30="Production_végétale","Superficie emblavée :","")) -> Superficie emblavée : | I39: 2 | K39: =IF(G30="","Hectares",IF(R30="Production_végétale","Hectares","")) -> Hectares | P39: Pôle de développement agricole (PDA) : | AA39: A | AD39: Village : | AG39: TAMBAYAH ET CONTA
C43: Autres activités : | G43: COMMERCE DE RIZ DU PAYS | Y43: =IF(AA39="A",PARAMETRAGE!N24,IF('1. DEMANDE'!AA39="B",PARAMETRAGE!N25,IF('1. DEMANDE'!AA39="C",PARAMETRAGE!N26,IF('1. DEMANDE'!AA39="D",PARAMETRAGE!N27,IF('1. DEMANDE'!AA39="E",PARAMETRAGE!N28,IF('1. DEMANDE'!AA39="F",PARAMETRAGE!N29,IF('1. DEMANDE'!AA39="G",PARAMETRAGE!N30,IF('1. DEMANDE'!AA39="H",PARAMETRAGE!N31,IF('1. DEMANDE'!AA39="I",PARAMETRAGE!N32,""))))))))) -> Riz, banane, ananas, agrume, légumes, palmier à huile, pêche, élevage, Taro. (Zone : Conakry, Forécariah, Dubréka, Boffa).
C45: Lieu de l'activité : | G45: KABACK ET KAKOSSA
B48: 3. | C48: MODALITÉS DE LA DEMANDE
C50: Montant demandé : | H50: 300000000 | M50: GNF | P50: Durée demandée : | V50: 8 | X50: Mois | Z50: Périodicité de remboursement : | AI50: Mensuelle
C52: Taux d'intérêts : | G52: 0.03 | K52: Période de différé : | Q52: 5 | S52: Mois | U52: Nombre d'échéance : | AA52: 3 | AC52: Échéance : | AH52: 363000000
AH53: (Montant en GNF)
C54: Objet du crédit sollicité : | I54: Investissement | T54: Détail de l'objet de crédit : | AA54: ACHAT D'UN TRACTEUR ET INTRANTS AGRICOLES POUR LA REALISATION DE LA CULTURE D'ANANAS A TAMBAYAH ET CONTA
C56: Nouveau crédit : | I56: Renouvellement : | O56: X | Q56: Rang de crédit : | V56: 2
B59: 4. | C59: GARANTIES PROPOSÉES
C61: Type de Garantie | J61: Nature / Description des garanties | Z61: Valeur de la garantie | AG61: Valeur d'emprunt
C62: Caution solidaire | J62: 3 PERSONNES CAUTIONS
C63: Dépôt à terme
C64: Suretés réelles | J64: ATTESTATION DE CESSION ET PLAN DE MASSE( 1ha/2) | Z64: 810000000 | AG64: 648000000
C65: Autre garantie | J65: ACTE AUTHENTIQUE CONVENTION D'HYPOTHEQUE
C66: Total | AG66: =AG62+AG63+AG64+AG65 -> 648000000

Sheet 2. PROD
B2: AGENCE :
B3: Nom et Prénoms du client : | C3: ='1. DEMANDE'!H15 -> MARIAMA KABA | G3: N° Membre : | H3: ='1. DEMANDE'!AH15 -> 10300181501
B5: Date d'évaluation : | C5: 46093
B7: PÉRIODE DE LA CAMPAGNE AGRICOLE : | D7: 46127 | E7: Au : | F7: 46614
B9: Campagne | C9: Culture 1 | D9: Culture 2 | E9: Culture 3 | F9: Culture 4 | G9: Culture 5 | H9: Culture 6 | I9: TOTAL
B10: Type de culture | C10: ANANAS
B11: Surface cultivée en ha | C11: 2 | I11: =C11+D11+E11+F11+G11+H11 -> 2
B12: ÉLÉMENTS
B16: COÛT DE PRODUCTION (GNF) | C16: 922680000 | I16: =D16+E16+F16+G16+H16+C16 -> 922680000
B24: CHIFFRE D'AFFAIRES (GNF) | C24: 1700000000 | I24: =C24+D24+E24+F24+G24+H24 -> 1700000000
B25: Marge brute totale sur production (GNF) | C25: =C24-C16 -> 777320000 | D25: =D24-D16 -> 0 | E25: =E24-E16 -> 0 | F25: =F24-F16 -> 0 | G25: =G24-G16 -> 0 | H25: =H24-H16 -> 0 | I25: =C25+D25+E25+F25+G25+H25 -> 777320000
B27: Évaluation de l'apport personnel en main d'œuvre (force de travail personnel et familial) | C27: 220440000 | I27: =C27+D27+E27+F27+G27+H27 -> 220440000
B28: Besoins en crédit exprimés pour la production | C28: 300000000 | I28: =C28+D28+E28+F28+G28+H28 -> 300000000

Sheet 3. BILAN
B2: Nom et Prénoms du membre : | D2: ='1. DEMANDE'!H15 -> MARIAMA KABA | J2: Agence de : | K2: ='1. DEMANDE'!AD5 -> FORECARIAH
B4: Numéro client /membre : | D4: ='1. DEMANDE'!AH15 -> 10300181501 | H4: Agent de crédit : | J4: ='1. DEMANDE'!AD7 -> MOHAMED MMAH CAMARA
I6: Date d'évaluation : | J6: ='2. PROD'!C5 -> 46093
B8: 5. | C8: BILAN RECONSTITUE
C10: Éléments du bilan | I10: Actuel (N) | J10: Précédent (N-1) | K10: Commentaires
B13: 1 | C13: Encaisse / Compte épargne IMF/ Banque | I13: 30000000 | J13: 15000000
B14: 2 | C14: =IF('1. DEMANDE'!G30="","Inventaires (stocks de produits /intrants/etc.)",IF('1. DEMANDE'!G30="AGRICULTURE","Inventaires (stocks de produits /intrants/etc.)","Inventaires (stocks de marchandises/produits, etc.)")) -> Inventaires (stocks de produits /intrants/etc.) | I14: 20000000 | J14: 10000000
B15: 3 | C15: Clients (ventes à crédit)
B16: 4 | C16: Autres comptes à recevoir | I16: 6000000 | J16: 3000000
B17: 5 | C17: Actif à court terme (1+2+3+4) | I17: =SUM(I13:I16) -> 56000000 | J17: =SUM(J13:J16) -> 28000000
B18: 6 | C18: =IF('1. DEMANDE'!G30="","Terrains (terres cultivables)",IF('1. DEMANDE'!G30="AGRICULTURE","Terrains (terres cultivables)","Terrains")) -> Terrains (terres cultivables) | I18: 600000000 | J18: 300000000
B19: 7 | C19: Bâtiments (Magasins et autres) | I19: 500000000 | J19: 250000000
B20: 8 | C20: =IF('1. DEMANDE'!G30="","Moyens de transport (Véhicules, motos, charrettes, etc.)",IF('1. DEMANDE'!G30="AGRICULTURE","Moyens de transport (Véhicules, motos, charrettes, etc.)","Moyens de transport (Véhicules, motos, etc.)")) -> Moyens de transport (Véhicules, motos, charrettes, etc.) | I20: 7000000 | J20: 6500000
B21: 9 | C21: =IF('1. DEMANDE'!G30="","Équipements (charrue, tracteur et autres)",IF('1. DEMANDE'!G30="AGRICULTURE","Équipements (charrue, tracteur et autres)","Équipements et autres")) -> Équipements (charrue, tracteur et autres)
B22: 10 | C22: =IF('1. DEMANDE'!G30="","Autres (animaux de trait)",IF('1. DEMANDE'!G30="AGRICULTURE","Autres (animaux de trait)","Matériels et mobiliers")) -> Autres (animaux de trait) | I22: 30000000 | J22: 15000000
B23: 11 | C23: Autres actifs immobilisés
B24: 12 | C24: Actif à long terme (6+7+8+9+10+11) | I24: =SUM(I18:I23) -> 1137000000 | J24: =SUM(J18:J23) -> 571500000
B26: 13 | C26: TOTAL ACTIF (5+12) | I26: =I17+I24 -> 1193000000 | J26: =J17+J24 -> 599500000
B28: 14 | C28: Dettes Fournisseurs | I28: 20000000 | J28: 10000000
B29: 15 | C29: Avances reçues des clients
B30: 16 | C30: Intérêt à payer
B31: 17 | C31: Autres comptes à payer | I31: 0
B32: 18 | C32: Passif court terme (14+15+16+17) | I32: =SUM(I28:I31) -> 20000000 | J32: =SUM(J28:J31) -> 10000000
B33: 19 | C33: Emprunt à payer / Autres dettes à + d'un an | I33: 0
B35: 20 | C35: DETTES TOTALES (18+19) | I35: =SUM(I32:I33) -> 20000000 | J35: =J32+J33 -> 10000000
B37: 21 | C37: CAPITAUX PROPRES | I37: =I26-I35 -> 1173000000 | J37: =J26-J35 -> 589500000
B39: 22 | C39: TOTAL PASSIF (20+21) | I39: =I26 -> 1193000000 | J39: =J26 -> 599500000
B41: 23 | C41: Fonds de roulement (5-18) | I41: =I17-I32 -> 36000000 | J41: =J17-J32 -> 18000000
B42: 24 | C42: Besoin en Fonds de roulement (23-1) | I42: =I41-I13 -> 6000000 | J42: =J41-J13 -> 3000000
B44: 6. | C44: ANALYSE DES BESOINS RÉELS EN CRÉDIT
C46: CRÉDIT INVESTISSEMENT | J46: Valeurs | K46: Commentaires
B47: 25 | C47: =IF('1. DEMANDE'!G30="","Besoins d’investissement (machine, tracteur, matériel, etc.)",IF('1. DEMANDE'!G30="AGRICULTURE","Besoins d’investissement (machine, tracteur, matériel, etc.)","Besoins d’investissement (machine et autre équipement, etc.)")) -> Besoins d’investissement (machine, tracteur, matériel, etc.) | J47: 526700000 | K47: TRACTEUR
B48: 26 | C48: Dépenses rattachées à l’investissement | J48: 395980000 | K48: INTRENTS
B49: 27 | C49: Apport personnel (et/ou Subvention)
B50: 28 | C50: Besoins réels en crédit investissement (25+26-27) | I50: =IF(J50<0,"Attention/Erreur","") | J50: =J47+J48-J49 -> 922680000
C52: CRÉDIT PRODUCTION/EXPLOITATION | J52: Valeurs | K52: Commentaires
B53: 29 | C53: =IF('1. DEMANDE'!G30="","Besoins pour tout le cycle (Coût de production + autres charges d'exploitation)",IF('1. DEMANDE'!G30="AGRICULTURE","Besoins pour tout le cycle (Coût de production + autres charges d'exploitation)","Besoins pour tout le cycle d'activité")) -> Besoins pour tout le cycle (Coût de production + autres charges d'exploitation) | J53: ='5. RESULTAT'!K27 -> 922680000
B54: 30 | C54: =IF('1. DEMANDE'!G30="","Trésorerie disponible pour l'activité de production",IF('1. DEMANDE'!G30="AGRICULTURE","Trésorerie disponible pour l'activité de production","Trésorerie disponible pour l'activité")) -> Trésorerie disponible pour l'activité de production
B55: 31 | C55: Stock actuel (2) | J55: =I14 -> 20000000
B56: 32 | C56: Comptes à recevoir (3+4) | J56: =I15+I16 -> 6000000
B57: 33 | C57: Dettes fournisseurs et autres dettes (18) | J57: =I32 -> 20000000
B58: 34 | C58: Crédit fournisseur (et/ou Subvention)
B59: 35 | C59: Apport personnel en force de travail (personnel et familial) | J59: ='2. PROD'!I27 -> 220440000
B60: 36 | C60: =IF('1. DEMANDE'!G30="","Besoins réels en crédit pour la production (29-30-31-32+33-34-35)",IF('1. DEMANDE'!G30="AGRICULTURE","Besoins réels en crédit pour la production (29-30-31-32+33-34-35)","Besoins réels en crédit exploitation (29-30-31-32+33-34-35)")) -> Besoins réels en crédit pour la production (29-30-31-32+33-34-35) | I60: =IF(J60<0,"Attention-Pas de besoin","") | J60: =J53-J54-J55-J56+J57-J58-J59 -> 696240000

Sheet 4. BUDGET FAMILIAL
C3: Nom et Prénoms du membre : | D3: ='1. DEMANDE'!H15 -> MARIAMA KABA | K3: Agence de : | L3: ='1. DEMANDE'!AD5 -> FORECARIAH
C5: Numéro client /membre : | D5: ='1. DEMANDE'!AH15 -> 10300181501 | H5: Agent de crédit : | K5: ='1. DEMANDE'!AD7 -> MOHAMED MMAH CAMARA
H7: Date d'évaluation : | K7: ='5. RESULTAT'!M7 -> 46093
B9: 7. | C9: ANALYSE BUDGÉTAIRE DES AUTRES REVENUS ET DÉPENSES DE LA FAMILLE
C11: REVENUS | H11: Revenu mensuel | J11: Nbre de mois | K11: Revenu attendu pour la période | L11: Observations
C12: Autres sources de revenus | H12: 15000000 | J12: 10 | K12: =H12*J12 -> 150000000 | L12: VENTE DE RIZ DU PAYS
C13: Revenus nets issus d'autres activités commerciales | H13: 8332000 | J13: 3 | K13: =H13*J13 -> 24996000 | L13: VENTE DES REJETS
C14: Revenus nets issus de la location (biens immobiliers et/matériels) | H14: 12000000 | J14: 10 | K14: =H14*J14 -> 120000000 | L14: LOCATION TRACTEUR
C15: Revenus nets issus d'autres activités commerciales | H15: 20000000 | J15: 8 | K15: =H15*J15 -> 160000000
K16: =H16*J16 -> 0
C17: TOTAL | K17: =SUM(K12:K16) -> 454996000
C19: DÉPENSES FAMILIALES | H19: Coût mensuel | J19: Nbre de mois | K19: Coût pour la période | L19: Observations
C21: Frais d'alimentation
C22: Produits vivriers | H22: 6000000 | J22: 12 | K22: =H22*J22 -> 72000000 | L22: RIZ
C23: Condiments | H23: 3000000 | J23: 12 | K23: =H23*J23 -> 36000000 | L23: SAUCE
C24: Charbon - Bois - Gaz | H24: 200000 | J24: 12 | K24: =H24*J24 -> 2400000
C25: Redevance - Loyer
C26: Loyer | H26: 2000000 | J26: 2 | K26: =H26*J26 -> 4000000 | L26: LOCATION TERRAINS
C27: Electricité - eau | H27: 200000 | J27: 12 | K27: =H27*J27 -> 2400000 | L27: ELECTRICITE
C28: Télécommunication | H28: 3500000 | J28: 12 | K28: =H28*J28 -> 42000000 | L28: TELEPHONE
C29: Frais de transport
C30: Transport en commun | K30: =H30*J30 -> 0
C31: Entretien moto/auto | H31: 2000000 | J31: 12 | K31: =H31*J31 -> 24000000
C32: Carburant moto/auto | H32: 5000000 | J32: 12 | K32: =H32*J32 -> 60000000
C33: Autres frais de subsistance
C34: Frais d'habillement | H34: 3000000 | J34: 12 | K34: =H34*J34 -> 36000000
C35: Frais médicaux | H35: 5000000 | J35: 12 | K35: =H35*J35 -> 60000000
C36: Frais de scolarité | H36: 1500000 | J36: 8 | K36: =H36*J36 -> 12000000
C37: Autres frais | K37: =H37*J37 -> 0
C38: Travaux de constructions privées | H38: 100000000 | J38: 1 | K38: =H38*J38 -> 100000000
C39: TOTAL | K39: =K22+K23+K24+K26+K27+K28+K30+K31+K32+K34+K35+K36+K37+K38 -> 450800000
C42: EXCÉDENT/MANQUANT DU BUDGET FAMILIAL | H42: =IF(K42<0,"Manquant",IF(K42>0,"Excédent","NUL")) -> Excédent | K42: =K17-K39 -> 4196000

Sheet 5. RESULTAT
B3: Nom et Prénoms du membre : | G3: ='1. DEMANDE'!H15 -> MARIAMA KABA | M3: Agence de : | N3: ='1. DEMANDE'!AD5 -> FORECARIAH
B5: Numéro client /membre : | G5: ='1. DEMANDE'!AH15 -> 10300181501 | J5: Agent de crédit : | M5: ='1. DEMANDE'!AD7 -> MOHAMED MMAH CAMARA
K7: Date d'évaluation : | M7: ='3. BILAN'!J6 -> 46093
B9: 12. | C9: COMPTE DE RÉSULTAT
B11: N° | C11: Eléments | K11: Période (n) | L11: Période (n-1) | N11: Observations
K12: =IF('3. BILAN'!I11="","",'3. BILAN'!I11) | L12: =IF('3. BILAN'!J11="","",'3. BILAN'!J11)
B13: 37 | C13: Chiffre d'affaires | K13: =PARAMETRAGE!G6 -> 1700000000
B14: 38 | C14: =IF('1. DEMANDE'!G30="","Coût de production",IF('1. DEMANDE'!G30="AGRICULTURE","Coût de production",IF('1. DEMANDE'!R30="Commercialisation","Coût d'achats de produits agricoles","Coût d'achat/production"))) -> Coût de production | K14: =PARAMETRAGE!F6 -> 922680000
B15: 39 | C15: =IF('1. DEMANDE'!G30="","Marge brute sur coût de production (37-38)",IF('1. DEMANDE'!R30="Production_végétale","Marge brute sur coût de production (37-38)","Marge brute (37-38)")) -> Marge brute sur coût de production (37-38) | K15: =K13-K14 -> 777320000 | L15: =M13-M14 -> 0
B16: 40 | C16: Les autres charges
B17: 41
B18: 42
B19: 43
B20: 44
B21: 45
B22: 46
B23: 47
B24: 48
B25: 49
B26: 50 | D26: Total des autres charges (40+41+42+43+44+45+46+47+48+49) | K26: =SUM(K16:K25) -> 0 | L26: =SUM(L16:L25) -> 0
B27: 51 | C27: =IF(PARAMETRAGE!CS2>0,"Total des dépenses d'exploitation & Amort_ (38+50)","Total des dépenses d'exploitation (38+50)") -> Total des dépenses d'exploitation (38+50) | K27: =K14+K26 -> 922680000 | L27: =L14+L26 -> 0
B28: 52 | C28: Bénéfice net d'exploitation | K28: =K13-K27 -> 777320000 | L28: =L13-L27 -> 0
B29: 53 | C29: Surplus ou manquant du budget familial | K29: ='4. BUDGET FAMILIAL'!K42 -> 4196000
B30: 54 | C30: Les réintégrations (Capital du crédit, Amort et Prov.) | K30: =IF('1. DEMANDE'!I54="Investissement",PARAMETRAGE!CS2,PARAMETRAGE!CS1) -> 0
B31: 55 | C31: Échéances des autres crédits en cours sur la période
B32: 56 | C32: Montant disponible pour le remboursement du crédit | K32: =K28+K29+K30-K31 -> 781516000 | L32: =L28+L29+L30-L31 -> 0
B34: 13. | C34: RATIOS FINANCIERS D'AIDE À LA DÉCISION
C36: Ratios | E36: Formules | K36: Calculs | M36: Résultats | N36: Commentaire
C37: Niveau de financement R1 ≤ 65 % | F37: Montant du crédit proposé | K37: =IF('8. PROPOSITION'!M12="","",'8. PROPOSITION'!M12) -> 300000000 | M37: =IF('8. PROPOSITION'!M12="","",K37/K38) -> 0.32513981 | N37: =PARAMETRAGE!BI2 -> Bon ratio. Le niveau de participation de financement est acceptable. Attention, le crédit ne couvre pas le besoin réel.
F38: =IF('1. DEMANDE'!I54="Investissement","Total Dépenses d'investissement","Total Dépenses d'exploitation") -> Total Dépenses d'investissement | K38: =IF('8. PROPOSITION'!M12="","",IF('1. DEMANDE'!I54="Investissement",('3. BILAN'!J47+'3. BILAN'!J48),(K27-PARAMETRAGE!CS2))) -> 922680000
C39: Capacité de remboursement R2 ≥ 1,5 | F39: Montant disponible pour l'échéance | K39: =IF('8. PROPOSITION'!M12="","",PARAMETRAGE!CU5) -> 2.6050533e+08 | M39: =IF('8. PROPOSITION'!M12="","",K39/K40) -> 1.439256 | N39: =PARAMETRAGE!BI4 -> La couverture de l'échéance est acceptable mais trop juste. Le risque d'impayé est à prendre en compte.
F40: Échéance du crédit | K40: =IF('8. PROPOSITION'!M12="","",'8. PROPOSITION'!M22) -> 181000000
C41: Ratio de fonds de roulement R3 ≥ 1,5 | F41: Actif à court terme | K41: =IF('8. PROPOSITION'!M12="","",'3. BILAN'!I17) -> 56000000 | M41: =IF('8. PROPOSITION'!M12="","",K41/K42) -> 2.8 | N41: =IF(AND(K41>0,K42=0),"Pas de dette à court terme. Le fonds de roulement est positif.",PARAMETRAGE!BI6) -> Bon ratio. Les actifs à court terme surpassent les dettes à moins d'un an et dégagent un surplus important.
F42: Passif à court terme | K42: =IF('8. PROPOSITION'!M12="","",'3. BILAN'!I32) -> 20000000
C43: Ratio de solvabilité R4 ≤ 0,5 | F43: Dettes totales | K43: =IF('8. PROPOSITION'!M12="","",'3. BILAN'!I35) -> 20000000 | M43: =IF('8. PROPOSITION'!M12="","",K43/K44) -> 0.017050298 | N43: =PARAMETRAGE!BI9 -> Excellent ratio de solvabilité. Les dettes de l'entreprise sont très faibles par rapport aux fonds propres
F44: Fonds propres | K44: =IF('8. PROPOSITION'!M12="","",'3. BILAN'!I37) -> 1173000000
C45: Ratio de liquidité à échéance R5 ≥ 1 | F45: Actif circulant - Stock | K45: =IF('8. PROPOSITION'!M12="","",('3. BILAN'!I17-'3. BILAN'!I14)) -> 36000000 | M45: =IF('8. PROPOSITION'!M12="","",K45/K46) -> 1.8 | N45: =IF(AND(K41>0,K42=0),"Pas de dette à court terme. Le fonds de roulement est positif.",PARAMETRAGE!BI11) -> Ratio respectant la norme. Les dettes à moins d'un an seront réglées.
F46: Passif à court terme | K46: =IF('8. PROPOSITION'!M12="","",'3. BILAN'!I32) -> 20000000
C47: Ratio d'endettement R6 ≤ 65 % | F47: Dettes totales + Crédit proposé | K47: =IF('8. PROPOSITION'!M12="","",'3. BILAN'!I35+'8. PROPOSITION'!M12) -> 320000000 | M47: =IF('8. PROPOSITION'!M12="","",K47/K48) -> 0.21433356 | N47: =PARAMETRAGE!BI13 -> Niveau d'endettement faible pour l'entreprise. Elle possède une bonne marge pour s'endetter davantage.
F48: Actif total + Crédit proposé | K48: =IF('8. PROPOSITION'!M12="","",'3. BILAN'!I26+'8. PROPOSITION'!M12) -> 1493000000
C49: Ratio de consommation familiale 35% < R7 ≤ 65% | F49: Consommation familiale | K49: =IF('8. PROPOSITION'!M12="","",'4. BUDGET FAMILIAL'!K39) -> 450800000 | M49: =IF('8. PROPOSITION'!M12="","",K49/K50) -> 0.36581526 | N49: =PARAMETRAGE!BI15 -> Le niveau de consommation du ménage de l'entrepreneur est dans les normes.
F50: Revenus totaux | K50: =IF('8. PROPOSITION'!M12="","",(K28+'4. BUDGET FAMILIAL'!K17)) -> 1232316000
C51: Ratio de dependance des autres revenus R8 ≤ 50% | F51: Autres revenus | K51: =IF('8. PROPOSITION'!M12="","",('4. BUDGET FAMILIAL'!K17-PARAMETRAGE!CN12)) -> 454996000 | M51: =IF('8. PROPOSITION'!M12="","",K51/K52) -> 0.36922023 | N51: =PARAMETRAGE!BI17 -> Ratio de dépendance aux autres revenus dans la norme.
F52: Revenus totaux | K52: =IF('8. PROPOSITION'!M12="","",(K28+'4. BUDGET FAMILIAL'!K17)) -> 1232316000

Sheet 6. MATRICE
B3: Nom et Prénoms du membre : | E3: ='1. DEMANDE'!H15 -> MARIAMA KABA | L3: Agence de : | M3: ='1. DEMANDE'!AD5 -> FORECARIAH
B5: Numéro client /membre : | E5: ='1. DEMANDE'!AH15 -> 10300181501 | L5: Agent de crédit : | M5: ='1. DEMANDE'!AD7 -> MOHAMED MMAH CAMARA
L7: Date d'évaluation : | M7: ='4. BUDGET FAMILIAL'!K7 -> 46093
B9: 14. MATRICE D'ANALYSE ET DE DÉCISION
C11: CAPACITÉ DE L'ENTREPRENEUR Stabilité sociale, Réputation, Expérience dans l’activité, Formation, Techniques de production: rendements, historique, Encadrement technique, Antécédents de crédit, Associations culturales ou autres, Soins vétérinaires, Taux de mortalité, performances, Gestion des risques. | I11: LE MARCHÉ Débouchés pour le produit, Infrastructures pour la vente différée, Fluctuation des prix, Niveau d’organisation de la filière, Regroupement pour achat ou vente, Approvisionnement en intrants
C14: L'ACTIVITÉ À FINANCER Production principale (superficie), Productions secondaires (superficies), Autres sources de revenus, Propriétaire, Rendements / productivité /rentabilité, Races | I14: LES FACTEURS EXTERNES Qualité / fertilité du sol, Disponibilité en eau (irrigation), Mesures d’atténuation des risques (fonds de garantie, assurances, autres), Risques inondation / glissement de terrain, etc.
B18: 15. ANALYSES DES FACTEURS DE RISQUES
C20: Critères d’analyse des risques | F20: Niveau de maîtrise par le client | I20: Cote de risque | J20: Commentaire associé | M20: Commentaires de l'agent de crédit
C21: A. Direction de l'activité Compétences, expériences, qualité morale, stabilité sociale, planification, comptabilité, réputation, contrôle des prix, suivi du marché, etc. | F21: Excellent | I21: =IF(F21="Excellent",1,IF(F21="Très bien",2,IF(F21="Bien",3,IF(F21="Passable",4,IF(F21="Faible",5,IF(F21="Très faible",6,"")))))) -> 1 | J21: =IF(F21="Excellent","Expérience importante dans le secteur (plus de dix ans), Excellente connaissance de son domaine d'activité et très bon suivi.",IF(F21="Très bien","Grande expérience dans le secteur (plus de cinq ans), formation et bon suivi de l'activité.",IF(F21="Bien","Grande expérience dans le secteur (plus de cinq ans)",IF(F21="Passable","Expérience limitée (moins de cinq ans) dans le secteur / suivi délégué de l'activité",IF(F21="Faible","Expérience limitée comme entrepreneur (moins de cinq ans) mais pas dans le secteur",IF(F21="Très faible","Aucune expérience","")))))) -> Expérience importante dans le secteur (plus de dix ans), Excellente connaissance de son domaine d'activité et très bon suivi.
C22: B. Historique de crédits et scoring de remboursement Habitude de crédits, Historique de remboursement des crédits antérieurs, Présence de retard dans le dossier, Nombre de retards observés. | F22: Passable | I22: =IF(F22="Nouveau Client",3,IF(F22="Excellent",1,IF(F22="Très bien",2,IF(F22="Bien",3,IF(F22="Passable",4,IF(F22="Faible",5,IF(F22="Très faible",6,""))))))) -> 4 | J22: =IF(F22="Nouveau Client","Il s'agit d'un nouveau client sans historique de crédit",IF(F22="Excellent","Plus de 10 crédits déjà remboursés et n'ayant jamais de retard",IF(F22="Très bien","Entre 5 et 10 crédits remboursés - Aucun retard de remboursement",IF(F22="Bien","Plus de 5 crédits remboursés et des retards ayant cumulés moins de 60 jours",IF(F22="Passable","Entre 3 et 5 crédits remboursés - Retards compris entre 60 et 90 jours",IF(F22="Faible","Entre 1 et 5 crédits remboursés - Crédit en retard et provisionné",IF(F22="Très faible","Ancien client - Crédit précedemment radié",""))))))) -> Entre 3 et 5 crédits remboursés - Retards compris entre 60 et 90 jours
C23: =IF('1. DEMANDE'!G30="","C. Accès aux intrants Accès et approvisionnement en intrants, Capacité de négociation des intrants, Disponibilités des intrants, Fluctuation des prix, Niveau d’organisation de la filière, Regroupement pour achat, etc.",IF('1. DEMANDE'!G30="AGRICULTURE","C. Accès aux intrants Accès et approvisionnement en intrants, Capacité de négociation des intrants, Disponibilités des intrants, Fluctuation des prix, Niveau d’organisation de la filière, Regroupement pour achat, etc.","C. Accès aux approvisionnements Accès et approvisionnement, Capacité de négociation, Disponibilités des articles, Fluctuation des prix, etc.")) -> C. Accès aux intrants Accès et approvisionnement en intrants, Capacité de négociation des intrants, Disponibilités des intrants, Fluctuation des prix, Niveau d’organisation de la filière, Regroupement pour achat, etc. | F23: Très bien | I23: =IF(F23="Excellent",1,IF(F23="Très bien",2,IF(F23="Bien",3,IF(F23="Passable",4,IF(F23="Faible",5,IF(F23="Très faible",6,"")))))) -> 2 | J23: =IF(F23="Excellent","Accès aux intrants de qualité, subventionnés, achats groupés",IF(F23="Très bien","Accès facile aux intrants",IF(F23="Bien","Accès aux intrants sans difficultés majeures",IF(F23="Passable","Accès aux intrants avec difficultés",IF(F23="Faible","Accès aux intrants très limité",IF(F23="Très faible","Aucun accès","")))))) -> Accès facile aux intrants
C24: =IF('1. DEMANDE'!G30="","D. Accès et position dans le marché Débouchés pour le produit, part de marché, Infrastructures pour la vente différée, Fluctuation des prix, Niveau d’organisation de la filière, Regroupement pour vente, Concurrence, réputation, contrôle des prix, etc.",IF('1. DEMANDE'!G30="AGRICULTURE","D. Accès et position dans le marché Débouchés pour le produit, part de marché, Infrastructures pour la vente différée, Fluctuation des prix, Niveau d’organisation de la filière, Regroupement pour vente, Concurrence, réputation, contrôle des prix, etc.","D. Accès et position dans le marché Débouchés pour le produit, part de marché, Infrastructures pour la vente, Fluctuation des prix, Concurrence, réputation, contrôle des prix, etc.")) -> D. Accès et position dans le marché Débouchés pour le produit, part de marché, Infrastructures pour la vente différée, Fluctuation des prix, Niveau d’organisation de la filière, Regroupement pour vente, Concurrence, réputation, contrôle des prix, etc. | F24: Bien | I24: =IF(F24="Excellent",1,IF(F24="Très bien",2,IF(F24="Bien",3,IF(F24="Passable",4,IF(F24="Faible",5,IF(F24="Très faible",6,"")))))) -> 3 | J24: =IF(F24="Excellent","Contrat d’achat avec prix garanti avec une société reconnue",IF(F24="Très bien","Entente contractuelle avec un groupement ou une société portant sur le prix et/ou la quantité",IF(F24="Bien","Mise en marché commun mais sans garantie",IF(F24="Passable","Distribution par des intermédiaires ",IF(F24="Faible","Vente directe au marché ou à la demande",IF(F24="Très Faible","Canaux de mise en marché non connus","")))))) -> Mise en marché commun mais sans garantie
C25: =IF('1. DEMANDE'!G30="","E. Qualité des actifs de l'entreprise/exploitation Terres, équipement, Technologie, composition, valeur, âge, désuétude, spécificité, etc.)",IF('1. DEMANDE'!G30="AGRICULTURE","E. Qualité des actifs de l'entreprise/exploitation Terres, équipement, Technologie, composition, valeur, âge, désuétude, spécificité, etc.)","E. Qualité des actifs de l'entreprise/exploitation Particularité des actifs liés à l'activité, etc.")) -> E. Qualité des actifs de l'entreprise/exploitation Terres, équipement, Technologie, composition, valeur, âge, désuétude, spécificité, etc.) | F25: Bien | I25: =IF(F25="Excellent",1,IF(F25="Très bien",2,IF(F25="Bien",3,IF(F25="Passable",4,IF(F25="Faible",5,IF(F25="Très faible",6,"")))))) -> 3 | J25: =IF(F25="Excellent","Terre disponible et très fertile, équipements neufs avec existence de pièces de rechange sur le marché, technologie très bien adaptée",IF(F25="Très bien","Existence de matériels d'exploitation, terre disponible et de bonne qualité, tehnologie en cours d'amélioration",IF(F25="Bien","Terre disponible et régulièrement exploitée, existence d'équipement, pas de technologie particulière",IF(F25="Passable","Terre disponible et régulièrement exploitée - Nécessité d'apport de fumure - pas de technologie",IF(F25="Faible","Terre disponible nécessitant des apports de fumure avec un rendement en-dessous de la moyenne, équipement vétuste",IF(F25="Très faible","Terre nécéssitant la mise en jachère, Équipement vétuste et utilisation de technique de production dépassée","")))))) -> Terre disponible et régulièrement exploitée, existence d'équipement, pas de technologie particulière
C26: =IF('1. DEMANDE'!G30="","F. Production et Exploitation Climat, pluviométrie, maladie, ravageurs, disponibilité des ressources humaines, etc.",IF('1. DEMANDE'!G30="AGRICULTURE","F. Production et Exploitation Climat, pluviométrie, maladie, ravageurs, disponibilité des ressources humaines, etc.","F. Risque de continuité de l'exploitation Risque politique, réglementation, disponibilité des ressources humaines, etc.")) -> F. Production et Exploitation Climat, pluviométrie, maladie, ravageurs, disponibilité des ressources humaines, etc. | F26: Très faible | I26: =IF(F26="Excellent",1,IF(F26="Très bien",2,IF(F26="Bien",3,IF(F26="Passable",4,IF(F26="Faible",5,IF(F26="Très faible",6,"")))))) -> 6 | J26: =IF(F26="Excellent","Très bonne disposition pour atténuer les risques climatiques, Diversification de la production et des revenus, Assurance récole",IF(F26="Très bien","Apte à réagir face aux risques de production agricole - Autre source de revenus disponible",IF(F26="Bien","Connaissance des risques de production agricole - Expérience dans la gestion",IF(F26="Passable","Une bonne connaissance des risques de production agricole mais sans mesures appropriées d'atténuation",IF(F26="Faible","Absence de mesures d'atténuation face aux risques agricoles - Difficultés d'accès à la main d'oeuvre",IF(F26="Très faible","Aucune connaissance des risques agricoles - Difficultés d'accès à la main d'oeuvre","")))))) -> Aucune connaissance des risques agricoles - Difficultés d'accès à la main d'oeuvre
C27: G. Environnement Respect de l'environnement, impact sur l'environnement, activité non prohibé, etc. | F27: Très bien | I27: =IF(F27="Excellent",1,IF(F27="Très bien",2,IF(F27="Bien",3,IF(F27="Passable",4,IF(F27="Faible",5,IF(F27="Très faible",6,"")))))) -> 2 | J27: =IF(F27="Excellent","Catégorisé-C Bonne pratique culturale respectueuse de l'environnement, protection, Utilisation des produits bio.",IF(F27="Très bien"," Catégorisé-C Bonne pratique culturale respectueuse de l'environnement, protection, Utilisation des produits des engrais homologués.",IF(F27="Bien","Catégorisé-C utilisation des engrais homologués, protection",IF(F27="Passable","Catégorisé-C Utilisation des engrais chimiques homologués sans protection adéquate.",IF(F27="Faible","Catégorisé-B Utilisation des produits homologués sans protection adéquate.",IF(F27="Très faible","Catégorisé-A Utilisation des produits non homologués sans aucune protection","")))))) -> Catégorisé-C Bonne pratique culturale respectueuse de l'environnement, protection, Utilisation des produits des engrais homologués.
C28: H. Capacité de remboursement, Solvabilité et niveau d'endettement La capacité de remboursement est-elle confortable ? L'entreprise est-elle capable de payer ses dettes ? Le niveau d'endettement, sera-t-il assez raisonnable avec un nouveau crédit ? | F28: Bien | I28: =IF(F28="Excellent",1,IF(F28="Très bien",2,IF(F28="Bien",3,IF(F28="Passable",4,IF(F28="Faible",5,IF(F28="Très faible",6,"")))))) -> 3 | J28: =IF(F28="Excellent","Tous les ratios sont largement au-dessus de la norme; la capacité de remboursement est de plus 300% le service de la dette et le niveau d'endettement est de moins de 10% des fonds propres",IF(F28="Très bien","Tous les ratios sont largement au-dessus de la norme; la capacité de remboursement est de plus 200% le service de la dette et le niveau d'endettement est de moins de 50% des fonds propres",IF(F28="Bien","5 ratios sur 8 sont au-dessus de la norme; la capacité de remboursement est de plus 150% le service de la dette et le niveau d'endettement est de moins de 75% des fonds propres",IF(F28="Passable","4 ratios sur 8 sont au-dessus de la norme; la capacité de remboursement est de plus de 100% le service de la dette et le niveau d'endettement est de moins de 100% des fonds propres",IF(F28="Faible","Moins de 4 ratios sont au-dessus de la norme; la capacité de remboursement est de moins de 100% le service de la dette et le niveau d'endettement est de plus de 100% des fonds propres",IF(F28="Très faible","Moins de 4 ratios sont au-dessus de la norme; la capacité de remboursement est négative et le niveau d'endettement est de plus de 100% des fonds propres","")))))) -> 5 ratios sur 8 sont au-dessus de la norme; la capacité de remboursement est de plus 150% le service de la dette et le niveau d'endettement est de moins de 75% des fonds propres

Sheet 7. RISQUE
B3: Nom et Prénoms du membre : | D3: ='1. DEMANDE'!H15 -> MARIAMA KABA | H3: Agence de : | I3: ='1. DEMANDE'!AD5 -> FORECARIAH
B5: Numéro client /membre : | D5: ='1. DEMANDE'!AH15 -> 10300181501 | H5: Agent de crédit : | I5: ='1. DEMANDE'!AD7 -> MOHAMED MMAH CAMARA
H7: Date d'évaluation : | I7: ='4. BUDGET FAMILIAL'!K7 -> 46093
B9: 16. SYNTHÈSE DES RISQUES
B11: Critères d'analyse | E11: Pondération | F11: Pondération | G11: Pondération | H11: Cote attribué par l’Agent de Crédit (C) | I11: Pointage
E12: Proposée | F12: Ajustée | G12: (P) | I12: (P X C)
B13: A. Direction Compétences, expériences, qualité morale, stabilité sociale.. | E13: 0.1 | G13: =IF(ISBLANK(F13),E13,F13) -> 0.1 | H13: ='6. MATRICE'!I21 -> 1 | I13: =H13*G13 -> 0.1
B14: B. Historique de crédits et scoring de remboursement | E14: 0.1 | G14: =IF(ISBLANK(F14),E14,F14) -> 0.1 | H14: ='6. MATRICE'!I22 -> 4 | I14: =G14*H14 -> 0.4
B15: =IF('1. DEMANDE'!G30="","C. Accès aux intrants",IF('1. DEMANDE'!G30="AGRICULTURE","C. Accès aux intrants","C. Accès aux approvisionnements")) -> C. Accès aux intrants | E15: 0.1 | G15: =IF(ISBLANK(F15),E15,F15) -> 0.1 | H15: ='6. MATRICE'!I23 -> 2 | I15: =G15*H15 -> 0.2
B16: D. Accès et position dans le marché | E16: 0.1 | G16: =IF(ISBLANK(F16),E16,F16) -> 0.1 | H16: ='6. MATRICE'!I24 -> 3 | I16: =G16*H16 -> 0.3
B17: E. Qualité des actifs de l'entreprise/exploitation | E17: 0.1 | G17: =IF(ISBLANK(F17),E17,F17) -> 0.1 | H17: ='6. MATRICE'!I25 -> 3 | I17: =G17*H17 -> 0.3
B18: =IF('1. DEMANDE'!G30="","F. Production et Exploitation",IF('1. DEMANDE'!G30="AGRICULTURE","F. Production et Exploitation","F. Risque de continuité de l'exploitation")) -> F. Production et Exploitation | E18: 0.2 | G18: =IF(ISBLANK(F18),E18,F18) -> 0.2 | H18: ='6. MATRICE'!I26 -> 6 | I18: =G18*H18 -> 1.2
B19: G. Environnement | E19: 0.1 | G19: =IF(ISBLANK(F19),E19,F19) -> 0.1 | H19: ='6. MATRICE'!I27 -> 2 | I19: =G19*H19 -> 0.2
B20: H. Capacité de remboursement, Solvabilité et niveau d'endettement | E20: 0.2 | G20: =IF(ISBLANK(F20),E20,F20) -> 0.2 | H20: ='6. MATRICE'!I28 -> 3 | I20: =G20*H20 -> 0.6
B21: =IF((G13+G14+G15+G16+G17+G18+G19+G20)<>100%,"Erreur sur les pondérations","Cote de risque") -> Cote de risque | I21: =IF(B21="Cote de risque",(I13+I14+I15+I16+I17+I18+I19+I20),"ATTENTION") -> 3.3 | J21: =IF(OR(H13="",H14="",H15="",H16="",H17="",H18="",H19="",H20=""),"",ROUNDUP(I21,0)) -> 4
B22: Commentaire sur la cote de risque
B23: =IF(J21=1,PARAMETRAGE!B1,IF(J21=2,PARAMETRAGE!B2,IF(J21=3,PARAMETRAGE!B3,IF(J21=4,PARAMETRAGE!B4,IF(J21=5,PARAMETRAGE!B5,IF(J21=6,PARAMETRAGE!B6,"Veuillez noter tous les critères de risques !")))))) -> Il faut être prudent avec ce genre de client. Soit il est nouveau, soit il s’agir d’un emprunteur de longue date qui a connu une situation adverse avec qui il faut opérer un redressement ou d’un emprunteur qui est financièrement plus serré, mais qui démontre des aptitudes pour progresser. Bien que non obligatoire, le support d’un conseiller technique et/ou de gestion pourrait être suggéré. Appuyez-vous sur les commentaires relatifs aux Ratios de décision pour valider votre recommandation.

Sheet 8. PROPOSITION
B2: Nom et Prénoms du membre : | F2: ='1. DEMANDE'!H15 -> MARIAMA KABA | L2: Agence de : | M2: ='1. DEMANDE'!AD5 -> FORECARIAH
B4: Numéro client /membre : | F4: ='1. DEMANDE'!AH15 -> 10300181501 | K4: Agent de crédit : | M4: ='1. DEMANDE'!AD7 -> MOHAMED MMAH CAMARA
J6: Date d'évaluation : | M6: ='5. RESULTAT'!M7 -> 46093
B8: 17. | C8: RECOMMANDATION DE L'AGENT DE CRÉDIT
C10: Conditions sollicitées | I10: Conditons proposées
C12: Crédit sollicité | D12: ='1. DEMANDE'!H50 -> 300000000 | I12: Crédit proposé | M12: 300000000
C14: Taux d'intérêt | D14: ='1. DEMANDE'!G52 -> 0.03 | I14: Taux d'intérêt | M14: 0.03
C16: Durée du crédit | D16: ='1. DEMANDE'!V50 -> 8 | I16: Durée du crédit (en mois) | M16: 11
C18: Différé | D18: ='1. DEMANDE'!Q52 -> 5 | I18: Différé (en mois) | M18: 9
I20: Nombre d'échéance | M20: 3
C22: Montant échéance | D22: ='1. DEMANDE'!AH52 -> 363000000 | I22: Montant échéance (C+I) | M22: 181000000
C24: Périodicité de remb. | D24: ='1. DEMANDE'!AI50 -> Mensuelle | I24: Intérêts sur crédit | M24: =IF(M12="","",((M22*M20)-M12)) -> 243000000
C26: Garanties proposées | I26: Ratio de couverture des garanties acceptées
C27: =CONCATENATE(,'1. DEMANDE'!J62," ",'1. DEMANDE'!J63," ",'1. DEMANDE'!J64," ",'1. DEMANDE'!J65) -> 3 PERSONNES CAUTIONS ATTESTATION DE CESSION ET PLAN DE MASSE( 1ha/2) ACTE AUTHENTIQUE CONVENTION D'HYPOTHEQUE | I27: Norme > 125% | L27: Ratio = | M27: ='1. DEMANDE'!AG66 -> 648000000
M28: =M12 -> 300000000
I29: =IF(M29>=125%,"Norme respectée",IF(M29<125%,"Hors norme","")) -> Norme respectée | L29: Ratio = | M29: =M27/M28 -> 2.16
C33: Commentaire et signature de l'agent de crédit
B39: 18. | C39: AVIS DU SUPÉRIEUR HIÉRARCHIQUE
B43: 19. | C43: DÉCISION DU COMITÉ DE CRÉDIT
C45: Montant accordé : | G45: GNF | H45: Durée : | L45: mois
C47: Taux d'intérêts : | I47: Observations
C51: Signatures

Sheet TRFM1
B2: Nom et Prénoms du membre : | F2: ='8. PROPOSITION'!F2 -> MARIAMA KABA | J2: Agence de : | K2: ='4. BUDGET FAMILIAL'!L3 -> FORECARIAH
B4: Numéro client /membre : | F4: ='5. RESULTAT'!G5 -> 10300181501 | H4: Agent de crédit : | J4: ='1. DEMANDE'!AD7 -> MOHAMED MMAH CAMARA
I6: Date d'évaluation : | J6: ='4. BUDGET FAMILIAL'!K7 -> 46093
B8: 8. | C8: COMPTE D'EXPLOITATION - TRANSFORMATION 1
B10: Éléments | G10: Unité | H10: Quantité | I10: Prix unitaire | J10: Montant | K10: Observations
B11: Intrants
C12: Matières premières | J12: =I12*H12 -> 0
C13: Matières premières | J13: =I13*H13 -> 0
C14: Intrant1 | J14: =I14*H14 -> 0
C15: Intrant2 | J15: =I15*H15 -> 0
C16: Intrant3 | J16: =I16*H16 -> 0
C17: Intrant4 | J17: =I17*H17 -> 0
C18: Intrant5 | J18: =I18*H18 -> 0
C19: Intrant6 | J19: =I19*H19 -> 0
C20: Intrant7 | J20: =I20*H20 -> 0
C21: Intrant8 | J21: =I21*H21 -> 0
B22: Main d'œuvre et usinage
C23: Main d'œuvre | J23: =I23*H23 -> 0
C24: Usinage | J24: =I24*H24 -> 0
C25: Autre | J25: =I25*H25 -> 0
C26: Autre | J26: =I26*H26 -> 0
C27: Autre | J27: =I27*H27 -> 0
C28: Autre | J28: =I28*H28 -> 0
B29: Coût total de production | J29: =J12+J13+J14+J15+J16+J17+J18+J19+J20+J21+J23+J24+J25+J26+J27+J28 -> 0
B31: Chiffre d'affaires
C32: Produit principal 1 | J32: =I32*H32 -> 0
C33: Produit principal 2 | J33: =I33*H33 -> 0
C34: Sous-Produit 1 | J34: =I34*H34 -> 0
C35: Sous-Produit 2 | J35: =I35*H35 -> 0
C36: Sous-Produit 3 | J36: =I36*H36 -> 0
B37: Total | J37: =J32+J33+J34+J35+J36 -> 0
B39: Marge brute sur coût de production des produits dérivés | J39: =J37-J29 -> 0 | K39: =IF(J39<0,"NÉGATIF",IF(J39>0,"POSITIF","NUL")) -> NUL

Sheet TRFM2
B2: Nom et Prénoms du membre : | F2: =TRFM1!F2 -> MARIAMA KABA | J2: Agence de : | K2: =TRFM1!K2 -> FORECARIAH
B4: Numéro client /membre : | F4: =TRFM1!F4 -> 10300181501 | H4: Agent de crédit : | J4: ='1. DEMANDE'!AD7 -> MOHAMED MMAH CAMARA
I6: Date d'évaluation : | J6: =TRFM1!J6 -> 46093
B8: 9. | C8: COMPTE D'EXPLOITATION - TRANSFORMATION 2
B10: Éléments | G10: Unité | H10: Quantité | I10: Prix unitaire | J10: Montant | K10: Observations
B11: Intrants
C12: Matières premières | J12: =I12*H12 -> 0
C13: Matières premières | J13: =I13*H13 -> 0
C14: Intrant1 | J14: =I14*H14 -> 0
C15: Intrant2 | J15: =I15*H15 -> 0
C16: Intrant3 | J16: =I16*H16 -> 0
C17: Intrant4 | J17: =I17*H17 -> 0
C18: Intrant5 | J18: =I18*H18 -> 0
C19: Intrant6 | J19: =I19*H19 -> 0
C20: Intrant7 | J20: =I20*H20 -> 0
C21: Intrant8 | J21: =I21*H21 -> 0
B22: Main d'œuvre et usinage
C23: Main d'œuvre | J23: =I23*H23 -> 0
C24: Usinage | J24: =I24*H24 -> 0
C25: Autre | J25: =I25*H25 -> 0
C26: Autre | J26: =I26*H26 -> 0
C27: Autre | J27: =I27*H27 -> 0
C28: Autre | J28: =I28*H28 -> 0
B29: Coût total de production | J29: =J12+J13+J14+J15+J16+J17+J18+J19+J20+J21+J23+J24+J25+J26+J27+J28 -> 0
B31: Chiffre d'affaires
C32: Produit principal 1 | J32: =I32*H32 -> 0
C33: Produit principal 2 | J33: =I33*H33 -> 0
C34: Sous-Produit 1 | J34: =I34*H34 -> 0
C35: Sous-Produit 2 | J35: =I35*H35 -> 0
C36: Sous-Produit 3 | J36: =I36*H36 -> 0
B37: Total | J37: =J32+J33+J34+J35+J36 -> 0
B39: Marge brute sur coût de production des produits dérivés | J39: =J37-J29 -> 0 | K39: =IF(J39<0,"NÉGATIF",IF(J39>0,"POSITIF","NUL")) -> NUL

Sheet TRFM3
B2: Nom et Prénoms du membre : | F2: =TRFM2!F2 -> MARIAMA KABA | J2: Agence de : | K2: =TRFM2!K2 -> FORECARIAH
B4: Numéro client /membre : | F4: =TRFM2!F4 -> 10300181501 | H4: Agent de crédit : | J4: ='1. DEMANDE'!AD7 -> MOHAMED MMAH CAMARA
I6: Date d'évaluation : | J6: =TRFM2!J6 -> 46093
B8: 10. | C8: COMPTE D'EXPLOITATION - TRANSFORMATION 3
B10: Éléments | G10: Unité | H10: Quantité | I10: Prix unitaire | J10: Montant | K10: Observations
B11: Intrants
C12: Matières premières | J12: =I12*H12 -> 0
C13: Matières premières | J13: =I13*H13 -> 0
C14: Intrant1 | J14: =I14*H14 -> 0
C15: Intrant2 | J15: =I15*H15 -> 0
C16: Intrant3 | J16: =I16*H16 -> 0
C17: Intrant4 | J17: =I17*H17 -> 0
C18: Intrant5 | J18: =I18*H18 -> 0
C19: Intrant6 | J19: =I19*H19 -> 0
C20: Intrant7 | J20: =I20*H20 -> 0
C21: Intrant8 | J21: =I21*H21 -> 0
B22: Main d'œuvre et usinage
C23: Main d'œuvre | J23: =I23*H23 -> 0
C24: Usinage | J24: =I24*H24 -> 0
C25: Autre | J25: =I25*H25 -> 0
C26: Autre | J26: =I26*H26 -> 0
C27: Autre | J27: =I27*H27 -> 0
C28: Autre | J28: =I28*H28 -> 0
B29: Coût total de production | J29: =J12+J13+J14+J15+J16+J17+J18+J19+J20+J21+J23+J24+J25+J26+J27+J28 -> 0
B31: Chiffre d'affaires
C32: Produit principal 1 | J32: =I32*H32 -> 0
C33: Produit principal 2 | J33: =I33*H33 -> 0
C34: Sous-Produit 1 | J34: =I34*H34 -> 0
C35: Sous-Produit 2 | J35: =I35*H35 -> 0
C36: Sous-Produit 3 | J36: =I36*H36 -> 0
B37: Total | J37: =J32+J33+J34+J35+J36 -> 0
B39: Marge brute sur coût de production des produits dérivés | J39: =J37-J29 -> 0 | K39: =IF(J39<0,"NÉGATIF",IF(J39>0,"POSITIF","NUL")) -> NUL

Sheet COMM
B2: Nom et Prénoms du membre : | F2: =TRFM3!F2 -> MARIAMA KABA | J2: Agence de : | K2: =TRFM3!K2 -> FORECARIAH
B4: Numéro client /membre : | F4: =TRFM3!F4 -> 10300181501 | H4: Agent de crédit : | J4: ='1. DEMANDE'!AD7 -> MOHAMED MMAH CAMARA
I6: Date d'évaluation : | J6: =TRFM3!J6 -> 46093
B8: 11. | C8: COMPTE D'EXPLOITATION - | F8: =IF('1. DEMANDE'!G30="AGRICULTURE","COMMERCIALISATION","ACTIVITÉ COMMERCE") -> COMMERCIALISATION
B10: Éléments | G10: Unité | H10: Quantité | I10: Prix unitaire | J10: Montant | K10: Observations
B11: =IF('1. DEMANDE'!G30="AGRICULTURE","Achats de produits agricoles","Achats de marchandises et les frais variables d'achat") -> Achats de produits agricoles
C12: Frais variables1 | J12: =I12*H12 -> 0
C13: Frais variables2 | J13: =I13*H13 -> 0
C14: Frais variables3 | J14: =I14*H14 -> 0
C15: Frais variables4 | J15: =I15*H15 -> 0
C16: Frais variables5 | J16: =I16*H16 -> 0
C17: Frais variables6 | J17: =I17*H17 -> 0
C18: Frais variables7 | J18: =I18*H18 -> 0
C19: Frais variables8 | J19: =I19*H19 -> 0
C20: Frais variables9 | J20: =I20*H20 -> 0
C21: Frais variables10 | J21: =I21*H21 -> 0
C22: Frais variables11 | J22: =I22*H22 -> 0
C23: Frais variables12 | J23: =I23*H23 -> 0
B24: Coût d'achats des produits agricoles | J24: =J12+J13+J14+J15+J16+J17+J18+J19+J20+J21+J22+J23 -> 0
B26: Chiffre d'affaires
C27: Vente 1 | J27: =I27*H27 -> 0
C28: Vente 2 | J28: =I28*H28 -> 0
C29: Vente 3 | J29: =I29*H29 -> 0
C30: Vente 4 | J30: =I30*H30 -> 0
C31: Vente 5 | J31: =I31*H31 -> 0
B32: Total | J32: =J27+J28+J29+J30+J31 -> 0
B34: =IF('1. DEMANDE'!G30="AGRICULTURE","Marge brute sur coût d'achats des produits agricoles","Marge sur coût d'achat des marchandises") -> Marge brute sur coût d'achats des produits agricoles | J34: =J32-J24 -> 0 | K34: =IF(J34<0,"NÉGATIF",IF(J34>0,"POSITIF","NUL")) -> NUL

Sheet ANIMAL
B2: Nom et Prénoms du membre : | F2: =TRFM3!F2 -> MARIAMA KABA | J2: Agence de : | K2: =TRFM3!K2 -> FORECARIAH
B4: Numéro client /membre : | F4: =TRFM3!F4 -> 10300181501 | H4: Agent de crédit : | J4: ='1. DEMANDE'!AD7 -> MOHAMED MMAH CAMARA
I6: Date d'évaluation : | J6: =TRFM3!J6 -> 46093
B8: 12. | C8: COMPTE D'EXPLOITATION - PRODUCTION ANIMALE
B10: Éléments | G10: Unité | H10: Quantité | I10: Prix unitaire | J10: Montant | K10: Observations
B11: Achats d'animaux et frais d'alimentation et d'entretien
C12: Frais variables0 | J12: =I12*H12 -> 0
C13: Frais variables1 | J13: =I13*H13 -> 0
C14: Frais variables2 | J14: =I14*H14 -> 0
C15: Frais variables3 | J15: =I15*H15 -> 0
C16: Frais variables4 | J16: =I16*H16 -> 0
C17: Frais variables5 | J17: =I17*H17 -> 0
C18: Frais variables6 | J18: =I18*H18 -> 0
C19: Frais variables7 | J19: =I19*H19 -> 0
C20: Frais variables8 | J20: =I20*H20 -> 0
C21: Frais variables9 | J21: =I21*H21 -> 0
C22: Frais variables10 | J22: =I22*H22 -> 0
C23: Frais variables11 | J23: =I23*H23 -> 0
B24: Coût de production | J24: =J12+J13+J14+J15+J16+J17+J18+J19+J20+J21+J22+J23 -> 0
B26: Chiffre d'affaires
C27: Vente d'animaux 1 | J27: =I27*H27 -> 0
C28: Vente d'animaux 2 | J28: =I28*H28 -> 0
C29: Vente d'animaux 3 | J29: =I29*H29 -> 0
C30: Vente d'animaux 4 | J30: =I30*H30 -> 0
C31: Vente d'animaux 5 | J31: =I31*H31 -> 0
B32: Total | J32: =J27+J28+J29+J30+J31 -> 0
B34: Marge brute sur coût de production animale | J34: =J32-J24 -> 0 | K34: =IF(J34<0,"NÉGATIF",IF(J34>0,"POSITIF","NUL")) -> NUL

Sheet BIENS
B2: Nom et Prénoms du membre : | C2: =TRFM3!F2 -> MARIAMA KABA | F2: Agence de : | H2: =TRFM3!K2 -> FORECARIAH
B4: Numéro client /membre : | C4: =TRFM3!F4 -> 10300181501 | F4: Agent de crédit : | H4: ='1. DEMANDE'!AD7 -> MOHAMED MMAH CAMARA
I6: Date d'évaluation : | J6: =TRFM3!J6 -> 46093
B8: EVALUATION DES BIENS (Commerciaux et personnels) DU CLIENT - Choix de la garantie
B10: Biens à usage commercial
B12: Terrains et constructions | J12: en milliers de GNF
B13: Nature du bien | C13: Localisation et adresse complète | E13: Date d'acquisition | F13: Superficie | G13: Coût d'acquisition | H13: Valeur marchande | I13: Maximum applicable % | J13: Valeur d'emprunt
J14: =IF(H14="","",H14*I14)
J15: =IF(H15="","",H15*I15)
J16: =IF(H16="","",H16*I16)
J17: =IF(H17="","",H17*I17)
B18: Total partiel -Terrains et constructions | G18: =IF(SUM(G14:G17)>0,SUM(G14:G17)," ") | H18: =IF(SUM(H14:H17)>0,SUM(H14:H17)," ") | J18: =IF(SUM(J16:J17)>0,SUM(J14:J17)," ")
B20: Matériels de transport | J20: en milliers de GNF
B21: Nature du bien | C21: Marque # Modèle / année/Numéro de série | E21: Immatriculation | F21: Date d'acquisition | G21: Coût d'acquisition | H21: Valeur marchande | I21: Maximum applicable % | J21: Valeur d'emprunt
J22: =IF(H22="","",H22*I22)
J23: =IF(H23="","",H23*I23)
J24: =IF(H24="","",H24*I24)
J25: =IF(H25="","",H25*I25)
B26: Total partiel - Matériels de transport | G26: =IF(SUM(G22:G25)>0,SUM(G22:G25)," ") | H26: =IF(SUM(H22:H25)>0,SUM(H22:H25)," ") | J26: =IF(SUM(J22:J25)>0,SUM(J22:J25)," ")
B28: Mobilier et matériel (autres) | J28: en milliers de GNF
B29: Description | C29: Description / Modèle / Marque et série | F29: Date d'acquisition | G29: Coût d'acquisition | H29: Valeur marchande | I29: Maximum applicable % | J29: Valeur d'emprunt
J30: =IF(H30="","",H30*I30)
J31: =IF(H31="","",H31*I31)
J32: =IF(H32="","",H32*I32)
J33: =IF(H33="","",H33*I33)
J34: =IF(H34="","",H34*I34)
J35: =IF(H35="","",H35*I35)
B36: Total partiel - Mobilier et matériel | G36: =IF(SUM(G30:G35)>0,SUM(G30:G35)," ") | H36: =IF(SUM(H30:H35)>0,SUM(H30:H35)," ") | J36: =IF(SUM(J30:J35)>0,SUM(J30:J35)," ")
B38: Inventaires des stocks et produits divers | J38: en milliers de GNF
B39: Nature et description des articles (matières premières, produits semis-finis, production, etc…) | F39: Date d'acquisition | G39: Coût d'acquisition | H39: Valeur marchande | I39: Maximum applicable % | J39: Valeur d'emprunt
J40: =IF(H40="","",H40*I40)
J41: =IF(H41="","",H41*I41)
J42: =IF(H42="","",H42*I42)
J43: =IF(H43="","",H43*I43)
J44: =IF(H44="","",H44*I44)
J45: =IF(H45="","",H45*I45)
J46: =IF(H46="","",H46*I46)
J47: =IF(H47="","",H47*I47)
J48: =IF(H48="","",H48*I48)
J49: =IF(H49="","",H49*I49)
J50: =IF(H50="","",H50*I50)
B51: Total partiel - Inventaire | G51: =IF(SUM(G40:G50)>0,SUM(G40:G50)," ") | H51: =IF(SUM(H40:H50)>0,SUM(H40:H50)," ") | J51: =IF(SUM(J40:J50)>0,SUM(J40:J50)," ")
B53: Biens personnels
J54: en milliers de GNF
B55: Nature et Description | D55: Référence du bien | F55: Date d'acquisition | G55: Coût d'acquisition | H55: Valeur marchande | I55: Observations
B70: Valeur totale des biens personnels | G70: =IF(SUM(G56:G69)>0,SUM(G56:G69)," ") | H70: =IF(SUM(H56:H69)>0,SUM(H56:H69)," ")
