Workbook
Name Activites1: CRG!$B$1:$F$1
Name AGRICULTURE: CRG!$A$2:$A$5
Name Amorti: #REF!
Name ARTISANAT: CRG!$C$2:$C$9
Name Autre: CRG!$F$1:$F$1
Name Autres_charges_dexploitation: #REF!
Name ChiffreAffaire: CRG!$Y$1:$Y$3
Name COMMERCE: CRG!$B$2:$B$8
Name Commercialisation: CRG!$J$2:$J$14
Name Immobilisations: CRG!$A$15:$A$20
Name INDUSTRIE: CRG!$E$2:$E$3
Name MargeBrute: CRG!$Z$1:$Z$4
Name niveau_de_risque: #REF!
Name Objet_crédit: #REF!
Name PDA: #REF!
Name Periode_analyse: CRG!$AC$1:$AC$7
Name Periodicite: CRG!$L$2:$L$8
Name Production_animale: CRG!$G$2:$G$9
Name Production_vegetale: CRG!$H$2:$H$14
Name Production_végétale: CRG!$H$2:$H$14
Name SERVICE: CRG!$D$2:$D$7
Name Simulation: CRG!$AE$1:$AE$2
Name Transformation: CRG!$I$2:$I$14

Sheet CRG
A1: AGRICULTURE | B1: COMMERCE | C1: ARTISANAT | D1: SERVICE | E1: INDUSTRIE | F1: Autre | G1: Production_animale | H1: Production_vegetale | I1: Transformation | J1: Commercialisation | K1: Autre | L1: Périodicité | N1: Durée Amorts (mois) | O1: Valeur d'acquisition | P1: mensualité | S1: CA | V1: Objet du crédit : | W1: ='Collecte des données'!I12 -> Fonds de roulement | Y1: Hyp. Faib. | Z1: % Recom. | AA1: =IF('Collecte des données'!$I$49="OUI",CRG!W18,CRG!W17) -> 0.34489796 | AB1: Cycle : | AC1: Modifier cycle | AE1: ='Collecte des données'!I18 -> 60000000
A2: Production_animale | B2: Habillement | C2: Menuiserie | D2: Formation | E2: Fabrication | F2: Divers | G2: Bovin | H2: Agrumes | I2: Agrumes | J2: Agrumes | L2: Mensuelle | N2: =Amorts!F6 -> 96 | O2: =Amorts!G6 -> 8000000 | P2: =O2/N2 -> 83333.333 | R2: Janvier | S2: =COUNTA('Collecte des données'!$C$34:$C$36) -> 1 | T2: =IF(OR(S2=2,S2=3),1,0) -> 0 | V2: Coût de l'investissement : | W2: =IF(Analyse!Q70="",'Collecte des données'!I14,Analyse!Q70) -> 0 | Y2: Hyp. Moy. | Z2: Fort % | AA2: =IF('Collecte des données'!$I$49="OUI",CRG!W19,CRG!W17) -> 0.55 | AC2: Mensuelle | AE2: 0
A3: Production_vegetale | B3: Restauration | C3: Soudure | D3: Assistance | E3: Autre | G3: Aquaculture | H3: Anacarde | I3: Anacarde | J3: Anacarde | L3: Bimestrielle | N3: =Amorts!F7 -> 96 | O3: =Amorts!G7 -> 6000000 | P3: =O3/N3 -> 62500 | R3: Février | S3: =COUNTA('Collecte des données'!$D$34:$D$36) -> 1 | T3: =IF(OR(S3=2,S3=3),1,0) -> 0 | V3: Autres dépenses invest. | W3: =IF(Analyse!Q71="",'Collecte des données'!I15,Analyse!Q71) -> 0 | Y3: Hyp. Elev. | Z3: Faible % | AA3: =IF('Collecte des données'!$I$49="OUI",CRG!W20,CRG!W17) -> 0.13333333 | AC3: Bimestrielle
A4: Transformation | B4: Alimentation | C4: Coiffure | D4: Service divers | G4: Aviculture | H4: Ananas | I4: Ananas | J4: Ananas | L4: Trimestrielle | N4: =Amorts!F8 -> 96 | O4: =Amorts!G8 -> 3000000 | P4: =O4/N4 -> 31250 | R4: Mars | S4: =COUNTA('Collecte des données'!$E$34:$E$36) -> 1 | T4: =IF(OR(S4=2,S4=3),1,0) -> 0 | V4: Apport personnel | W4: =IF(Analyse!Q72="",'Collecte des données'!I16,Analyse!Q72) -> 0 | Z4: % Declar | AA4: =IF('Collecte des données'!P47="",0%,'Collecte des données'!P47) -> 0.34 | AC4: Trimestrielle | BK4: GRILLE D'ANALYSE DES DEMANDES DE CRÉDITS DES PETITES ET MOYENNES ENTREPRISES
A5: Commercialisation | B5: Cosmétique | C5: Mécanique | D5: Auto-école | G5: Caprin | H5: Arachide | I5: Arachide | J5: Arachide | L5: Quadrimestrielle | N5: =Amorts!F9 -> 96 | O5: =Amorts!G9 -> 2000000 | P5: =O5/N5 -> 20833.333 | R5: Avril | S5: =COUNTA('Collecte des données'!$F$34:$F$36) -> 1 | T5: =IF(OR(S5=2,S5=3),1,0) -> 0 | AA5: =IF(Analyse!G41=CRG!Z1,CRG!AA1,IF(Analyse!G41=CRG!Z2,CRG!AA2,IF(Analyse!G41=CRG!Z3,CRG!AA3,IF(Analyse!G41=CRG!Z4,CRG!AA4,"")))) -> 0.34489796 | AC5: Quadrimestrielle
B6: Mercerie | C6: Maçonnerie | D6: École - Collège | G6: Ovin | H6: Coton | I6: Coton | J6: Igname | L6: Semestrielle | N6: =Amorts!F10 -> 96 | O6: =Amorts!G10 -> 2500000 | P6: =O6/N6 -> 26041.667 | R6: Mai | S6: =COUNTA('Collecte des données'!$G$34:$G$36) -> 1 | T6: =IF(OR(S6=2,S6=3),1,0) -> 0 | V6: Estimation CA Hebdom | W6: ='Collecte des données'!I29*4 -> 58000000 | AC6: Semestrielle
B7: Vaisselle -Émaux | C7: Cordonnerie | D7: Autre | G7: Pêche | H7: Igname | I7: Igname | J7: Maïs | L7: Annuelle | N7: =Amorts!F11 -> 96 | O7: =Amorts!G11 -> 2500000 | P7: =O7/N7 -> 26041.667 | R7: Juin | S7: =COUNTA('Collecte des données'!$H$34:$H$36) -> 1 | T7: =IF(OR(S7=2,S7=3),1,0) -> 0 | V7: Estimation CA mensuel | W7: ='Collecte des données'!I30 -> 58000000 | AC7: Annuelle
B8: Autre | C8: Coiffure | G8: Pisciculture | H8: Maïs | I8: Maïs | J8: Mangue | L8: Unique | N8: =Amorts!F12 -> 96 | O8: =Amorts!G12 -> 35000000 | P8: =O8/N8 -> 364583.33 | R8: Juillet | S8: =COUNTA('Collecte des données'!$I$34:$I$36) -> 1 | T8: =IF(OR(S8=2,S8=3),1,0) -> 0 | V8: CA fort mensuel | W8: =IF('Collecte des données'!O34="","",'Collecte des données'!O34) -> 25000000 | X8: =COUNTA('Collecte des données'!C34:N34) -> 5 | Y8: =IF(X8=MAX($X$8:$X$10),W8,0) -> 25000000 | AC8: =IF(Analyse!I9="Modifier cycle",'Collecte des données'!I20,Analyse!I9) -> Mensuelle
C9: Autre | G9: Autre | H9: Mangue | I9: Mangue | J9: Manioc | N9: =Amorts!F13 -> 0 | O9: =Amorts!G13 -> 0 | P9: =O9/N9 -> #DIV/0! | R9: Août | S9: =COUNTA('Collecte des données'!$J$34:$J$36) -> 1 | T9: =IF(OR(S9=2,S9=3),1,0) -> 0 | V9: CA moyen mensuel | W9: =IF('Collecte des données'!O35="","",'Collecte des données'!O35) -> 16000000 | X9: =COUNTA('Collecte des données'!C35:N35) -> 4 | Y9: =IF(X9=MAX($X$8:$X$10),W9,0) -> 0 | AC9: =IF(AC8=AC2,1,IF(AC8=AC3,2,IF(AC8=AC4,3,IF(AC8=AC5,4,IF(AC8=AC6,6,IF(AC8=AC7,12,IF(AC8="Unique",1,0))))))) -> 1
H10: Manioc | I10: Manioc | J10: Maraîchage | N10: =Amorts!F14 -> 0 | O10: =Amorts!G14 -> 0 | P10: =O10/N10 -> #DIV/0! | R10: Septembre | S10: =COUNTA('Collecte des données'!$K$34:$K$36) -> 1 | T10: =IF(OR(S10=2,S10=3),1,0) -> 0 | V10: CA faible mensuel | W10: =IF('Collecte des données'!O36="","",'Collecte des données'!O36) -> 10500000 | X10: =COUNTA('Collecte des données'!C36:N36) -> 3 | Y10: =IF(X10=MAX($X$8:$X$10),W10,0) -> 0
H11: Maraîchage | I11: Niébé | J11: Niebe | N11: =Amorts!F15 -> 0 | O11: =Amorts!G15 -> 0 | P11: =O11/N11 -> #DIV/0! | R11: Octobre | S11: =COUNTA('Collecte des données'!$L$34:$L$36) -> 1 | T11: =IF(OR(S11=2,S11=3),1,0) -> 0 | V11: CA hebdo mensuel | W11: =IF('Collecte des données'!M44=0,"",'Collecte des données'!M44) -> 58000000 | AC11: =IF('Collecte des données'!I20=AC2,1,IF('Collecte des données'!I20=AC3,2,IF('Collecte des données'!I20=AC4,3,IF('Collecte des données'!I20=AC5,4,IF('Collecte des données'!I20=AC6,6,IF('Collecte des données'!I20=AC7,12,0)))))) -> 1 | AD11: Nbre Cycle
B12: 45595 | H12: Niébé | I12: Palmier à huile | J12: Riz | N12: =Amorts!F16 -> 0 | O12: =Amorts!G16 -> 0 | P12: =O12/N12 -> #DIV/0! | R12: Novembre | S12: =COUNTA('Collecte des données'!$M$34:$M$36) -> 1 | T12: =IF(OR(S12=2,S12=3),1,0) -> 0 | V12: CA mensuel dernère vente | W12: ='Collecte des données'!M70 -> 441000000 | AB12: Durée 1 soll | AC12: ='Collecte des données'!I19 -> 12 | AD12: =AC12/AC9 -> 12
H13: Palmier à huile | I13: Riz | J13: Soja | N13: =Amorts!F17 -> 0 | O13: =Amorts!G17 -> 0 | P13: =O13/N13 -> #DIV/0! | R13: Décembre | S13: =COUNTA('Collecte des données'!$N$34:$N$36) -> 1 | T13: =IF(OR(S13=2,S13=3),1,0) -> 0 | V13: CA Hyoth. Élevée | W13: =IF('Collecte des données'!I12="Bon de commande",CRG!W12,MAX(W6:W12)) -> 441000000 | Y13: =IF('Collecte des données'!I12="Bon de commande",CRG!W12,W13) -> 441000000 | AB13: Nbre Cycle | AD13: Nbre Cycle
A14: Immobilisations | H14: Autre | I14: Autre | J14: Autre | N14: =Amorts!F18 -> 0 | O14: =Amorts!G18 -> 0 | P14: =O14/N14 -> #DIV/0! | S14: =IF(T14>0,1,0) -> 0 | T14: =SUM(T2:T13) -> 0 | V14: CA Hyoth. Moyenne | W14: =IF('Collecte des données'!I12="Bon de commande",CRG!W12,AVERAGE(W6:W12)) -> 95214286 | Y14: =IF('Collecte des données'!I12="Bon de commande",CRG!W12,W14) -> 95214286 | AB14: Durée propo | AC14: =Analyse!P90 -> 12 | AD14: =AC14/AC9 -> 12
A15: Bâtiments et magasin | N15: =Amorts!F19 -> 0 | O15: =Amorts!G19 -> 0 | P15: =O15/N15 -> #DIV/0! | V15: CA Hyoth. Faible | W15: =IF('Collecte des données'!I12="Bon de commande",CRG!W12,MIN(W6:W12)) -> 10500000 | Y15: =IF('Collecte des données'!I12="Bon de commande",CRG!W12,W15) -> 10500000
A16: Installations et agencements | N16: =Amorts!F20 -> 0 | O16: =Amorts!G20 -> 0 | P16: =O16/N16 -> #DIV/0! | V16: CA recommandé | Y16: =IF(Analyse!G39=CRG!Y1,CRG!Y15,IF(Analyse!G39=CRG!Y2,W14,IF(Analyse!G39=CRG!Y3,W13,""))) -> 441000000
A17: Matériels industriels | N17: =Amorts!F21 -> 0 | O17: =Amorts!G21 -> 0 | P17: =O17/N17 -> #DIV/0! | V17: Taux MB fixé | W17: ='Collecte des données'!P47 -> 0.34 | AB17: Fraction Crédit | AC17: ='Collecte des données'!I18/'Collecte des données'!I22 -> 5000000 | AD17: =Analyse!P89/Analyse!T90 -> 5000000
A18: Mobilier de bureau | N18: =Amorts!F22 -> 0 | O18: =Amorts!G22 -> 0 | P18: =O18/N18 -> #DIV/0! | V18: Taux MB Calculé | W18: ='Collecte des données'!T70 -> 0.34489796 | AA18: Sollicité | AB18: Proposé | AC18: Fonds de roulem | AD18: Investiss
A19: Matériel informatique | N19: =Amorts!F23 -> 0 | O19: =Amorts!G23 -> 0 | P19: =O19/N19 -> #DIV/0! | V19: TMB élevé | W19: =MAX('Collecte des données'!T55:T69) -> 0.55 | Z19: (Investis) R.1 | AA19: =IFERROR((AA28/'Collecte des données'!I23),"Informations manquantes") -> 1.9928173 | AB19: =IFERROR((AA28/Analyse!P91),"Informations manquantes") -> 1.9928173 | AC19: =IFERROR(((AA28+AC17)/'Collecte des données'!I23),"Informations manquantes") -> 2.0625523 | AD19: =IFERROR(((AA28+AD17)/Analyse!P91),"Information manquante") -> 2.0625523
A20: Matériel de transport | N20: =Amorts!F24 -> 0 | O20: =Amorts!G24 -> 0 | P20: =O20/N20 -> #DIV/0! | V20: TMB faible | W20: =MIN('Collecte des données'!T55:T69) -> 0.13333333 | Z20: R.2 | AA20: =IFERROR((Analyse!I27/Analyse!I32),"Information manquante") -> 1 | AB20: =AA20 -> 1
A21: Autres immobilisations | N21: =Amorts!F25 -> 0 | O21: =Amorts!G25 -> 0 | P21: =O21/N21 -> #DIV/0! | Z21: R.3 | AA21: =IFERROR(((Analyse!I23+Analyse!I24)/(Analyse!I29+Analyse!I30)),"Information manquante") -> Information manquante | AB21: =AA21 -> Information manquante | BM21: Septembre 2024
N22: =Amorts!F26 -> 0 | O22: =Amorts!G26 -> 0 | P22: =O22/N22 -> #DIV/0! | V22: Marge Brute | W22: =Y16*AA5 -> 152100000 | Z22: R.4 | AA22: =IFERROR(((Analyse!I28+Analyse!I29+Analyse!I30+'Collecte des données'!I18)/(Analyse!I32+'Collecte des données'!I18)),"Information manquante") -> 0.28570068 | AB22: =IFERROR(((Analyse!I28+Analyse!I29+Analyse!I30+Analyse!P89)/(Analyse!I32+Analyse!P89)),"Information manquante") -> 0.28570068
N23: =Amorts!F27 -> 0 | O23: =Amorts!G27 -> 0 | P23: =O23/N23 -> #DIV/0! | V23: CA Marchandises vendues | W23: =Y16-W22 -> 288900000 | Z23: R.5 | AA23: =IFERROR((Analyse!I61/(Analyse!I57+Analyse!I61)),"Information manquante") -> 0.01757217 | AB23: =AA23 -> 0.01757217
N24: =Amorts!F28 -> 0 | O24: =Amorts!G28 -> 0 | P24: =O24/N24 -> #DIV/0! | V24: Salaire | W24: ='Collecte des données'!P179 -> 520000 | Z24: R.6 | AA24: =IFERROR(('Collecte des données'!I24/'Collecte des données'!I18),"Information manquante") -> 1.7666667 | AB24: =IFERROR(('Collecte des données'!I24/Analyse!P89),"Information manquante") -> 1.7666667
N25: =Amorts!F29 -> 0 | O25: =Amorts!G29 -> 0 | P25: =O25/N25 -> #DIV/0! | V25: Prélèment de l'entrepreneur | W25: =W62 -> 0 | Z25: (Fonds de roul.)R.1 | AA25: =IFERROR(((Analyse!I59+Analyse!I61+AC17)/'Collecte des données'!I23),"Informations manquantes") -> 2.0625523 | AB25: =IFERROR(((Analyse!I59+Analyse!I61+AD17)/Analyse!P91),"Information manquante") -> 2.0625523
N26: =Amorts!F30 -> 0 | O26: =Amorts!G30 -> 0 | P26: =O26/N26 -> #DIV/0! | V26: Loyers | W26: ='Collecte des données'!P176 -> 1300000 | Z26: R1 retenu | AA26: =IF('Collecte des données'!I12="Fonds de roulement",CRG!AA25,CRG!AA19) -> 2.0625523 | AB26: =IF('Collecte des données'!I12="Fonds de roulement",AB25,AB19) -> 2.0625523
N27: =Amorts!F31 -> 0 | O27: =Amorts!G31 -> 0 | P27: =O27/N27 -> #DIV/0! | V27: Transport | W27: ='Collecte des données'!P197+'Collecte des données'!P200+'Collecte des données'!P203 -> 6000000
N28: =Amorts!F32 -> 0 | O28: =Amorts!G32 -> 0 | P28: =O28/N28 -> #DIV/0! | V28: Electricité, eau, téléphone | W28: ='Collecte des données'!P188+'Collecte des données'!P191+'Collecte des données'!P194 -> 1090000 | Z28: =IF(Analyse!E90="Capacité de remb. déclarée",1,2) -> 2 | AA28: =IF(Analyse!E90="Capacité de remb. déclarée",CRG!AA30,CRG!AA29) -> 142885000
N29: =Amorts!F33 -> 0 | O29: =Amorts!G33 -> 0 | P29: =O29/N29 -> #DIV/0! | V29: Fournitures et autres besoins | W29: ='Collecte des données'!P182 -> 0 | Z29: Capacité calculée | AA29: =Analyse!I63 -> 142885000
N30: =Amorts!F34 -> 0 | O30: =Amorts!G34 -> 0 | P30: =O30/N30 -> #DIV/0! | V30: Entretien et réparation | W30: ='Collecte des données'!P206 -> 200000 | Z30: Capacité déclarée | AA30: =IF('Collecte des données'!I25="",0,'Collecte des données'!I25) -> 6700000
N31: =Amorts!F35 -> 0 | O31: =Amorts!G35 -> 0 | P31: =O31/N31 -> #DIV/0! | V31: Carburant et lubrifiants | W31: ='Collecte des données'!P209 -> 720000
N32: =Amorts!F36 -> 0 | O32: =Amorts!G36 -> 0 | P32: =O32/N32 -> #DIV/0! | V32: Frais de publicité et promotion | W32: ='Collecte des données'!P185 -> 0
N33: =Amorts!F37 -> 0 | O33: =Amorts!G37 -> 0 | P33: =O33/N33 -> #DIV/0! | V33: Redevance, impôts et taxes | W33: ='Collecte des données'!P221 -> 85000
N34: =Amorts!F38 -> 0 | O34: =Amorts!G38 -> 0 | P34: =O34/N34 -> #DIV/0! | V34: Frais bancaires, Intérêts payés | W34: ='Collecte des données'!P215+'Collecte des données'!P218 -> 1800000
N35: =Amorts!F39 -> 0 | O35: =Amorts!G39 -> 0 | P35: =O35/N35 -> #DIV/0! | V35: Échance autre crédit | W35: ='Collecte des données'!P230 -> 0
N36: =Amorts!F40 -> 0 | O36: =Amorts!G40 -> 0 | P36: =O36/N36 -> #DIV/0! | V36: Diverses charges | W36: ='Collecte des données'!P212+'Collecte des données'!P224+'Collecte des données'!P233 -> 0
N37: =Amorts!F41 -> 0 | O37: =Amorts!G41 -> 0 | P37: =O37/N37 -> #DIV/0! | V37: Provisions | W37: ='Collecte des données'!P227 -> 0
N38: =Amorts!F42 -> 0 | O38: =Amorts!G42 -> 0 | P38: =O38/N38 -> #DIV/0! | V38: Amortissement | W38: =SUMIFS(Amorts!H6:'Amorts'!H105,Amorts!S6:'Amorts'!S105,"OUI") -> 614583.33
N39: =Amorts!F43 -> 0 | O39: =Amorts!G43 -> 0 | P39: =O39/N39 -> #DIV/0! | V39: Terrains | W39: ='Collecte des données'!P76 -> 0
N40: =Amorts!F44 -> 0 | O40: =Amorts!G44 -> 0 | P40: =O40/N40 -> #DIV/0! | V40: Bâtiments et magasin | W40: =SUMIFS(Amorts!$K$6:'Amorts'!$K$105,Amorts!$D$6:$D$105,V40) -> 2500000
N41: =Amorts!F45 -> 0 | O41: =Amorts!G45 -> 0 | P41: =O41/N41 -> #DIV/0! | V41: Installations et agencements | W41: =SUMIFS(Amorts!$K$6:'Amorts'!$K$105,Amorts!$D$6:$D$105,V41) -> 0
N42: =Amorts!F46 -> 0 | O42: =Amorts!G46 -> 0 | P42: =O42/N42 -> #DIV/0! | V42: Matériels industriels | W42: =SUMIFS(Amorts!$K$6:'Amorts'!$K$105,Amorts!$D$6:$D$105,V42) -> 0
N43: =Amorts!F47 -> 0 | O43: =Amorts!G47 -> 0 | P43: =O43/N43 -> #DIV/0! | V43: Mobilier de bureau | W43: =SUMIFS(Amorts!$K$6:'Amorts'!$K$105,Amorts!$D$6:$D$105,V43) -> 21500000
N44: =Amorts!F48 -> 0 | O44: =Amorts!G48 -> 0 | P44: =O44/N44 -> #DIV/0! | V44: Matériel informatique | W44: =SUMIFS(Amorts!$K$6:'Amorts'!$K$105,Amorts!$D$6:$D$105,V44) -> 0
N45: =Amorts!F49 -> 0 | O45: =Amorts!G49 -> 0 | P45: =O45/N45 -> #DIV/0! | V45: Matériel de transport | W45: =SUMIFS(Amorts!$K$6:'Amorts'!$K$105,Amorts!$D$6:$D$105,V45) -> 20000000
N46: =Amorts!F50 -> 0 | O46: =Amorts!G50 -> 0 | P46: =O46/N46 -> #DIV/0! | V46: Autres immobilisations | W46: ='Collecte des données'!P94+'Collecte des données'!P97 -> 6000000
N47: =Amorts!F51 -> 0 | O47: =Amorts!G51 -> 0 | P47: =O47/N47 -> #DIV/0! | V47: Stocks | W47: =IF('Collecte des données'!I101="OUI",'Collecte des données'!M121,'Collecte des données'!P100) -> 62510000
N48: =Amorts!F52 -> 0 | O48: =Amorts!G52 -> 0 | P48: =O48/N48 -> #DIV/0! | V48: Créances, Clients | W48: =W49+W50 -> 16500000
V49: Moins de trois mois | W49: ='Collecte des données'!J129 -> 6500000
V50: Plus de trois mois | W50: ='Collecte des données'!J128 -> 10000000
N51: =Amorts!F53 -> 0 | O51: =Amorts!G53 -> 0 | P51: =O51/N51 -> #DIV/0! | V51: Trésorerie (Caisse+Banque) | W51: ='Collecte des données'!P132+'Collecte des données'!P135+'Collecte des données'!P138+'Collecte des données'!P141 -> 21000000
N52: =Amorts!F54 -> 0 | O52: =Amorts!G54 -> 0 | P52: =O52/N52 -> #DIV/0!
N53: =Amorts!F55 -> 0 | O53: =Amorts!G55 -> 0 | P53: =O53/N53 -> #DIV/0! | V53: Passif
N54: =Amorts!F56 -> 0 | O54: =Amorts!G56 -> 0 | P54: =O54/N54 -> #DIV/0! | V54: Situation nette (Capitaux propres)
N55: =Amorts!F57 -> 0 | O55: =Amorts!G57 -> 0 | P55: =O55/N55 -> #DIV/0! | V55: Emprunt à plus d'un an | W55: ='Collecte des données'!P147 -> 0
N56: =Amorts!F58 -> 0 | O56: =Amorts!G58 -> 0 | P56: =O56/N56 -> #DIV/0! | V56: Emprunt à moins d'un an | W56: ='Collecte des données'!P150 -> 0
N57: =Amorts!F59 -> 0 | O57: =Amorts!G59 -> 0 | P57: =O57/N57 -> #DIV/0! | V57: Autres dettes | W57: ='Collecte des données'!P153+'Collecte des données'!P156+'Collecte des données'!P159+'Collecte des données'!P162+'Collecte des données'!P165+'Collecte des données'!P168+'Collecte des données'!P171 -> 0
N58: =Amorts!F60 -> 0 | O58: =Amorts!G60 -> 0 | P58: =O58/N58 -> #DIV/0! | V58: TOTAL DETTES | W58: =W55+W56+W57 -> 0
N59: =Amorts!F61 -> 0 | O59: =Amorts!G61 -> 0 | P59: =O59/N59 -> #DIV/0!
N60: =Amorts!F62 -> 0 | O60: =Amorts!G62 -> 0 | P60: =O60/N60 -> #DIV/0! | V60: Autres revenus | W60: ='Collecte des données'!P280+'Collecte des données'!P282+'Collecte des données'!P284+'Collecte des données'!P286 -> 2500000
N61: =Amorts!F63 -> 0 | O61: =Amorts!G63 -> 0 | P61: =O61/N61 -> #DIV/0! | V61: Dépenses familiales | W61: ='Collecte des données'!P245+'Collecte des données'!P248+'Collecte des données'!P251+'Collecte des données'!P254+'Collecte des données'!P257+'Collecte des données'!P260+'Collecte des données'!P263+'Collecte des données'!P266+'Collecte des données'!P269+'Collecte des données'!P272 -> 5500000
N62: =Amorts!F64 -> 0 | O62: =Amorts!G64 -> 0 | P62: =O62/N62 -> #DIV/0! | V62: Prélèment (Dépenses personnelles) | W62: =IF('Collecte des données'!I274="OUI",CRG!W61,IF('Collecte des données'!J238="OUI",'Collecte des données'!P238,0)) -> 0
N63: =Amorts!F65 -> 0 | O63: =Amorts!G65 -> 0 | P63: =O63/N63 -> #DIV/0!
N64: =Amorts!F66 -> 0 | O64: =Amorts!G66 -> 0 | P64: =O64/N64 -> #DIV/0!
N65: =Amorts!F67 -> 0 | O65: =Amorts!G67 -> 0 | P65: =O65/N65 -> #DIV/0! | V65: Coût d'achats pour 1 cycle d'exploitation) | W65: =IF(Analyse!I40="","",(Analyse!I40*CRG!X65)) -> 288900000 | X65: =IF(Analyse!L76="",1,Analyse!L76) -> 1 | Y65: =IF(Analyse!Q76="",W65,Analyse!Q76) -> 288900000
N66: =Amorts!F68 -> 0 | O66: =Amorts!G68 -> 0 | P66: =O66/N66 -> #DIV/0! | V66: Trésorerie disponible pour l'activité | W66: =W51 -> 21000000 | Y66: =IF(Analyse!Q77="",W66,Analyse!Q77) -> 21000000
N67: =Amorts!F69 -> 0 | O67: =Amorts!G69 -> 0 | P67: =O67/N67 -> #DIV/0! | V67: Stock actuel | W67: =W47 -> 62510000 | Y67: =IF(Analyse!Q78="",W67,Analyse!Q78) -> 62510000
N68: =Amorts!F70 -> 0 | O68: =Amorts!G70 -> 0 | P68: =O68/N68 -> #DIV/0! | V68: Comptes à recevoir | W68: =W49 -> 6500000 | Y68: =IF(Analyse!Q79="",W68,Analyse!Q79) -> 6500000
N69: =Amorts!F71 -> 0 | O69: =Amorts!G71 -> 0 | P69: =O69/N69 -> #DIV/0! | V69: Dettes fournisseurs et autres dettes | W69: =W57 -> 0 | Y69: =IF(Analyse!Q80="",W69,Analyse!Q80) -> 0
N70: =Amorts!F72 -> 0 | O70: =Amorts!G72 -> 0 | P70: =O70/N70 -> #DIV/0! | V70: Crédit fournisseur (Promesse) | W70: =IF('Collecte des données'!P124="",0,'Collecte des données'!P124) -> 0 | Y70: =IF(Analyse!Q81="",W70,Analyse!Q81) -> 0
N71: =Amorts!F73 -> 0 | O71: =Amorts!G73 -> 0 | P71: =O71/N71 -> #DIV/0!
N72: =Amorts!F74 -> 0 | O72: =Amorts!G74 -> 0 | P72: =O72/N72 -> #DIV/0!
N73: =Amorts!F75 -> 0 | O73: =Amorts!G75 -> 0 | P73: =O73/N73 -> #DIV/0!
N74: =Amorts!F76 -> 0 | O74: =Amorts!G76 -> 0 | P74: =O74/N74 -> #DIV/0! | V74: Attention! Le crédit sollicité surpasse le besoin réel global en crédit de | W74: =W81-W80 -> #VALUE!
N75: =Amorts!F77 -> 0 | O75: =Amorts!G77 -> 0 | P75: =O75/N75 -> #DIV/0! | V75: =CONCATENATE(V74," ",W74," GNF") -> #VALUE!
N76: =Amorts!F78 -> 0 | O76: =Amorts!G78 -> 0 | P76: =O76/N76 -> #DIV/0!
N77: =Amorts!F79 -> 0 | O77: =Amorts!G79 -> 0 | P77: =O77/N77 -> #DIV/0!
N78: =Amorts!F80 -> 0 | O78: =Amorts!G80 -> 0 | P78: =O78/N78 -> #DIV/0! | V78: Besoin Investissement | W78: =IF(Analyse!M73>0,Analyse!M73,0)
N79: =Amorts!F81 -> 0 | O79: =Amorts!G81 -> 0 | P79: =O79/N79 -> #DIV/0! | V79: Besoin fonds de roulement | W79: =IF(Analyse!M82>0,Analyse!M82,0) -> 198890000
N80: =Amorts!F82 -> 0 | O80: =Amorts!G82 -> 0 | P80: =O80/N80 -> #DIV/0! | V80: Total | W80: =W78+W79 -> #VALUE!
N81: =Amorts!F83 -> 0 | O81: =Amorts!G83 -> 0 | P81: =O81/N81 -> #DIV/0! | V81: Sollicité | W81: ='Collecte des données'!I18 -> 60000000
N82: =Amorts!F84 -> 0 | O82: =Amorts!G84 -> 0 | P82: =O82/N82 -> #DIV/0! | W82: =IF(W81>W80,V75,"") -> #VALUE!
N83: =Amorts!F85 -> 0 | O83: =Amorts!G85 -> 0 | P83: =O83/N83 -> #DIV/0!
N84: =Amorts!F86 -> 0 | O84: =Amorts!G86 -> 0 | P84: =O84/N84 -> #DIV/0! | V84: Capacité déclarée | W84: ='Collecte des données'!I25 -> 6700000 | Y84: =(W84/AC11)*AC9 -> 6700000
N85: =Amorts!F87 -> 0 | O85: =Amorts!G87 -> 0 | P85: =O85/N85 -> #DIV/0! | V85: Capacité hors autres revenus | W85: =Analyse!I59 -> 140385000
N86: =Amorts!F88 -> 0 | O86: =Amorts!G88 -> 0 | P86: =O86/N86 -> #DIV/0! | V86: Capacité calculée | W86: =Analyse!I63 -> 142885000
N87: =Amorts!F89 -> 0 | O87: =Amorts!G89 -> 0 | P87: =O87/N87 -> #DIV/0! | V87: La capacité de remboursement déclarée par le membre semble réaliste. Privilégiez cette CDR pour le calcul des ratios.
N88: =Amorts!F90 -> 0 | O88: =Amorts!G90 -> 0 | P88: =O88/N88 -> #DIV/0! | V88: La capacité de remboursement calculée est réaliste par rapport à celle déclarée par le membre.
N89: =Amorts!F91 -> 0 | O89: =Amorts!G91 -> 0 | P89: =O89/N89 -> #DIV/0! | V89: =IF(Y84<W86,V87,V88) -> La capacité de remboursement déclarée par le membre semble réaliste. Privilégiez cette CDR pour le calcul des ratios.
N90: =Amorts!F92 -> 0 | O90: =Amorts!G92 -> 0 | P90: =O90/N90 -> #DIV/0!
N91: =Amorts!F93 -> 0 | O91: =Amorts!G93 -> 0 | P91: =O91/N91 -> #DIV/0!
N92: =Amorts!F94 -> 0 | O92: =Amorts!G94 -> 0 | P92: =O92/N92 -> #DIV/0!
N93: =Amorts!F95 -> 0 | O93: =Amorts!G95 -> 0 | P93: =O93/N93 -> #DIV/0!
N94: =Amorts!F96 -> 0 | O94: =Amorts!G96 -> 0 | P94: =O94/N94 -> #DIV/0!
N95: =Amorts!F97 -> 0 | O95: =Amorts!G97 -> 0 | P95: =O95/N95 -> #DIV/0!
N96: =Amorts!F98 -> 0 | O96: =Amorts!G98 -> 0 | P96: =O96/N96 -> #DIV/0!
N97: =Amorts!F99 -> 0 | O97: =Amorts!G99 -> 0 | P97: =O97/N97 -> #DIV/0!
N98: =Amorts!F100 -> 0 | O98: =Amorts!G100 -> 0 | P98: =O98/N98 -> #DIV/0!
N99: =Amorts!F101 -> 0 | O99: =Amorts!G101 -> 0 | P99: =O99/N99 -> #DIV/0!
N100: =Amorts!F102 -> 0 | O100: =Amorts!G102 -> 0 | P100: =O100/N100 -> #DIV/0!
...

Sheet Demande
J3: DEMANDE DE CRÉDIT - GROS DOSSIER
Z5: Agence de : | AD5: KALOUM
C7: Date de la demande : | I7: 12 | J7: / | K7: 1 | L7: / | M7: 2026 | Y7: Agent de crédit : | AD7: Mr YAKE SONOMOU
B10: 1. | C10: INFORMATIONS SUR LE MEMBRE/CLIENT
C12: Nom et Prénoms : | H12: BARRY AISSATOU BOBO | AB12: Numéro/membre : | AH12: 95240025289
H13: (Suivant l'ordre de la pièce d’identité )
C14: Type de pièce d'identité : | J14: Carte d'Identité Biométrique | T14: Référence : | Y14: 2.1150422e+15
C16: Date et lieu de naissance : | J16: 10 | K16: / | L16: 12 | M16: / | N16: 1991 | P16: à | Q16: DIXINN | Y16: Genre : | AA16: Femme
C18: Situation matrimoniale : | I18: Célibataire | O18: Nombre de personnes à charge : | AA18: Nombre d'enfants scolarisés : | AJ18: 1
C20: Adresse de domicile et Contact : | K20: YATTAYA FOSSIDET
K21: 624-20-35-32/620-56-00-83
O23: (Quartier, maison, lot et numéro de téléphone)
C24: Nombre d'années à l'adresse : | K24: 11 | P24: Type de propriété : | V24: Propriétaire
B27: 2. | C27: ACTIVITÉS
C29: Type d'activité : | G29: COMMERCE | M29: Sous-activité : | R29: Autre
C31: Description de l'activité : | J31: ACHAT DES CONTENEURS DE FRIPERIES ET VENTES A MADINA AVARIA
C33: Nombre d'années dans l'activité : | L33: 20 | P33: Adresse du lieu d'activité : | X33: MADINA AVARIA
C34: (Depuis combien de temps vous exercez cette activité ?)
C36: Autres activités : | G36: COMMERCE D'HABIT ,PARFUM,COSMETIQUE ET D'ARTICLE DIVERS
C38: Lieu de l'activité : | G38: FOSSIDET CARREFOUR
B41: 3. | C41: MODALITÉS DE LA DEMANDE
C43: Montant demandé : | H43: 60000000 | M43: GNF | P43: Durée demandée : | V43: 12 | X43: Mois | Z43: Périodicité de remboursement : | AI43: Mensuelle
C45: Taux d'intérêts : | G45: 3 | K45: Période de différé : | S45: Mois | U45: Nombre d'échéance : | AA45: 12 | AC45: Échéance : | AH45: 71700000
AH46: (Montant en GNF)
C47: Objet du crédit sollicité : | I47: Fonds de roulement | T47: Détail de l'objet de crédit : | AA47: ACHAT D'HABIT,PARFUM,COSMETIQUE ET ARTICLE DIVERS
C49: Nouveau crédit : | I49: Renouvellement : | O49: X | Q49: Rang de crédit : | V49: 3
B52: 4. | C52: GARANTIES PROPOSÉES
C54: Type de Garantie | J54: Nature / Description des garanties | Z54: Valeur de la garantie | AG54: Valeur d'emprunt
C55: Caution solidaire | J55: CAUTION FINANCIERE
C56: Dépôt à terme
C57: Suretés réelles | J57: PARCELLE A KOURIAH | Z57: 20000000 | AG57: 100000000
C58: Autre garantie | J58: APPORT EG | Z58: 6000000 | AG58: 6000000
C59: Total | AG59: =AG55+AG56+AG57+AG58 -> 106000000
D62: Nom et Prénom, Date et Signature | AD62: Nom et Prénom, Date et Signature
D63: (Agent de crédit) | AF63: (Emprunteur)

Sheet Collecte des données
B1: Attention ! Ne pas insérer, ni supprimer ligne ou colonne. Juste écrire dans les cellules de couleur verte claire et choisir dans la liste au niveau des cellules jaunes
B3: Date d'évaluation : | D3: 46038 | F3: Nom du membre : | I3: =IF(Demande!H12="","",Demande!H12) -> BARRY AISSATOU BOBO | P3: N° membre : | R3: =IF(Demande!AH12="","",Demande!AH12) -> 95240025289
A5: 1. | B5: Activité
B6: Quelle est votre activité ? | I6: =IF(Demande!J31="","",Demande!J31) -> ACHAT DES CONTENEURS DE FRIPERIES ET VENTES A MADINA AVARIA
B7: Secteur d'activité | I7: =IF(Demande!G29="","",Demande!G29) -> COMMERCE
B8: Sous-secteur d'activité | I8: =IF(Demande!R29="","",Demande!R29) -> Autre
B9: Sous-sous secteur d'activité
A11: 2. | B11: Conditions de crédit sollicité
B12: Objet du crédit | I12: =IF(Demande!I47="","",Demande!I47) -> Fonds de roulement
C14: =IF(OR(I12="Investissement",I12="Invest+Fonds de roulement"),"Quel est le coût de votre investissement ?","")
C15: =IF(OR(I12="Investissement",I12="Invest+Fonds de roulement"),"Autres dépenses rattachées à l’investissement ?","")
C16: =IF(OR(I12="Investissement",I12="Invest+Fonds de roulement"),"Quel est le montant de votre apport personnel ?","")
B18: Montant sollicité | I18: =IF(Demande!H43="","",Demande!H43) -> 60000000
B19: Durée de crédit sollicité | I19: =IF(Demande!V43="","",Demande!V43) -> 12 | L19: mois
B20: Périodicité de remboursement sollicité | I20: =IF(Demande!AI43="","",Demande!AI43) -> Mensuelle
B21: Pédiode de différé | I21: =IF(Demande!Q45="","",Demande!Q45) | L21: mois
B22: Nombre d'échéances | I22: =IF(Demande!AA45="","",Demande!AA45) -> 12
B23: Échéance correspondante | I23: =IF(Demande!AH45="","",Demande!AH45) -> 71700000
B24: Valeur de la garantie proposée | I24: =IF(Demande!AG59=0,"",Demande!AG59) -> 106000000
B25: Capacité de remboursement périodique déclarée | I25: 6700000
A27: 3. | B27: Quel Chiffre d’Affaires?
B28: =IF(I12="Bon de commande","","Estimation initiale du Chiffre d'affaire") -> Estimation initiale du Chiffre d'affaire
C29: =IF(I12="Bon de commande","","Chiffre d'affaires hebdomadaire") -> Chiffre d'affaires hebdomadaire | I29: 14500000
C30: =IF(I12="Bon de commande","","Chiffre d'affaires mensuel") -> Chiffre d'affaires mensuel | I30: 58000000
B32: =IF(I12="Bon de commande","","Cycle d'affaires mensuel") -> Cycle d'affaires mensuel
B33: =IF(I12="Bon de commande","","Cycle") -> Cycle | C33: =IF(I12="Bon de commande","","Janv") -> Janv | D33: =IF(I12="Bon de commande","","Févr") -> Févr | E33: =IF(I12="Bon de commande","","Mars") -> Mars | F33: =IF(I12="Bon de commande","","Avril") -> Avril | G33: =IF(I12="Bon de commande","","Mai") -> Mai | H33: =IF(I12="Bon de commande","","Juin") -> Juin | I33: =IF(I12="Bon de commande","","Juill") -> Juill | J33: =IF(I12="Bon de commande","","Août") -> Août | K33: =IF(I12="Bon de commande","","Sept.") -> Sept. | L33: =IF(I12="Bon de commande","","Oct.") -> Oct. | M33: =IF(I12="Bon de commande","","Nov.") -> Nov. | N33: =IF(I12="Bon de commande","","Déc.") -> Déc. | O33: =IF(I12="Bon de commande","","Chiffre d'affaires mensuel") -> Chiffre d'affaires mensuel
B34: =IF(I12="Bon de commande","","Fort") -> Fort | D34: X | E34: X | G34: X | H34: X | N34: X | O34: 25000000
B35: =IF(I12="Bon de commande","","Moyen") -> Moyen | C35: X | F35: X | L35: X | M35: X | O35: 16000000
B36: =IF(I12="Bon de commande","","Faible") -> Faible | I36: X | J36: X | K36: X | O36: 10500000
B38: =IF(I12="Bon de commande","","Structure du Chiffre d’Affaire Hebdomadaire") -> Structure du Chiffre d’Affaire Hebdomadaire
B39: =IF(I12="Bon de commande","","Cycle :") -> Cycle : | C39: =IF(I12="Bon de commande","",IF(AND(C40="X",C41="X"),"Faux",IF(AND(C40="X",C42="X"),"Faux",IF(AND(C42="X",C41="X"),"Faux","Lun")))) -> Lun | D39: =IF(I12="Bon de commande","",IF(AND(D40="X",D41="X"),"Faux",IF(AND(D40="X",D42="X"),"Faux",IF(AND(D42="X",D41="X"),"Faux","Mar")))) -> Mar | E39: =IF(I12="Bon de commande","",IF(AND(E40="X",E41="X"),"Faux",IF(AND(E40="X",E42="X"),"Faux",IF(AND(E42="X",E41="X"),"Faux","Mer")))) -> Mer | F39: =IF(I12="Bon de commande","",IF(AND(F40="X",F41="X"),"Faux",IF(AND(F40="X",F42="X"),"Faux",IF(AND(F42="X",F41="X"),"Faux","Jeu")))) -> Jeu | G39: =IF(I12="Bon de commande","",IF(AND(G40="X",G41="X"),"Faux",IF(AND(G40="X",G42="X"),"Faux",IF(AND(G42="X",G41="X"),"Faux","Ven")))) -> Ven | H39: =IF(I12="Bon de commande","",IF(AND(H40="X",H41="X"),"Faux",IF(AND(H40="X",H42="X"),"Faux",IF(AND(H42="X",H41="X"),"Faux","Sam")))) -> Sam | I39: =IF(I12="Bon de commande","",IF(AND(I40="X",I41="X"),"Faux",IF(AND(I40="X",I42="X"),"Faux",IF(AND(I42="X",I41="X"),"Faux","Dim")))) -> Dim | J39: =IF(I12="Bon de commande","","GNF par Jour") -> GNF par Jour | M39: =IF(I12="Bon de commande","","Total par cycle") -> Total par cycle
B40: =IF(I12="Bon de commande","","Fort") -> Fort | G40: X | H40: X | I40: X | J40: 2500000 | M40: =IF(I12="Bon de commande","",J40*COUNTA(C40:I40)) -> 7500000
B41: =IF(I12="Bon de commande","","Moyen") -> Moyen | E41: X | F41: X | J41: 2000000 | M41: =IF(I12="Bon de commande","",J41*COUNTA(C41:I41)) -> 4000000
B42: =IF(I12="Bon de commande","","Faible") -> Faible | C42: X | D42: X | J42: 1500000 | M42: =IF(I12="Bon de commande","",J42*COUNTA(C42:I42)) -> 3000000
G43: =IF(I12="Bon de commande","","Chiffre d'affaires total hebdomadaire") -> Chiffre d'affaires total hebdomadaire | M43: =IF(I12="Bon de commande","",SUM(M40:O42)) -> 14500000
G44: =IF(I12="Bon de commande","","Chiffre d'affaires total mensuel") -> Chiffre d'affaires total mensuel | M44: =IF(I12="Bon de commande","",M43*4) -> 58000000
A46: 4. | B46: Structure de la marge brute
B47: Connaissez-vous votre pourcentage de marge brute ? | I47: OUI | K47: =IF(I47="OUI","Alors quel est taux de marge brute ?","") -> Alors quel est taux de marge brute ? | P47: 0.34
B49: Procédez au calcul du taux marge brute ? | I49: OUI
B51: =IF(I12="Bon de commande","Marché/Bon de commande - Fréquence unique",IF(I49="OUI","Quelle est la fréquence des ventes ?","")) -> Quelle est la fréquence des ventes ? | I51: Mensuelle | M51: =IF(I51="Journalière","Nombre de jours dans le mois",IF(I51="Autre","Précisez ici (ratio en jours)",""))
B53: =IF(I49="OUI","Produits ou Articles","") -> Produits ou Articles | E53: =IF(I12="Bon de commande","Coût du Marché",IF(I49="OUI","Prix de vente (GNF)","")) -> Prix de vente (GNF) | H53: =IF(I12="Bon de commande","Coût d'exécution",IF(I49="OUI","Coût d'achat (GNF)","")) -> Coût d'achat (GNF) | K53: =IF(I49="OUI","Quantité","") -> Quantité | M53: =IF(I49="OUI","Chiffres d'affaires (GNF)","") -> Chiffres d'affaires (GNF) | P53: =IF(I49="OUI","Coûts d'achat (GNF)","") -> Coûts d'achat (GNF) | T53: =IF(I49="OUI","%MB","") -> %MB
B55: PAIRE DE CHAUSSURE(CARTONS) | E55: 7000000 | H55: 6000000 | K55: 5 | M55: =IF($I$49="OUI",E55*K55,"") -> 35000000 | P55: =IF($I$49="OUI",H55*K55,"") -> 30000000 | T55: =IFERROR(((M55-P55)/M55),"") -> 0.14285714
B56: SAC A MAIN (DOUZAINE) | E56: 3500000 | H56: 2500000 | K56: 20 | M56: =IF($I$49="OUI",E56*K56,"") -> 70000000 | P56: =IF($I$49="OUI",H56*K56,"") -> 50000000 | T56: =IFERROR(((M56-P56)/M56),"") -> 0.28571429
B57: HABIT PRÊT A PORTER | E57: 3000000 | H57: 2600000 | K57: 2 | M57: =IF($I$49="OUI",E57*K57,"") -> 6000000 | P57: =IF($I$49="OUI",H57*K57,"") -> 5200000 | T57: =IFERROR(((M57-P57)/M57),"") -> 0.13333333
B58: PANTALON(FEMME) | E58: 2400000 | H58: 1700000 | K58: 5 | M58: =IF($I$49="OUI",E58*K58,"") -> 12000000 | P58: =IF($I$49="OUI",H58*K58,"") -> 8500000 | T58: =IFERROR(((M58-P58)/M58),"") -> 0.29166667
B59: TISSUS(WAX) | E59: 500000 | H59: 280000 | K59: 10 | M59: =IF($I$49="OUI",E59*K59,"") -> 5000000 | P59: =IF($I$49="OUI",H59*K59,"") -> 2800000 | T59: =IFERROR(((M59-P59)/M59),"") -> 0.44
B60: PARFUM(CARTON) | E60: 4500000 | H60: 3500000 | K60: 10 | M60: =IF($I$49="OUI",E60*K60,"") -> 45000000 | P60: =IF($I$49="OUI",H60*K60,"") -> 35000000 | T60: =IFERROR(((M60-P60)/M60),"") -> 0.22222222
B61: SHAMPOING(CARTON) | E61: 1500000 | H61: 800000 | K61: 20 | M61: =IF($I$49="OUI",E61*K61,"") -> 30000000 | P61: =IF($I$49="OUI",H61*K61,"") -> 16000000 | T61: =IFERROR(((M61-P61)/M61),"") -> 0.46666667
B62: LAIT DE PEAU(CARTON) | E62: 2500000 | H62: 1800000 | K62: 20 | M62: =IF($I$49="OUI",E62*K62,"") -> 50000000 | P62: =IF($I$49="OUI",H62*K62,"") -> 36000000 | T62: =IFERROR(((M62-P62)/M62),"") -> 0.28
B63: SAVON (CARTON) | E63: 2400000 | H63: 1300000 | K63: 20 | M63: =IF($I$49="OUI",E63*K63,"") -> 48000000 | P63: =IF($I$49="OUI",H63*K63,"") -> 26000000 | T63: =IFERROR(((M63-P63)/M63),"") -> 0.45833333
B64: CREME DE CHEVEUX(CARTON) | E64: 4000000 | H64: 1800000 | K64: 10 | M64: =IF($I$49="OUI",E64*K64,"") -> 40000000 | P64: =IF($I$49="OUI",H64*K64,"") -> 18000000 | T64: =IFERROR(((M64-P64)/M64),"") -> 0.55
B65: PAIRE DE CHAUSSURE EN PLASTIQUE | E65: 1000000 | H65: 640000 | K65: 10 | M65: =IF($I$49="OUI",E65*K65,"") -> 10000000 | P65: =IF($I$49="OUI",H65*K65,"") -> 6400000 | T65: =IFERROR(((M65-P65)/M65),"") -> 0.36
B66: CHAUSSURE POUR ENFANT | E66: 1000000 | H66: 500000 | K66: 20 | M66: =IF($I$49="OUI",E66*K66,"") -> 20000000 | P66: =IF($I$49="OUI",H66*K66,"") -> 10000000 | T66: =IFERROR(((M66-P66)/M66),"") -> 0.5
... B68: ENSEMBLE DE LINGERIE | E68: 6000000 | H68: 4000000 | K68: 10 | M68: =IF($I$49="OUI",E68*K68,"") -> 60000000 | P68: =IF($I$49="OUI",H68*K68,"") -> 40000000 | T68: =IFERROR(((M68-P68)/M68),"") -> 0.33333333
M69: =IF($I$49="OUI",E69*K69,"") -> 0 | P69: =IF($I$49="OUI",H69*K69,"") -> 0 | T69: =IFERROR(((M69-P69)/M69),"")
B70: =IF(I12="Bon de commande","Coût du bon de commande et taux de marge",IF(I49="OUI","Total mensuel","")) -> Total mensuel | M70: =IF(I12="Bon de commande",(SUM(M55:O69)*1),IF($I$51="Journalière",((SUM(M55:O69)*$P$51)),IF($I$51="Hebdomadaire",(SUM(M55:O69)*4),IF($I$51="Mensuelle",(SUM(M55:O69)),IF($I$51="Unique",(SUM(M55:O69)*1),""))))) -> 441000000 | P70: =IF(I12="Bon de commande",(SUM(P55:R69)*1),IF($I$51="Journalière",((SUM(P55:R69)*$P$51)),IF($I$51="Hebdomadaire",(SUM(P55:R69)*4),IF($I$51="Mensuelle",(SUM(P55:R69)),IF($I$51="Unique",(SUM(P55:R69)*1),""))))) -> 288900000 | T70: =IFERROR(((M70-P70)/M70),"") -> 0.34489796
A73: 5. | B73: Évaluation des actifs nets de l'entreprise ou de l'activité
B75: a) Existe-t-il des terrains utilisés pour l'activité ? | I75: NON | K75: =IF(I75="OUI","Est-ce votre propriété ?","") | P75: NON
K76: =IF(P75="OUI","Évalués à :","")
B78: b) Existe-t-il des bâtiments et magasin dédiés à l'activité ? | I78: NON | K78: =IF(I78="OUI","Est-ce votre propriété ?","") | P78: NON
B79: =IF(P78="OUI","Référez-vous à la feuille _ Amorts","")
B81: c) Existe-t-il des installations dédiées à l'activité ? | I81: OUI | K81: =IF(I81="OUI","Est-ce votre propriété ?","") -> Est-ce votre propriété ? | P81: OUI
B82: =IF(P81="OUI","Référez-vous à la feuille _ Amorts","") -> Référez-vous à la feuille _ Amorts
B84: d) Existe-t-il des matériels roulants dédiés à l'activité ? | I84: OUI | K84: =IF(I84="OUI","Est-ce votre propriété ?","") -> Est-ce votre propriété ? | P84: OUI
B85: =IF(P84="OUI","Référez-vous à la feuille _ Amorts","") -> Référez-vous à la feuille _ Amorts
B87: e) Existe-t-il des mobiliers et matériels de bureau ? | I87: OUI | K87: =IF(I87="OUI","Est-ce votre propriété ?","") -> Est-ce votre propriété ? | P87: OUI
B88: =IF(P87="OUI","Référez-vous à la feuille _ Amorts","") -> Référez-vous à la feuille _ Amorts
B90: f) Existent-t-ils des machines et équipements de production ? | I90: NON | K90: =IF(I90="OUI","Est-ce votre propriété ?","") | P90: NON
B91: =IF(P90="OUI","Référez-vous à la feuille _ Amorts","")
B93: g) Caution financière/dépôt financier effectué ou autres ? | I93: OUI | K93: =IF(I93="OUI","Vous pouvez évaluer le montant total ?","") -> Vous pouvez évaluer le montant total ? | P93: OUI
K94: =IF(P93="OUI","Évalués à :","") -> Évalués à : | P94: 6000000
B96: h) Avez-vous fait des prêts à vos employés ou autres prêts ? | I96: NON | K96: =IF(I96="OUI","Est-ce avec les fonds de l'activité ?","")
K97: =IF(P96="OUI","Évalués à :","")
B99: =IF(I12="Bon de commande","i) Avez-vous déjà exécuté une partie des travaux ?","i) Avez-vous un stock de marchandises à vendre") -> i) Avez-vous un stock de marchandises à vendre | I99: OUI | K99: =IF(I99="OUI","Avez-vous une idée de sa valeur ?","") -> Avez-vous une idée de sa valeur ? | P99: OUI
K100: =IF(P99="OUI","Évalués à :","") -> Évalués à : | P100: 62510000
C101: Faire l'évaluation du stock disponible ? | I101: OUI
B103: =IF(I101="OUI","Évaluation du stock disponible","") -> Évaluation du stock disponible
B104: =IF(I101="OUI","Produits ou Articles (les principaux)","") -> Produits ou Articles (les principaux) | H104: =IF(I101="OUI","Quantité","") -> Quantité | J104: =IF(I101="OUI","Coûts d'achats","") -> Coûts d'achats | M104: =IF(I101="OUI","Valeur du Stock","") -> Valeur du Stock
B106: TISSUS WAX | H106: 18 | J106: 180000 | M106: =IF($I$101="OUI",J106*H106,"") -> 3240000
B107: COMPLET MACKY SALL | H107: 16 | J107: 350000 | M107: =IF($I$101="OUI",J107*H107,"") -> 5600000
B108: CHAUSSURES EN TALON | H108: 20 | J108: 150000 | M108: =IF($I$101="OUI",J108*H108,"") -> 3000000
B109: SACS A MAIN | H109: 30 | J109: 150000 | M109: =IF($I$101="OUI",J109*H109,"") -> 4500000
B110: PANTALON JEAN | H110: 38 | J110: 100000 | M110: =IF($I$101="OUI",J110*H110,"") -> 3800000
B111: SAVON DE DOUCHE | H111: 20 | J111: 240000 | M111: =IF($I$101="OUI",J111*H111,"") -> 4800000
B112: SHAMPOING | H112: 30 | J112: 600000 | M112: =IF($I$101="OUI",J112*H112,"") -> 18000000
B113: PARFUM DE PEAU | H113: 25 | J113: 100000 | M113: =IF($I$101="OUI",J113*H113,"") -> 2500000
B114: PARFUM DE CHAMBRE | H114: 19 | J114: 130000 | M114: =IF($I$101="OUI",J114*H114,"") -> 2470000
B115: ROBE | H115: 30 | J115: 200000 | M115: =IF($I$101="OUI",J115*H115,"") -> 6000000
B116: COLLANT | H116: 50 | J116: 100000 | M116: =IF($I$101="OUI",J116*H116,"") -> 5000000
B117: CHEMISE | H117: 40 | J117: 90000 | M117: =IF($I$101="OUI",J117*H117,"") -> 3600000
M118: =IF($I$101="OUI",J118*H118,"") -> 0
M119: =IF($I$101="OUI",J119*H119,"") -> 0
M120: =IF($I$101="OUI",J120*H120,"") -> 0
J121: =IF(I101="OUI","TOTAL","") -> TOTAL | M121: =IF(I101="OUI",SUM(M106:P120),"") -> 62510000
B123: j) Obtenez-vous des crédits fournisseurs ? | I123: NON | J123: =IF(I123="OUI","Avez-vous prévu obtenir un crédit fournisseur ?","") | P123: NON
K124: =IF(P123="OUI","Évalués à :","")
B126: k) Avez-vous des clients qui vous doivent de l'argent ? | I126: OUI | K126: =IF(I126="OUI","Avez-vous une idée de sa valeur ?","") -> Avez-vous une idée de sa valeur ? | P126: OUI
H128: =IF(P126="OUI","Évalués à :","") -> Évalués à : | J128: 10000000 | N128: =IF(P126="OUI","Depuis plus de 3 mois","") -> Depuis plus de 3 mois
H129: =IF(P126="OUI","Évalués à :","") -> Évalués à : | J129: 6500000 | N129: =IF(P126="OUI","Moins de 3 mois","") -> Moins de 3 mois
B131: l) Avez-vous de l'argent cash quelque part ? | I131: NON | K131: =IF(I131="OUI","Avez-vous une idée du montant ?","") | P131: NON
...

Sheet Amorts
C2: ← | E2: =IF(E3<>"","Date d'évaluation","") -> Date d'évaluation | F2: =IF(AND(E3="",C6<>""),"Attention! Veuillez renseigner la date d'évaluation en haut de la feuille - Collecte des données","")
E3: =IF('Collecte des données'!D3="","",'Collecte des données'!D3) -> 46038
B5: № | C5: Nature de l'immobilisation | D5: Type d'immobilisation | E5: Date d'acquisition | F5: Durée Amorts (mois) | G5: Valeur d'acquisition (en GNF) | H5: Mensualité | I5: Cumul des amortissements | J5: Date de fin d'amortissement | K5: Valeur nette comptable | L5: Valeur nette ajustée | M5: Observation | O5: Mois cumulé | P5: Mois cumulé corrigé | Q5: Mois cumulé corrigé | R5: mois restant | S5: mensualité
B6: 1 | C6: ETAGERE POUR LES HABITS | D6: Mobilier de bureau | E6: 43876 | F6: 96 | G6: 8000000 | H6: =IFERROR(CRG!P2,0) -> 83333.333 | I6: =IF(J6="","",IFERROR((CRG!P2*Q6),0)) -> 5916666.7 | J6: =IF(E6="","",EDATE(E6,F6)) -> 46798 | K6: =IF(L6="",(IF(G6="","",ROUNDDOWN((G6-I6),0))),L6) -> 8000000 | L6: 8000000 | O6: =DATEDIF(E6,$E$3,"m") -> 71 | P6: =IF(O6>F6,"Amorti","En_cours") -> En_cours | Q6: =IF(P6="En_cours",O6,F6) -> 71 | R6: =F6-O6 -> 25 | S6: =IF(R6>=1,"OUI","NON") -> OUI
B7: 2 | C7: ETAGERE POUR LES PRODUITS COSMETIQUE | D7: Mobilier de bureau | E7: 43876 | F7: 96 | G7: 6000000 | H7: =IFERROR(CRG!P3,0) -> 62500 | I7: =IF(J7="","",IFERROR((CRG!P3*Q7),0)) -> 4437500 | J7: =IF(E7="","",EDATE(E7,F7)) -> 46798 | K7: =IF(L7="",(IF(G7="","",ROUNDDOWN((G7-I7),0))),L7) -> 6000000 | L7: 6000000 | O7: =DATEDIF(E7,$E$3,"m") -> 71 | P7: =IF(O7>F7,"Amorti","En_cours") -> En_cours | Q7: =IF(P7="En_cours",O7,F7) -> 71 | R7: =F7-O7 -> 25 | S7: =IF(R7>=1,"OUI","NON") -> OUI
B8: 3 | C8: ETAGERE POUR WAX | D8: Mobilier de bureau | E8: 43876 | F8: 96 | G8: 3000000 | H8: =IFERROR(CRG!P4,0) -> 31250 | I8: =IF(J8="","",IFERROR((CRG!P4*Q8),0)) -> 2218750 | J8: =IF(E8="","",EDATE(E8,F8)) -> 46798 | K8: =IF(L8="",(IF(G8="","",ROUNDDOWN((G8-I8),0))),L8) -> 3000000 | L8: 3000000 | O8: =DATEDIF(E8,$E$3,"m") -> 71 | P8: =IF(O8>F8,"Amorti","En_cours") -> En_cours | Q8: =IF(P8="En_cours",O8,F8) -> 71 | R8: =F8-O8 -> 25 | S8: =IF(R8>=1,"OUI","NON") -> OUI
B9: 4 | C9: COMPTOIRE | D9: Mobilier de bureau | E9: 43876 | F9: 96 | G9: 2000000 | H9: =IFERROR(CRG!P5,0) -> 20833.333 | I9: =IF(J9="","",IFERROR((CRG!P5*Q9),0)) -> 1479166.7 | J9: =IF(E9="","",EDATE(E9,F9)) -> 46798 | K9: =IF(L9="",(IF(G9="","",ROUNDDOWN((G9-I9),0))),L9) -> 2000000 | L9: 2000000 | O9: =DATEDIF(E9,$E$3,"m") -> 71 | P9: =IF(O9>F9,"Amorti","En_cours") -> En_cours | Q9: =IF(P9="En_cours",O9,F9) -> 71 | R9: =F9-O9 -> 25 | S9: =IF(R9>=1,"OUI","NON") -> OUI
B10: 5 | C10: CONGELATEUR I | D10: Mobilier de bureau | E10: 45383 | F10: 96 | G10: 2500000 | H10: =IFERROR(CRG!P6,0) -> 26041.667 | I10: =IF(J10="","",IFERROR((CRG!P6*Q10),0)) -> 546875 | J10: =IF(E10="","",EDATE(E10,F10)) -> 48305 | K10: =IF(L10="",(IF(G10="","",ROUNDDOWN((G10-I10),0))),L10) -> 2500000 | L10: 2500000 | O10: =DATEDIF(E10,$E$3,"m") -> 21 | P10: =IF(O10>F10,"Amorti","En_cours") -> En_cours | Q10: =IF(P10="En_cours",O10,F10) -> 21 | R10: =F10-O10 -> 75 | S10: =IF(R10>=1,"OUI","NON") -> OUI
B11: 6 | C11: CONGELATEURII | D11: Bâtiments et magasin | E11: 45384 | F11: 96 | G11: 2500000 | H11: =IFERROR(CRG!P7,0) -> 26041.667 | I11: =IF(J11="","",IFERROR((CRG!P7*Q11),0)) -> 546875 | J11: =IF(E11="","",EDATE(E11,F11)) -> 48306 | K11: =IF(L11="",(IF(G11="","",ROUNDDOWN((G11-I11),0))),L11) -> 2500000 | L11: 2500000 | O11: =DATEDIF(E11,$E$3,"m") -> 21 | P11: =IF(O11>F11,"Amorti","En_cours") -> En_cours | Q11: =IF(P11="En_cours",O11,F11) -> 21 | R11: =F11-O11 -> 75 | S11: =IF(R11>=1,"OUI","NON") -> OUI
B12: 7 | C12: AUDI | D12: Matériel de transport | E12: 44451 | F12: 96 | G12: 35000000 | H12: =IFERROR(CRG!P8,0) -> 364583.33 | I12: =IF(J12="","",IFERROR((CRG!P8*Q12),0)) -> 18958333 | J12: =IF(E12="","",EDATE(E12,F12)) -> 47373 | K12: =IF(L12="",(IF(G12="","",ROUNDDOWN((G12-I12),0))),L12) -> 20000000 | L12: 20000000 | O12: =DATEDIF(E12,$E$3,"m") -> 52 | P12: =IF(O12>F12,"Amorti","En_cours") -> En_cours | Q12: =IF(P12="En_cours",O12,F12) -> 52 | R12: =F12-O12 -> 44 | S12: =IF(R12>=1,"OUI","NON") -> OUI
B13: 8 | H13: =IFERROR(CRG!P9,0) -> 0 | I13: =IF(J13="","",IFERROR((CRG!P9*Q13),0)) | J13: =IF(E13="","",EDATE(E13,F13)) | K13: =IF(L13="",(IF(G13="","",ROUNDDOWN((G13-I13),0))),L13) | O13: =DATEDIF(E13,$E$3,"m") -> 1512 | P13: =IF(O13>F13,"Amorti","En_cours") -> Amorti | Q13: =IF(P13="En_cours",O13,F13) -> 0 | R13: =F13-O13 -> -1512 | S13: =IF(R13>=1,"OUI","NON") -> NON
B14: 9 | H14: =IFERROR(CRG!P10,0) -> 0 | I14: =IF(J14="","",IFERROR((CRG!P10*Q14),0)) | J14: =IF(E14="","",EDATE(E14,F14)) | K14: =IF(L14="",(IF(G14="","",ROUNDDOWN((G14-I14),0))),L14) | O14: =DATEDIF(E14,$E$3,"m") -> 1512 | P14: =IF(O14>F14,"Amorti","En_cours") -> Amorti | Q14: =IF(P14="En_cours",O14,F14) -> 0 | R14: =F14-O14 -> -1512 | S14: =IF(R14>=1,"OUI","NON") -> NON
B15: 10 | H15: =IFERROR(CRG!P11,0) -> 0 | I15: =IF(J15="","",IFERROR((CRG!P11*Q15),0)) | J15: =IF(E15="","",EDATE(E15,F15)) | K15: =IF(L15="",(IF(G15="","",ROUNDDOWN((G15-I15),0))),L15) | O15: =DATEDIF(E15,$E$3,"m") -> 1512 | P15: =IF(O15>F15,"Amorti","En_cours") -> Amorti | Q15: =IF(P15="En_cours",O15,F15) -> 0 | R15: =F15-O15 -> -1512 | S15: =IF(R15>=1,"OUI","NON") -> NON
B16: 11 | H16: =IFERROR(CRG!P12,0) -> 0 | I16: =IF(J16="","",IFERROR((CRG!P12*Q16),0)) | J16: =IF(E16="","",EDATE(E16,F16)) | K16: =IF(L16="",(IF(G16="","",ROUNDDOWN((G16-I16),0))),L16) | O16: =DATEDIF(E16,$E$3,"m") -> 1512 | P16: =IF(O16>F16,"Amorti","En_cours") -> Amorti | Q16: =IF(P16="En_cours",O16,F16) -> 0 | R16: =F16-O16 -> -1512 | S16: =IF(R16>=1,"OUI","NON") -> NON
B17: 12 | H17: =IFERROR(CRG!P13,0) -> 0 | I17: =IF(J17="","",IFERROR((CRG!P13*Q17),0)) | J17: =IF(E17="","",EDATE(E17,F17)) | K17: =IF(L17="",(IF(G17="","",ROUNDDOWN((G17-I17),0))),L17) | O17: =DATEDIF(E17,$E$3,"m") -> 1512 | P17: =IF(O17>F17,"Amorti","En_cours") -> Amorti | Q17: =IF(P17="En_cours",O17,F17) -> 0 | R17: =F17-O17 -> -1512 | S17: =IF(R17>=1,"OUI","NON") -> NON
B18: 13 | H18: =IFERROR(CRG!P14,0) -> 0 | I18: =IF(J18="","",IFERROR((CRG!P14*Q18),0)) | J18: =IF(E18="","",EDATE(E18,F18)) | K18: =IF(L18="",(IF(G18="","",ROUNDDOWN((G18-I18),0))),L18) | O18: =DATEDIF(E18,$E$3,"m") -> 1512 | P18: =IF(O18>F18,"Amorti","En_cours") -> Amorti | Q18: =IF(P18="En_cours",O18,F18) -> 0 | R18: =F18-O18 -> -1512 | S18: =IF(R18>=1,"OUI","NON") -> NON
B19: 14 | H19: =IFERROR(CRG!P15,0) -> 0 | I19: =IF(J19="","",IFERROR((CRG!P15*Q19),0)) | J19: =IF(E19="","",EDATE(E19,F19)) | K19: =IF(L19="",(IF(G19="","",ROUNDDOWN((G19-I19),0))),L19) | O19: =DATEDIF(E19,$E$3,"m") -> 1512 | P19: =IF(O19>F19,"Amorti","En_cours") -> Amorti | Q19: =IF(P19="En_cours",O19,F19) -> 0 | R19: =F19-O19 -> -1512 | S19: =IF(R19>=1,"OUI","NON") -> NON
B20: 15 | H20: =IFERROR(CRG!P16,0) -> 0 | I20: =IF(J20="","",IFERROR((CRG!P16*Q20),0)) | J20: =IF(E20="","",EDATE(E20,F20)) | K20: =IF(L20="",(IF(G20="","",ROUNDDOWN((G20-I20),0))),L20) | O20: =DATEDIF(E20,$E$3,"m") -> 1512 | P20: =IF(O20>F20,"Amorti","En_cours") -> Amorti | Q20: =IF(P20="En_cours",O20,F20) -> 0 | R20: =F20-O20 -> -1512 | S20: =IF(R20>=1,"OUI","NON") -> NON
B21: 16 | H21: =IFERROR(CRG!P17,0) -> 0 | I21: =IF(J21="","",IFERROR((CRG!P17*Q21),0)) | J21: =IF(E21="","",EDATE(E21,F21)) | K21: =IF(L21="",(IF(G21="","",ROUNDDOWN((G21-I21),0))),L21) | O21: =DATEDIF(E21,$E$3,"m") -> 1512 | P21: =IF(O21>F21,"Amorti","En_cours") -> Amorti | Q21: =IF(P21="En_cours",O21,F21) -> 0 | R21: =F21-O21 -> -1512 | S21: =IF(R21>=1,"OUI","NON") -> NON
B22: 17 | H22: =IFERROR(CRG!P18,0) -> 0 | I22: =IF(J22="","",IFERROR((CRG!P18*Q22),0)) | J22: =IF(E22="","",EDATE(E22,F22)) | K22: =IF(L22="",(IF(G22="","",ROUNDDOWN((G22-I22),0))),L22) | O22: =DATEDIF(E22,$E$3,"m") -> 1512 | P22: =IF(O22>F22,"Amorti","En_cours") -> Amorti | Q22: =IF(P22="En_cours",O22,F22) -> 0 | R22: =F22-O22 -> -1512 | S22: =IF(R22>=1,"OUI","NON") -> NON
B23: 18 | H23: =IFERROR(CRG!P19,0) -> 0 | I23: =IF(J23="","",IFERROR((CRG!P19*Q23),0)) | J23: =IF(E23="","",EDATE(E23,F23)) | K23: =IF(L23="",(IF(G23="","",ROUNDDOWN((G23-I23),0))),L23) | O23: =DATEDIF(E23,$E$3,"m") -> 1512 | P23: =IF(O23>F23,"Amorti","En_cours") -> Amorti | Q23: =IF(P23="En_cours",O23,F23) -> 0 | R23: =F23-O23 -> -1512 | S23: =IF(R23>=1,"OUI","NON") -> NON
B24: 19 | H24: =IFERROR(CRG!P20,0) -> 0 | I24: =IF(J24="","",IFERROR((CRG!P20*Q24),0)) | J24: =IF(E24="","",EDATE(E24,F24)) | K24: =IF(L24="",(IF(G24="","",ROUNDDOWN((G24-I24),0))),L24) | O24: =DATEDIF(E24,$E$3,"m") -> 1512 | P24: =IF(O24>F24,"Amorti","En_cours") -> Amorti | Q24: =IF(P24="En_cours",O24,F24) -> 0 | R24: =F24-O24 -> -1512 | S24: =IF(R24>=1,"OUI","NON") -> NON
... B52: 47 | H52: =IFERROR(CRG!P48,0) -> 0 | I52: =IF(J52="","",IFERROR((CRG!P48*Q52),0)) | J52: =IF(E52="","",EDATE(E52,F52)) | K52: =IF(L52="",(IF(G52="","",ROUNDDOWN((G52-I52),0))),L52) | O52: =DATEDIF(E52,$E$3,"m") -> 1512 | P52: =IF(O52>F52,"Amorti","En_cours") -> Amorti | Q52: =IF(P52="En_cours",O52,F52) -> 0 | R52: =F52-O52 -> -1512 | S52: =IF(R52>=1,"OUI","NON") -> NON
B53: 48 | H53: =IFERROR(CRG!P51,0) -> 0 | I53: =IF(J53="","",IFERROR((CRG!P51*Q53),0)) | J53: =IF(E53="","",EDATE(E53,F53)) | K53: =IF(L53="",(IF(G53="","",ROUNDDOWN((G53-I53),0))),L53) | O53: =DATEDIF(E53,$E$3,"m") -> 1512 | P53: =IF(O53>F53,"Amorti","En_cours") -> Amorti | Q53: =IF(P53="En_cours",O53,F53) -> 0 | R53: =F53-O53 -> -1512 | S53: =IF(R53>=1,"OUI","NON") -> NON
B54: 49 | H54: =IFERROR(CRG!P52,0) -> 0 | I54: =IF(J54="","",IFERROR((CRG!P52*Q54),0)) | J54: =IF(E54="","",EDATE(E54,F54)) | K54: =IF(L54="",(IF(G54="","",ROUNDDOWN((G54-I54),0))),L54) | O54: =DATEDIF(E54,$E$3,"m") -> 1512 | P54: =IF(O54>F54,"Amorti","En_cours") -> Amorti | Q54: =IF(P54="En_cours",O54,F54) -> 0 | R54: =F54-O54 -> -1512 | S54: =IF(R54>=1,"OUI","NON") -> NON
B55: 50 | H55: =IFERROR(CRG!P53,0) -> 0 | I55: =IF(J55="","",IFERROR((CRG!P53*Q55),0)) | J55: =IF(E55="","",EDATE(E55,F55)) | K55: =IF(L55="",(IF(G55="","",ROUNDDOWN((G55-I55),0))),L55) | O55: =DATEDIF(E55,$E$3,"m") -> 1512 | P55: =IF(O55>F55,"Amorti","En_cours") -> Amorti | Q55: =IF(P55="En_cours",O55,F55) -> 0 | R55: =F55-O55 -> -1512 | S55: =IF(R55>=1,"OUI","NON") -> NON
B56: 51 | H56: =IFERROR(CRG!P54,0) -> 0 | I56: =IF(J56="","",IFERROR((CRG!P54*Q56),0)) | J56: =IF(E56="","",EDATE(E56,F56)) | K56: =IF(L56="",(IF(G56="","",ROUNDDOWN((G56-I56),0))),L56) | O56: =DATEDIF(E56,$E$3,"m") -> 1512 | P56: =IF(O56>F56,"Amorti","En_cours") -> Amorti | Q56: =IF(P56="En_cours",O56,F56) -> 0 | R56: =F56-O56 -> -1512 | S56: =IF(R56>=1,"OUI","NON") -> NON
B57: 52 | H57: =IFERROR(CRG!P55,0) -> 0 | I57: =IF(J57="","",IFERROR((CRG!P55*Q57),0)) | J57: =IF(E57="","",EDATE(E57,F57)) | K57: =IF(L57="",(IF(G57="","",ROUNDDOWN((G57-I57),0))),L57) | O57: =DATEDIF(E57,$E$3,"m") -> 1512 | P57: =IF(O57>F57,"Amorti","En_cours") -> Amorti | Q57: =IF(P57="En_cours",O57,F57) -> 0 | R57: =F57-O57 -> -1512 | S57: =IF(R57>=1,"OUI","NON") -> NON
B58: 53 | H58: =IFERROR(CRG!P56,0) -> 0 | I58: =IF(J58="","",IFERROR((CRG!P56*Q58),0)) | J58: =IF(E58="","",EDATE(E58,F58)) | K58: =IF(L58="",(IF(G58="","",ROUNDDOWN((G58-I58),0))),L58) | O58: =DATEDIF(E58,$E$3,"m") -> 1512 | P58: =IF(O58>F58,"Amorti","En_cours") -> Amorti | Q58: =IF(P58="En_cours",O58,F58) -> 0 | R58: =F58-O58 -> -1512 | S58: =IF(R58>=1,"OUI","NON") -> NON
B59: 54 | H59: =IFERROR(CRG!P57,0) -> 0 | I59: =IF(J59="","",IFERROR((CRG!P57*Q59),0)) | J59: =IF(E59="","",EDATE(E59,F59)) | K59: =IF(L59="",(IF(G59="","",ROUNDDOWN((G59-I59),0))),L59) | O59: =DATEDIF(E59,$E$3,"m") -> 1512 | P59: =IF(O59>F59,"Amorti","En_cours") -> Amorti | Q59: =IF(P59="En_cours",O59,F59) -> 0 | R59: =F59-O59 -> -1512 | S59: =IF(R59>=1,"OUI","NON") -> NON
B60: 55 | H60: =IFERROR(CRG!P58,0) -> 0 | I60: =IF(J60="","",IFERROR((CRG!P58*Q60),0)) | J60: =IF(E60="","",EDATE(E60,F60)) | K60: =IF(L60="",(IF(G60="","",ROUNDDOWN((G60-I60),0))),L60) | O60: =DATEDIF(E60,$E$3,"m") -> 1512 | P60: =IF(O60>F60,"Amorti","En_cours") -> Amorti | Q60: =IF(P60="En_cours",O60,F60) -> 0 | R60: =F60-O60 -> -1512 | S60: =IF(R60>=1,"OUI","NON") -> NON
B61: 56 | H61: =IFERROR(CRG!P59,0) -> 0 | I61: =IF(J61="","",IFERROR((CRG!P59*Q61),0)) | J61: =IF(E61="","",EDATE(E61,F61)) | K61: =IF(L61="",(IF(G61="","",ROUNDDOWN((G61-I61),0))),L61) | O61: =DATEDIF(E61,$E$3,"m") -> 1512 | P61: =IF(O61>F61,"Amorti","En_cours") -> Amorti | Q61: =IF(P61="En_cours",O61,F61) -> 0 | R61: =F61-O61 -> -1512 | S61: =IF(R61>=1,"OUI","NON") -> NON
B62: 57 | H62: =IFERROR(CRG!P60,0) -> 0 | I62: =IF(J62="","",IFERROR((CRG!P60*Q62),0)) | J62: =IF(E62="","",EDATE(E62,F62)) | K62: =IF(L62="",(IF(G62="","",ROUNDDOWN((G62-I62),0))),L62) | O62: =DATEDIF(E62,$E$3,"m") -> 1512 | P62: =IF(O62>F62,"Amorti","En_cours") -> Amorti | Q62: =IF(P62="En_cours",O62,F62) -> 0 | R62: =F62-O62 -> -1512 | S62: =IF(R62>=1,"OUI","NON") -> NON
B63: 58 | H63: =IFERROR(CRG!P61,0) -> 0 | I63: =IF(J63="","",IFERROR((CRG!P61*Q63),0)) | J63: =IF(E63="","",EDATE(E63,F63)) | K63: =IF(L63="",(IF(G63="","",ROUNDDOWN((G63-I63),0))),L63) | O63: =DATEDIF(E63,$E$3,"m") -> 1512 | P63: =IF(O63>F63,"Amorti","En_cours") -> Amorti | Q63: =IF(P63="En_cours",O63,F63) -> 0 | R63: =F63-O63 -> -1512 | S63: =IF(R63>=1,"OUI","NON") -> NON
B64: 59 | H64: =IFERROR(CRG!P62,0) -> 0 | I64: =IF(J64="","",IFERROR((CRG!P62*Q64),0)) | J64: =IF(E64="","",EDATE(E64,F64)) | K64: =IF(L64="",(IF(G64="","",ROUNDDOWN((G64-I64),0))),L64) | O64: =DATEDIF(E64,$E$3,"m") -> 1512 | P64: =IF(O64>F64,"Amorti","En_cours") -> Amorti | Q64: =IF(P64="En_cours",O64,F64) -> 0 | R64: =F64-O64 -> -1512 | S64: =IF(R64>=1,"OUI","NON") -> NON
... B104: 99 | H104: =IFERROR(CRG!P102,0) -> 0 | I104: =IF(J104="","",IFERROR((CRG!P102*Q104),0)) | J104: =IF(E104="","",EDATE(E104,F104)) | K104: =IF(L104="",(IF(G104="","",ROUNDDOWN((G104-I104),0))),L104) | O104: =DATEDIF(E104,$E$3,"m") -> 1512 | P104: =IF(O104>F104,"Amorti","En_cours") -> Amorti | Q104: =IF(P104="En_cours",O104,F104) -> 0 | R104: =F104-O104 -> -1512 | S104: =IF(R104>=1,"OUI","NON") -> NON
B105: 100 | H105: 0 | I105: =IF(J105="","",IFERROR((CRG!P103*Q105),0)) | J105: =IF(E105="","",EDATE(E105,F105)) | K105: =IF(L105="",(IF(G105="","",ROUNDDOWN((G105-I105),0))),L105) | O105: =DATEDIF(E105,$E$3,"m") -> 1512 | P105: =IF(O105>F105,"Amorti","En_cours") -> Amorti | Q105: =IF(P105="En_cours",O105,F105) -> 0 | R105: =F105-O105 -> -1512 | S105: =IF(R105>=1,"OUI","NON") -> NON

Sheet Analyse
E2: Grille d'évaluation de l'activité
C3: Crédit Rural de Guinée
C5: Nom et Prénom du membre : | I5: =IF('Collecte des données'!I3="","",'Collecte des données'!I3) -> BARRY AISSATOU BOBO | Q5: N° membre : | S5: =IF('Collecte des données'!R3="","",'Collecte des données'!R3) -> 95240025289
K6: =Amorts!F2
C7: Date d'évaluation : | I7: =IF('Collecte des données'!D3="","",'Collecte des données'!D3) -> 46038
C9: Cycle d'affaires: | E9: =IF('Collecte des données'!I20="","",IF(OR(Analyse!I9="Modifier cycle",Analyse!I9=""),'Collecte des données'!I20,"")) | I9: Mensuelle
S10: en GNF
B11: 1. | C11: Bilan | I11: Évaluation actuelle | M11: Évaluation précédente
C12: Actif | I12: Montant (n) | M12: Montant (n-1) | Q12: Observations
C13: Immobilisations | I13: =SUM(I14:K21) -> 50000000
D14: Terrains | I14: =IF(CRG!W39="",0,CRG!W39) -> 0
D15: Bâtiments et magasin | I15: =IF(CRG!W40="",0,CRG!W40) -> 2500000
D16: Installations et agencements | I16: =IF(CRG!W41="",0,CRG!W41) -> 0
D17: Matériels industriels | I17: =IF(CRG!W42="",0,CRG!W42) -> 0
D18: Mobilier de bureau | I18: =IF(CRG!W43="",0,CRG!W43) -> 21500000
D19: Matériel informatique | I19: =IF(CRG!W44="",0,CRG!W44) -> 0
D20: Matériel de transport | I20: =IF(CRG!W45="",0,CRG!W45) -> 20000000
D21: Autres immobilisations | I21: =IF(CRG!W46="",0,CRG!W46) -> 6000000
C22: Stocks | I22: =IF(CRG!W47="",0,CRG!W47) -> 62510000
C23: Créances, Clients | I23: =IF(CRG!W48="",0,CRG!W48) -> 16500000
C24: Trésorerie (Caisse+Banque) | I24: =IF(CRG!W51="",0,CRG!W51) -> 21000000
C26: Passif | I26: Montant (n) | M26: Montant (n-1) | Q26: Observations
C27: Situation nette (Capitaux propres) | I27: =I32-(I28+I29+I30) -> 150010000
C28: Emprunt à plus d'un an | I28: =IF(CRG!W55="",0,CRG!W55) -> 0
C29: Emprunt à moins d'un an | I29: =IF(CRG!W56="",0,CRG!W56) -> 0
C30: Autres dettes | I30: =IF(CRG!W57="",0,CRG!W57) -> 0
C32: TOTAL BILAN | I32: =SUM(I13+I22+I23+I24) -> 150010000
C33: Fonds de roulement | I33: =(I27+I28)-I13 -> 100010000
C34: Besoin en fonds de roulement | I34: =I33-I24 -> 79010000
S36: en GNF
B37: 2. | C37: Rentabilité de l'activité | I37: Évaluation actuelle | M37: Évaluation précédente | Q37: Analyse du Projet
I38: Montant (n) | M38: Montant (n-1) | Q38: Montant (n+1)
C39: Chiffre d'affaires | G39: Hyp. Elev. | I39: =IF(CRG!Y16="","",IF('Collecte des données'!$I$12="Bon de commande",CRG!Y16,(CRG!Y16*CRG!AC9))) -> 441000000
C40: Coût d'achats des marchandises vendues | I40: =IF(I39="","",(I39-I41)) -> 288900000
C41: Marge brute | F41: =IF(CRG!AA5="","",CRG!AA5) -> 0.34489796 | G41: % Recom. | I41: =IF(F41="","",(CRG!W22*CRG!AC9)) -> 152100000 | M41: =M39-M40 -> 0 | Q41: =Q39-Q40 -> 0
C42: Autres charges | D42: Salaire | I42: =IF(CRG!W24="",0,IF('Collecte des données'!$I$12="Bon de commande",CRG!W24,(CRG!W24*CRG!$AC$9))) -> 520000
D43: Prélèment de l'entrepreneur | I43: =IF(CRG!W25="",0,IF('Collecte des données'!$I$12="Bon de commande",CRG!W25,(CRG!W25*CRG!$AC$9))) -> 0
D44: Loyers | I44: =IF(CRG!W26="",0,IF('Collecte des données'!$I$12="Bon de commande",CRG!W26,(CRG!W26*CRG!$AC$9))) -> 1300000
D45: Transport | I45: =IF(CRG!W27="",0,IF('Collecte des données'!$I$12="Bon de commande",CRG!W27,(CRG!W27*CRG!$AC$9))) -> 6000000
D46: Electricité, eau, téléphone | I46: =IF(CRG!W28="",0,IF('Collecte des données'!$I$12="Bon de commande",CRG!W28,(CRG!W28*CRG!$AC$9))) -> 1090000
D47: Fournitures et autres besoins | I47: =IF(CRG!W29="",0,IF('Collecte des données'!$I$12="Bon de commande",CRG!W29,(CRG!W29*CRG!$AC$9))) -> 0
D48: Entretien et réparation | I48: =IF(CRG!W30="",0,IF('Collecte des données'!$I$12="Bon de commande",CRG!W30,(CRG!W30*CRG!$AC$9))) -> 200000
D49: Carburant et lubrifiants | I49: =IF(CRG!W31="",0,IF('Collecte des données'!$I$12="Bon de commande",CRG!W31,(CRG!W31*CRG!$AC$9))) -> 720000
D50: Frais de publicité et promotion | I50: =IF(CRG!W32="",0,IF('Collecte des données'!$I$12="Bon de commande",CRG!W32,(CRG!W32*CRG!$AC$9))) -> 0
D51: Redevance, impôts et taxes | I51: =IF(CRG!W33="",0,IF('Collecte des données'!$I$12="Bon de commande",CRG!W33,(CRG!W33*CRG!$AC$9))) -> 85000
D52: Frais bancaires, Intérêts payés | I52: =IF(CRG!W34="",0,IF('Collecte des données'!$I$12="Bon de commande",CRG!W34,(CRG!W34*CRG!$AC$9))) -> 1800000
D53: Échance autre crédit | I53: =IF(CRG!W35="",0,IF('Collecte des données'!$I$12="Bon de commande",CRG!W35,(CRG!W35*CRG!$AC$9))) -> 0
D54: Diverses charges | I54: =IF(CRG!W36="",0,IF('Collecte des données'!$I$12="Bon de commande",CRG!W36,(CRG!W36*CRG!$AC$9))) -> 0
C55: Total autres charges d'exploitation | I55: =SUM(I42:L54) -> 11715000 | M55: =SUM(M42:P54) -> 0 | Q55: =SUM(Q42:T54) -> 0
D56: Amortissements et Provisions | I56: =IF('Collecte des données'!$I$12="Bon de commande",(CRG!W37+CRG!W38),((CRG!W37+CRG!W38)*CRG!AC9)) -> 614583.33
C57: Résultat d'exploitation de l'activité | I57: =I41-(I55+I56) -> 1.3977042e+08 | M57: =M41-(M55+M56) -> 0 | Q57: =Q41-(Q55+Q56) -> 0
C59: =IF(I59<0,"MANQUANT DE TRÉSORERIE","Cash-flow (Excedent de trésorerie)") -> Cash-flow (Excedent de trésorerie) | I59: =I57+I56 -> 140385000 | M59: =M57+M56 -> 0 | Q59: =Q57+Q56 -> 0
C61: Autres revenus net hors activité | I61: =IF(CRG!W60="",0,CRG!W60) -> 2500000
C63: Capacité de remboursement calculée | I63: =I59+I61 -> 142885000 | M63: =M59+M61 -> 0 | Q63: =Q59+Q61 -> 0
C65: =IFERROR(CRG!V89,"") -> La capacité de remboursement déclarée par le membre semble réaliste. Privilégiez cette CDR pour le calcul des ratios.
S67: en GNF
B68: 3. | C68: Évaluation du besoin réel en crédit
M69: Montant | Q69: Ajustement
C70: Besoins d’investissement ou Coût de l'équipement | M70: =IF('Collecte des données'!I14="","",CRG!W2)
C71: Dépenses rattachées à l’investissement | M71: =IF('Collecte des données'!I15="","",CRG!W3)
C72: Apport personnel | M72: =IF('Collecte des données'!I16="","",CRG!W4)
C73: Besoin réel en crédit investissement | M73: =IFERROR((SUM(M70:P71)-M72),"")
M75: Montant | Q75: Ajustement
C76: Coût d'achats pour 1 cycle d'exploitation) | I76: Nbre de cycle à financer | L76: 1 | M76: =IF(CRG!W65="","",CRG!Y65) -> 288900000
C77: Trésorerie disponible pour l'activité | M77: =IF(CRG!W66="","",CRG!Y66) -> 21000000
C78: Stock actuel | M78: =IF(CRG!W67="","",CRG!Y67) -> 62510000
C79: Comptes à recevoir | M79: =IF(CRG!W68="","",CRG!Y68) -> 6500000
C80: Dettes fournisseurs et autres dettes | M80: =IF(CRG!W69="","",CRG!Y69) -> 0
C81: Crédit fournisseur (Promesse) | M81: =IF(CRG!W70="","",CRG!Y70) -> 0
C82: Besoin réel en crédit exploitation | M82: =(M76+M80)-(M77+M78+M79) -> 198890000
C84: =CRG!W82 -> #VALUE!
B86: 4. | C86: Ratios de décision
C88: =IFERROR(IF(CRG!Y84<CRG!W86,"Attention !",""),"") -> Attention ! | E88: =IFERROR(IF(CRG!Y84<CRG!W86,"Cliquez ci-dessous (bleu) pour sélectionner le type de CDR",""),"") -> Cliquez ci-dessous (bleu) pour sélectionner le type de CDR | P88: Proposition - simulation
M89: Montant : | P89: 60000000
E90: Capacité de remb. calculée | M90: Durée : | P90: 12 | Q90: mois | R90: Nbre d'éch. | T90: 12
M91: Échéance : | P91: 71700000
J92: Norme
C93: =IF(E90="Capacité de remb. déclarée","R.1 Capacité de remboursement déclarée","R.1 Capacité de remboursement calculée") -> R.1 Capacité de remboursement calculée | J93: ≥ 200% | M93: Ratios calculés en fonction du montant sollicité | N93: =IF(OR('Collecte des données'!I18="",'Collecte des données'!I20="",'Collecte des données'!I23="",'Collecte des données'!I22="",'Collecte des données'!I12=""),"Information manquante",CRG!AA26) -> 2.0625523 | Q93: Ratios associés au montant proposé | R93: =IF(OR(P89="",P90="",P91="",T90="",'Collecte des données'!I12=""),"Information manquante",CRG!AB26) -> 2.0625523
C94: (Cash Flow + Autres revenus) / Traite
C97: R.2 Ratio de solvabilité | J97: ≥ 35% | N97: =IF(OR('Collecte des données'!I18="",'Collecte des données'!I20="",'Collecte des données'!I23=""),"Information manquante",CRG!AA20) -> 1 | R97: =IF(OR(P89="",P90="",P91=""),"Information manquante",CRG!AB20) -> 1
C98: Capitaux propres / Total Actif
C101: R.3 Ratio de liquidité à échéance | J101: ≥ 100% | N101: =IF(OR('Collecte des données'!I18="",'Collecte des données'!I20="",'Collecte des données'!I23=""),"Information manquante",CRG!AA21) -> Information manquante | R101: =IF(OR(P89="",P90="",P91=""),"Information manquante",CRG!AB21) -> Information manquante
C102: (Créances+Trésorerie) / Dettes à court terme
C105: R.4 Ratio d'endettement | J105: < 50% | N105: =IF(OR('Collecte des données'!I18="",'Collecte des données'!I20="",'Collecte des données'!I23=""),"Information manquante",CRG!AA22) -> 0.28570068 | R105: =IF(OR(P89="",P90="",P91=""),"Information manquante",CRG!AB22) -> 0.28570068
C106: (Dettes totales + Crédit) / (Total Actif + Crédit)
C109: R.5 Ratio de dépendance | J109: < 50% | N109: =IF(OR('Collecte des données'!I18="",'Collecte des données'!I20="",'Collecte des données'!I23=""),"Information manquante",CRG!AA23) -> 0.01757217 | R109: =IF(OR(P89="",P90="",P91=""),"Information manquante",CRG!AB23) -> 0.01757217
C110: Autres revenus / Revenus totaux
C113: R.6 Ratio de couverture de la garantie | J113: > 150% | N113: =IF(OR('Collecte des données'!I18="",'Collecte des données'!I20="",'Collecte des données'!I23="",'Collecte des données'!I24=""),"Information manquante",CRG!AA24) -> 1.7666667 | R113: =IF(OR(P89="",P90="",P91=""),"Information manquante",CRG!AB24) -> 1.7666667
C114: Valeur de la garantie / Crédit
B118: 5. | C118: Commentaire d'orientation
H124: Nom et Prénom, Date et Signature
H125: (Agent de crédit)

Sheet Avis
B2: AVIS ET DÉCISION
B3: Crédit Rural de Guinée
B5: Nom et Prénom du membre : | E5: =IF('Collecte des données'!I3="","",'Collecte des données'!I3) -> BARRY AISSATOU BOBO | M5: N° membre : | O5: =IF('Collecte des données'!R3="","",'Collecte des données'!R3) -> 95240025289
B7: Date d'évaluation : | D7: =IF('Collecte des données'!D3="","",'Collecte des données'!D3) -> 46038
B9: 1. | C9: Directeur d'agence
C11: Décision et Signature
B21: 2. | C21: Délégué Régional
C23: Décision et Signature
B32: 3. | C32: Directeur de l'exploitation
C34: Décision et Signature
B43: 4. | C43: Comité de direction
C45: Décision et Signature
